Workbook
Name prevWBS: a!$A1048576
Name prevWBS: b!$A1048576
Name prevWBS: 'bc 1'!$A1048576
Name prevWBS: 'c'!$A1048576
Name prevWBS: d!$A1048576
Name prevWBS: e!$A1048576
Name prevWBS: f!$A1048576
Name prevWBS: g!$A1048576
Name prevWBS: h!$A1048576
Name prevWBS: i!$A1048576
Name prevWBS: j!$A1048576
Name valuevx: 42.314159

Sheet Sheet3
A1: PIC | B1: Schedule Kirim tgl 04/03/26 | D1: Schedule Kirim tgl 03/03/26 | F1: Schedule Kirim tgl 02/03/26 | H1: Schedule Kirim tgl 20/02/26 | J1: Schedule Kirim tgl 04/02/26 | L1: Schedule Kirim tgl 02/02/26 | N1: Schedule Kirim tgl 12/01/26 | P1: Schedule Kirim tgl 09/01/26 | R1: Schedule Kirim tgl 23/12/25
C2: Days | E2: Days | G2: Days | I2: Days | K2: Days | M2: Days | O2: Days | Q2: Days
A3: Baim, Budi | B3: =+COUNTIF(i!$C$9:$C$60,Sheet3!A3) -> 7 | C3: =+SUMIF(i!$C$9:$C$60,Sheet3!A3,i!$I$9:$I$60) -> 60 | D3: =COUNTIF(h!$C$9:$C$74,Sheet3!A3) -> 7 | E3: =+SUMIF(h!$C$9:$C$74,Sheet3!A3,h!$I$9:$I$74) -> 60 | F3: =+COUNTIF(g!$C$7:$C$59,Sheet3!A3) -> 7 | G3: =+SUMIF(g!$C$7:$C$59,Sheet3!A3,g!$I$7:$I$59) -> 60 | H3: =+COUNTIF(f!$C$9:$C$59,Sheet3!A3) -> 7 | I3: =+SUMIF(f!$C$9:$C$59,Sheet3!A3,f!$I$9:$I$59) -> 61 | J3: =+COUNTIF(e!$C$9:$C$59,Sheet3!A3) -> 6 | K3: =+SUMIF(e!$C$9:$C$59,Sheet3!A3,e!$I$9:$I$59) -> 58 | L3: =+COUNTIF(d!$C$9:$C$58,Sheet3!A3) -> 6 | M3: =+SUMIF(d!$C$9:$C$58,Sheet3!A3,d!$I$9:$I$58) -> 58 | N3: =+COUNTIF(a!$D$7:$D$46,Sheet3!A3) -> 6 | O3: =+SUMIF(a!$D$7:$D$46,Sheet3!A3,a!$K$7:$K$46) -> 80 | P3: =+COUNTIF(b!$C$7:$C$46,Sheet3!A3) -> 6 | Q3: =+SUMIF(b!$C$7:$C$46,Sheet3!A3,b!$G$7:$G$46) -> 80 | R3: =+COUNTIF('c'!$C$7:$C$20,Sheet3!A3) -> 4
A4: Baim | B4: =+COUNTIF(i!$C$9:$C$60,Sheet3!A4) -> 14 | C4: =+SUMIF(i!$C$9:$C$60,Sheet3!A4,i!$I$9:$I$60) -> 44 | D4: =COUNTIF(h!$C$9:$C$74,Sheet3!A4) -> 20 | E4: =+SUMIF(h!$C$9:$C$74,Sheet3!A4,h!$I$9:$I$74) -> 60 | F4: =+COUNTIF(g!$C$7:$C$59,Sheet3!A4) -> 22 | G4: =+SUMIF(g!$C$7:$C$59,Sheet3!A4,g!$I$7:$I$59) -> 64 | H4: =+COUNTIF(f!$C$9:$C$59,Sheet3!A4) -> 23 | I4: =+SUMIF(f!$C$9:$C$59,Sheet3!A4,f!$I$9:$I$59) -> 63 | J4: =+COUNTIF(e!$C$9:$C$59,Sheet3!A4) -> 24 | K4: =+SUMIF(e!$C$9:$C$59,Sheet3!A4,e!$I$9:$I$59) -> 56 | L4: =+COUNTIF(d!$C$9:$C$58,Sheet3!A4) -> 23 | M4: =+SUMIF(d!$C$9:$C$58,Sheet3!A4,d!$I$9:$I$58) -> 54 | N4: =+COUNTIF(a!$D$7:$D$46,Sheet3!A4) -> 17 | O4: =+SUMIF(a!$D$7:$D$46,Sheet3!A4,a!$K$7:$K$46) -> 148 | P4: =+COUNTIF(b!$C$7:$C$46,Sheet3!A4) -> 16 | Q4: =+SUMIF(b!$C$7:$C$46,Sheet3!A4,b!$G$7:$G$46) -> 138 | R4: =+COUNTIF('c'!$C$7:$C$20,Sheet3!A4) -> 4
A5: Budi | B5: =+COUNTIF(i!$C$9:$C$60,Sheet3!A5) -> 15 | C5: =+SUMIF(i!$C$9:$C$60,Sheet3!A5,i!$I$9:$I$60) -> 38 | D5: =COUNTIF(h!$C$9:$C$74,Sheet3!A5) -> 19 | E5: =+SUMIF(h!$C$9:$C$74,Sheet3!A5,h!$I$9:$I$74) -> 46 | F5: =+COUNTIF(g!$C$7:$C$59,Sheet3!A5) -> 20 | G5: =+SUMIF(g!$C$7:$C$59,Sheet3!A5,g!$I$7:$I$59) -> 48 | H5: =+COUNTIF(f!$C$9:$C$59,Sheet3!A5) -> 21 | I5: =+SUMIF(f!$C$9:$C$59,Sheet3!A5,f!$I$9:$I$59) -> 47 | J5: =+COUNTIF(e!$C$9:$C$59,Sheet3!A5) -> 21 | K5: =+SUMIF(e!$C$9:$C$59,Sheet3!A5,e!$I$9:$I$59) -> 36 | L5: =+COUNTIF(d!$C$9:$C$58,Sheet3!A5) -> 21 | M5: =+SUMIF(d!$C$9:$C$58,Sheet3!A5,d!$I$9:$I$58) -> 36 | N5: =+COUNTIF(a!$D$7:$D$46,Sheet3!A5) -> 15 | O5: =+SUMIF(a!$D$7:$D$46,Sheet3!A5,a!$K$7:$K$46) -> 130 | P5: =+COUNTIF(b!$C$7:$C$46,Sheet3!A5) -> 16 | Q5: =+SUMIF(b!$C$7:$C$46,Sheet3!A5,b!$G$7:$G$46) -> 140 | R5: =+COUNTIF('c'!$C$7:$C$20,Sheet3!A5) -> 4
A6: Star | B6: =+COUNTIF(i!$C$9:$C$60,Sheet3!A6) -> 4 | C6: =+SUMIF(i!$C$9:$C$60,Sheet3!A6,i!$I$9:$I$60) -> 9 | D6: =COUNTIF(h!$C$9:$C$74,Sheet3!A6) -> 0 | E6: =+SUMIF(h!$C$9:$C$74,Sheet3!A6,h!$I$9:$I$74) -> 0 | F6: =+COUNTIF(g!$C$7:$C$59,Sheet3!A6) -> 1 | G6: =+SUMIF(g!$C$7:$C$59,Sheet3!A6,g!$I$7:$I$59) -> 3
A7: Jali | B7: =+COUNTIF(i!$C$9:$C$60,Sheet3!A7) -> 11 | C7: =+SUMIF(i!$C$9:$C$60,Sheet3!A7,i!$I$9:$I$60) -> 22 | D7: =COUNTIF(h!$C$9:$C$74,Sheet3!A7) -> 15 | E7: =+SUMIF(h!$C$9:$C$74,Sheet3!A7,h!$I$9:$I$74) -> 38 | F7: =+COUNTIF(g!$C$7:$C$59,Sheet3!A7) -> 1 | G7: =+SUMIF(g!$C$7:$C$59,Sheet3!A7,g!$I$7:$I$59) -> 3
A8: Baim/Star | B8: =+COUNTIF(i!$C$9:$C$60,Sheet3!A8) -> 0 | C8: =+SUMIF(i!$C$9:$C$60,Sheet3!A8,i!$I$9:$I$60) -> 0 | D8: =COUNTIF(h!$C$9:$C$74,Sheet3!A8) -> 2 | E8: =+SUMIF(h!$C$9:$C$74,Sheet3!A8,h!$I$9:$I$74) -> 4
A9: Budi/Star | B9: =+COUNTIF(i!$C$9:$C$60,Sheet3!A9) -> 0 | C9: =+SUMIF(i!$C$9:$C$60,Sheet3!A9,i!$I$9:$I$60) -> 0 | D9: =COUNTIF(h!$C$9:$C$74,Sheet3!A9) -> 2 | E9: =+SUMIF(h!$C$9:$C$74,Sheet3!A9,h!$I$9:$I$74) -> 4
A10: Baim/Jali | B10: =+COUNTIF(i!$C$9:$C$60,Sheet3!A10) -> 0 | C10: =+SUMIF(i!$C$9:$C$60,Sheet3!A10,i!$I$9:$I$60) -> 0 | D10: =COUNTIF(h!$C$9:$C$74,Sheet3!A10) -> 1 | E10: =+SUMIF(h!$C$9:$C$74,Sheet3!A10,h!$I$9:$I$74) -> 2
A11: Baim, Budi, Jali, Star | B11: =+COUNTIF(i!$C$9:$C$60,Sheet3!A11) -> 1 | C11: =+SUMIF(i!$C$9:$C$60,Sheet3!A11,i!$I$9:$I$60) -> 6
B13: =+SUM(B3:B11) -> 52 | C13: =+SUM(C3:C11) -> 179 | D13: =+SUM(D3:D10) -> 66 | E13: =+SUM(E3:E10) -> 214 | F13: =+SUM(F3:F7) -> 51 | G13: =+SUM(G3:G7) -> 178 | H13: =+SUM(H3:H5) -> 51 | I13: =+SUM(I3:I5) -> 171 | J13: =+SUM(J3:J5) -> 51 | K13: =+SUM(K3:K5) -> 150 | L13: =+SUM(L3:L5) -> 50 | M13: =+SUM(M3:M5) -> 148 | N13: =+SUM(N3:N5) -> 38 | O13: =+SUM(O3:O5) -> 358 | ... R13: =+SUM(R3:R5) -> 12
C14: =+SUM(i!I9:I60) -> 179 | E14: =+SUM(h!I9:I74) -> 214 | G14: =+SUM(g!I9:I59) -> 178 | I14: =+SUM(f!I9:I59) -> 171 | K14: =+SUM(e!I9:I59) -> 150 | M14: =+SUM(d!I8:I58) -> 148 | O14: =+SUM(a!K9:K46) -> 358 | Q14: =+SUM(b!G8:G46) -> 358
C15: =+C13-C14 -> 0 | E15: =+E13-E14 -> 0 | G15: =+G13-G14 -> 0 | I15: =+I13-I14 -> 0 | K15: =+K13-K14 -> 0 | M15: =+M13-M14 -> 0 | O15: =+O13-O14 -> 0 | Q15: =+Q13-Q14 -> 0

Sheet Memo
A1: No | B1: Tgl Terima Memo | C1: Memo Dari | D1: Kode Memo
A2: 1 | B2: 46078 | C2: BC | D2: 010/SL-AAA/LJ1/0226
A3: 2 | B3: 46078 | C3: BC | D3: 009/SL-OFF/LJ1/0126
A4: 3 | B4: 46093 | C4: BC | D4: 015/SL-AAA/LJ1/0326

Sheet ToDo
C1: Done | D1: =+COUNTIF(G:G,C1) -> 161 | H1: =NOW() -> 46111.338
C2: On Progres | D2: =+COUNTIF(G:G,C2) -> 0
C3: All | D3: =SUM(B:B) -> 163
A6: No | C6: Tgl | D6: Kategori | E6: Req | F6: Task | G6: Status | H6: Done Date | I6: Work Day
A7: 1 | B7: 1 | C7: 46048 | D7: SAP | F7: Belajar SAP (Custom Logic) | G7: Done | H7: 46048.373 | I7: =+H7-C7 -> 0.37346065
A8: =+A7+1 -> 2 | B8: 1 | C8: 46049 | D8: Tiket | F8: Tiket #DV-DT224000007044 | G8: Done | H8: 46049.373 | I8: =+H8-C8 -> 0.37346065
A9: =+A8+1 -> 3 | B9: 1 | C9: 46049 | D9: Tiket | F9: Tiket #DV-DT224000007053 | G9: Done | H9: 46049.373 | I9: =+H9-C9 -> 0.37346065
A10: =+A9+1 -> 4 | B10: 1 | C10: 46049 | D10: Memo | F10: Revisi Memo PO 79260003 (LJM) | G10: Done | H10: 46049.373 | I10: =+H10-C10 -> 0.37346065
A11: =+A10+1 -> 5 | B11: 1 | C11: 46049 | D11: Memo | F11: Revisi Memo PO 79704844 (LJU) | G11: Done | H11: 46049.373 | I11: =+H11-C11 -> 0.37346065
A12: =+A11+1 -> 6 | B12: 1 | C12: 46049 | D12: WA | E12: Bu Atin | F12: Ganti Material PR 399 (material Kelebihan) | G12: Done | H12: 46049.373 | I12: =+H12-C12 -> 0.37346065
A13: =+A12+1 -> 7 | B13: 1 | C13: 46049 | D13: WA | E13: Bu Atin | F13: PO 878 ganti purchase group | G13: Done | H13: 46049.373 | I13: =+H13-C13 -> 0.37346065
A14: =+A13+1 -> 8 | B14: 1 | C14: 46049 | D14: WA | E14: Sandi | F14: Upload stock Gd Packing (LJU) periode 26/01/26 | G14: Done | H14: 46049.373 | I14: =+H14-C14 -> 0.37346065
A15: =+A14+1 -> 9 | B15: 1 | C15: 46049 | D15: Telphone | E15: Ratna | F15: Revisi Harga PO 72600928 (LJU) | G15: Done | H15: 46049.373 | I15: =+H15-C15 -> 0.37346065
A16: =+A15+1 -> 10 | B16: 1 | C16: 46049 | D16: SAP | F16: Pull template PASSAP | G16: Done | H16: 46049.373 | I16: =+H16-C16 -> 0.37346065
A17: =+A16+1 -> 11 | B17: 1 | C17: 46049 | D17: WA | E17: Evi | F17: Ganti satuan BBK BG-2601-00002 | G17: Done | H17: 46049.373 | I17: =+H17-C17 -> 0.37346065
A18: =+A17+1 -> 12 | B18: 1 | C18: 46050 | D18: WA | E18: Evi | F18: Ganti satuan SJ G-2610073 | G18: Done | H18: 46050.381 | I18: =+H18-C18 -> 0.38063727
A19: =+A18+1 -> 13 | B19: 1 | C19: 46050 | D19: SAP | F19: Penambahan Modul Print Barcode Final | G19: Done | H19: 46051.376 | I19: =+H19-C19 -> 1.3756626
A20: =+A19+1 -> 14 | B20: 1 | C20: 46050 | D20: Langsung | E20: Kevin | F20: Cek PR 10260424, 10805832 | G20: Done | H20: 46050.446 | I20: =+H20-C20 -> 0.44550532
A21: =+A20+1 -> 15 | B21: 1 | C21: 46050 | D21: Telphone | E21: Bagus | F21: Menambah kolom inputan Gross Weight dan Nett Weight di modul print Invoice BC (khusus mesin) | G21: Done | H21: 46050.558 | I21: =+H21-C21 -> 0.5584331
A22: =+A21+1 -> 16 | B22: 1 | C22: 46050 | D22: Tiket | F22: Tiket #DV-DT24000006841 | G22: Done | H22: 46050.565 | I22: =+H22-C22 -> 0.56503264
A23: =+A22+1 -> 17 | B23: 1 | C23: 46050 | D23: WA | E23: Reza | F23: Revisi harga PO 78260301 (LJK) | G23: Done | H23: 46050.635 | I23: =+H23-C23 -> 0.63452836
A24: =+A23+1 -> 18 | B24: 1 | C24: 46050 | D24: WA | E24: Bu Yani | F24: Cek data Report Jasa LJU bulan Agustus 2025 web dan dekstop varian | G24: Done | H24: 46050.678 | I24: =+H24-C24 -> 0.67793889
A25: =+A24+1 -> 19 | B25: 1 | C25: 46050 | D25: WA | E25: Reza | F25: Revisi Harga PO 72600961 (LJU) | G25: Done | H25: 46050.681 | I25: =+H25-C25 -> 0.68099005
A26: =+A25+1 -> 20 | B26: 1 | C26: 46051 | D26: WA | E26: Bu Tati | F26: Ganti Alamat di Invoice 055/PI/JAN/2026 (LJU) Di Forward ke pa budi | G26: Done | H26: 46051.375 | I26: =+H26-C26 -> 0.3749184
A27: =+A26+1 -> 21 | B27: 1 | C27: 46051 | D27: SAP | F27: Diskusi Penarikan Data API dan data API Barcode SAP | G27: Done | H27: 46051.426 | I27: =+H27-C27 -> 0.42624907
A28: =+A27+1 -> 22 | B28: 1 | C28: 46051 | D28: WA | E28: Bu Tati | F28: Ganti Final Destination di Invoice 055/PI/JAN/2026 (LJU) | G28: Done | H28: 46051.464 | I28: =+H28-C28 -> 0.46413125
A29: =+A28+1 -> 23 | B29: 1 | C29: 46051 | D29: SAP | F29: Create Module Master PO template (belum tarik data) | G29: Done | H29: 46051.566 | I29: =+H29-C29 -> 0.56626111
A30: =+A29+1 -> 24 | B30: 1 | C30: 46052 | D30: WA | E30: Meris | F30: Perbaikan Sistem Puzzle LJM (material tidak bisa ditransaksikan) | G30: Done | H30: 46052.381 | I30: =+H30-C30 -> 0.380925
A31: =+A30+1 -> 25 | B31: 1 | C31: 46052 | D31: WA | E31: Evi | F31: Permintaan pembuatan SKEP : S-168/KBC.0903/2026 (LJK) | G31: Done | H31: 46052.416 | I31: =+H31-C31 -> 0.41579491
A32: =+A31+1 -> 26 | B32: 1 | C32: 46052 | D32: Langsung | E32: Taufik | F32: ganti pengkodean no aju BC30 per tgl 28 januari 2026 asal -014481- menjadi -LEC395- req pa taufik | G32: Done | H32: 46052.465 | I32: =+H32-C32 -> 0.46501817
A33: =+A32+1 -> 27 | B33: 1 | C33: 46052 | D33: WA | E33: Putri | F33: Revisi No AJU 000030-LEC395-20260127-000130 (LJU) | G33: Done | H33: 46052.564 | I33: =+H33-C33 -> 0.56405451
A34: =+A33+1 -> 28 | B34: 1 | C34: 46052 | D34: WA | E34: Bara | F34: ganti no aju BC 30 asal 25 karakter jadi 22 karakter, req bara | G34: Done | H34: 46052.573 | I34: =+H34-C34 -> 0.57300324
A35: =+A34+1 -> 29 | B35: 1 | C35: 46052 | D35: Telphone | E35: Visqia | F35: Data AJU BC25 tidak muncul di menu audit pengeluaran beacukai | G35: Done | H35: 46052.605 | I35: =+H35-C35 -> 0.60490521
A36: =+A35+1 -> 30 | B36: 1 | C36: 46053 | D36: SAP | F36: Mapping tabel untuk API Delivery(SJ) | G36: Done | H36: 46053.409 | I36: =+H36-C36 -> 0.40917037
A37: =+A36+1 -> 31 | B37: 1 | C37: 46053 | D37: SAP | F37: Buat UI penarikan data dari API dan insert data Master Delivery | G37: Done | H37: 46055.668 | I37: =+H37-C37 -> 2.6675463
A38: =+A37+1 -> 32 | B38: 1 | C38: 46053 | D38: WA | E38: Dini | F38: Cek reservasi 92603964 (LJU) material tidak muncul | G38: Done | H38: 46053.408 | I38: =+H38-C38 -> 0.40840856
A39: =+A38+1 -> 33 | B39: 1 | C39: 46053 | D39: WA | E39: Taufik | F39: hilangkan radiobuton TPB dan otomatis ceklis Ceisa di Update Dok Export BC req pa taufik | G39: Done | H39: 46053.493 | I39: =+H39-C39 -> 0.49273194
A40: =+A39+1 -> 34 | B40: 1 | C40: 46055 | D40: Tiket | F40: Tiket #DV-DT24000007117 (tunggu Memo) (diforward ke star) | G40: Done | H40: 46055.575 | I40: =+H40-C40 -> 0.57548565
A41: =+A40+1 -> 35 | B41: 1 | C41: 46055 | D41: WA | E41: Meris | F41: Cek Data Material LJK 4000051495 beda satuan | G41: Done | H41: 46055.424 | I41: =+H41-C41 -> 0.42407523
A42: =+A41+1 -> 36 | B42: 1 | C42: 46055 | D42: WA | E42: Bu Apri | F42: Cek Packing list LJK 003 (diforward ke pa budi) | G42: Done | H42: 46055.477 | I42: =+H42-C42 -> 0.47677002
A43: =+A42+1 -> 37 | B43: 1 | C43: 46055 | D43: Telphone | E43: Bara | F43: Doc SJ G-2600235 di pengeluaran BC kode material tidak sesuai | G43: Done | H43: 46055.56 | I43: =+H43-C43 -> 0.55959352
A44: =+A43+1 -> 38 | B44: 1 | C44: 46055 | D44: Telphone | E44: Ledy | F44: PO 79704844 belum ada penambahan PPN padahal sudah dibuatkan memonya | G44: Done | H44: 46055.589 | I44: =+H44-C44 -> 0.58903831
A45: =+A44+1 -> 39 | B45: 1 | C45: 46055 | D45: WA | E45: Evi | F45: Perbedaan Qty Kode material 1000000018 | G45: Done | H45: 46055.595 | I45: =+H45-C45 -> 0.59547141
A46: =+A45+1 -> 40 | B46: 1 | C46: 46055 | D46: WA | E46: Dea | F46: Stockoverview LJOI material 1000001877 | G46: Done | H46: 46055.618 | I46: =+H46-C46 -> 0.61773183
A47: =+A46+1 -> 41 | B47: 1 | C47: 46055 | D47: WA | E47: Evi | F47: Revisi PO 78260083 (LJK) Tambah keterangan | G47: Done | H47: 46055.626 | I47: =+H47-C47 -> 0.62587963
A48: =+A47+1 -> 42 | B48: 1 | C48: 46055 | D48: Tiket | F48: Ticket #DV-DT24000007129 | G48: Done | H48: 46055.674 | I48: =+H48-C48 -> 0.67440868
A49: =+A48+1 -> 43 | B49: 1 | C49: 46056 | D49: SAP | F49: Buat UI penarikan data dari API dan insert data Master Supplier | G49: Done | H49: 46056.426 | I49: =+H49-C49 -> 0.42613935
A50: =+A49+1 -> 44 | B50: 1 | C50: 46056 | D50: Tiket | F50: Ticket #DV-DT24000006839 (PR.10260529 ganti LS11) | G50: Done | H50: 46056.414 | I50: =+H50-C50 -> 0.41432616
A51: =+A50+1 -> 45 | B51: 1 | C51: 46056 | D51: Tiket | F51: Ticket #DV-DT24000007138 (ganti sub vendor dan nilai kontrak) | G51: Done | H51: 46056.499 | I51: =+H51-C51 -> 0.49853171
A52: =+A51+1 -> 46 | B52: 1 | C52: 46056 | D52: SAP | F52: Menambah Custom Logic di Form Invoice | G52: Done | H52: 46057.603 | I52: =+H52-C52 -> 1.6026301 | J52: Pending Lanjut lagi ke Form UI
A53: =+A52+1 -> 47 | B53: 1 | C53: 46057 | D53: SAP | F53: Buat UI penarikan data dari API dan insert data Asset | G53: Done | H53: 46057.56 | I53: =+H53-C53 -> 0.56038924
A54: =+A53+1 -> 48 | B54: 1 | C54: 46057 | D54: Telphone | E54: Bu Desi | F54: Skep 419/TPB-SK.01/KBC.0903/2026 dan 291/TPB-SK.01/KBC.0903/2026 tidak muncul saat buat BPB | G54: Done | H54: 46057.48 | I54: =+H54-C54 -> 0.48006412
A55: =+A54+1 -> 49 | B55: 1 | C55: 46057 | D55: SAP | F55: Diskusi Mapping Tabel Delivery dengan tim Soltius | G55: Done | H55: 46057.603 | I55: =+H55-C55 -> 0.60263009 | J55: Batal Tim Soltius Masih Sibuk
A56: =+A55+1 -> 50 | B56: 1 | C56: 46057 | D56: WA | E56: Putri | F56: No Invoice 088/CI/FEB/2026 (LJU) Satuan Null (minta diisi jadi Meter) | G56: Done | H56: 46057.602 | I56: =+H56-C56 -> 0.60168426
A57: =+A56+1 -> 51 | B57: 1 | C57: 46057 | D57: WA | E57: Putri | F57: No Invoice 069/PI/FEB/2026 (LJU) data ambigu | G57: Done | H57: 46057.615 | I57: =+H57-C57 -> 0.61485278
A58: =+A57+1 -> 52 | B58: 1 | C58: 46057 | D58: SAP | F58: Buat UI penarikan data dari API dan insert data PO | G58: Done | H58: 46058.599 | I58: =+H58-C58 -> 1.5993287
A59: =+A58+1 -> 53 | B59: 1 | C59: 46059 | D59: SAP | F59: Buat UI penarikan data dari API dan insert data BOM | G59: Done | H59: 46069.473 | I59: =+H59-C59 -> 10.472566 | J59: Ikut KUT dan UAT
A60: =+A59+1 -> 54 | B60: 1 | C60: 46059 | D60: Telphone | E60: Bara | F60: ubah order by laporan balance skep dari asal order by no daftar, menjadi order by tgl daftar req bara | G60: Done | H60: 46059.617 | I60: =+H60-C60 -> 0.61660289
A61: =+A60+1 -> 55 | B61: 1 | C61: 46059 | D61: Telphone | E61: Ledy | F61: Permintaan Data Vendor beserta TOPnya (LJU, LJK, LJM) | G61: Done | H61: 46059.658 | I61: =+H61-C61 -> 0.65826389
A62: =+A61+1 -> 56 | B62: 1 | C62: 46060 | D62: SAP | F62: Meeting di 234 | G62: Done | H62: 46060.437 | I62: =+H62-C62 -> 0.43650255
A63: =+A62+1 -> 57 | B63: 1 | C63: 46060 | D63: Tiket | F63: #DV-DT24000007191 ganti tgl aju dan tgl daftar asal 06-02-26 jadi 05-02-26 | G63: Done | H63: 46060.445 | I63: =+H63-C63 -> 0.44492847
A64: =+A63+1 -> 58 | B64: 1 | C64: 46060 | D64: Tiket | F64: #DV-DT24000007187 edit nilai kontrak dan SKEP | G64: Done | H64: 46060.465 | I64: =+H64-C64 -> 0.46502315
A65: =+A64+1 -> 59 | C65: 46062 | F65: TIDAK MASUK SAKIT
A66: =+A65+1 -> 60 | B66: 1 | C66: 46063 | D66: WA | E66: Visqia | F66: Material 9000000458 (LJK) tidak bisa ditransaksikan | G66: Done | H66: 46063.423 | I66: =+H66-C66 -> 0.42349178
A67: =+A66+1 -> 61 | B67: 1 | C67: 46063 | D67: Telphone | E67: Ledy | F67: Permintaan Data Vendor terbaru dari periode PO awal 2024 sampai sekarang (LJU, LJK, LJM) | G67: Done | H67: 46063.634 | I67: =+H67-C67 -> 0.63396991
A68: =+A67+1 -> 62 | B68: 1 | C68: 46063 | D68: Tiket | F68: #DV-DT24000007220 ganti no Aju dan no daftar | G68: Done | H68: 46063.646 | I68: =+H68-C68 -> 0.64619444
A69: =+A68+1 -> 63 | B69: 1 | C69: 46063 | D69: Telphone | E69: Teti | F69: Ubah No Invoice PL-2602-00049 (LJK) | G69: Done | H69: 46063.759 | I69: =+H69-C69 -> 0.75929062
A70: =+A69+1 -> 64 | B70: 1 | C70: 46064 | D70: WA | E70: Sandi | F70: Upload stock Gd Packing (LJU) periode 10/02/26 | G70: Done | H70: 46064.379 | I70: =+H70-C70 -> 0.3794213
A71: =+A70+1 -> 65 | B71: 1 | C71: 46064 | D71: WA | E71: Sandi | F71: Upload stock Gd Packing (LJU) periode 10/02/26 (rev1) | G71: Done | H71: 46064.407 | I71: =+H71-C71 -> 0.40701076
A72: =+A71+1 -> 66 | B72: 1 | C72: 46064 | D72: Telphone | E72: Ledy | F72: Permintaan Data Vendor terbaru dari periode PO awal 2024 sampai sekarang (LJU, LJK, LJM) | G72: Done | H72: 46065.364 | I72: =+H72-C72 -> 1.3635138
A73: =+A72+1 -> 67 | B73: 1 | C73: 46064 | D73: WA | E73: Meris | F73: Data SJ G-2600382 (LJU) Error saat di print | G73: Done | H73: 46064.4 | I73: =+H73-C73 -> 0.40006944
A74: =+A73+1 -> 68 | B74: 1 | C74: 46064 | D74: SAP | F74: UAT selama 3 hari dari jam 10.00 WIB sampai jam 16.00 WIB (Hari Ke-1) | G74: Done | H74: 46064.667 | I74: =+H74-C74 -> 0.66694444
A75: =+A74+1 -> 69 | B75: 1 | C75: 46065.368 | D75: Langsung | E75: Meris | F75: Menu Puzzle Dekstop PO dicancel masih muncul di PR list
A76: =+A75+1 -> 70 | B76: 1 | C76: 46065.387 | D76: Tiket | F76: #DV-DT24000007231 ganti sub vendor jadi DODO SL | G76: Done | H76: 46065.406 | I76: =+H76-C76 -> 0.019440162
A77: =+A76+1 -> 71 | B77: 1 | C77: 46065.417 | D77: SAP | F77: UAT selama 3 hari dari jam 10.00 WIB sampai jam 16.00 WIB (Hari Ke-2) | G77: Done | H77: 46065.667 | I77: =+H77-C77 -> 0.24962963
A78: =+A77+1 -> 72 | B78: 1 | C78: 46066.396 | D78: SAP | F78: UAT selama 3 hari dari jam 10.00 WIB sampai jam 16.00 WIB (Hari Ke-3) | G78: Done | H78: 46066.667 | I78: =+H78-C78 -> 0.27027778
A79: =+A78+1 -> 73 | C79: 46067 | F79: TIDAK MASUK CUTI
A80: =+A79+1 -> 74 | B80: 1 | C80: 46069.387 | D80: WA | E80: Visqia | F80: Material 7000001564 (LJU) pak kode ini di panggil di menu IV25AC ngak muncul | G80: Done | H80: 46069.395 | I80: =+H80-C80 -> 0.0082918981
A81: =+A80+1 -> 75 | B81: 1 | C81: 46069.425 | D81: Telphone | E81: Nisa | F81: Invoice 091/PI/FEB/2026 revisi gross weight dan nett weight asal 6.8 dan 6.6 menjadi 12 dan 11.4 | G81: Done | H81: 46069.425 | I81: =+H81-C81 -> 0.00025011574
A82: =+A81+1 -> 76 | B82: 1 | C82: 46069.478 | D82: SAP | F82: Melanjutkan no 52 (API baru bisa diakses tgl 13/02/26) | G82: Done | H82: 46069.55 | I82: =+H82-C82 -> 0.072058102 | J82: Pending, API masih di cek oleh pihak Soltius
A83: =+A82+1 -> 77 | B83: 1 | C83: 46069.494 | D83: WA | E83: Ibu Tina | F83: Ubah packing list PL-2602-00077 (LJU) no invoice nya asal 1258/CI/FEB/2026 menjadi 128/CI/FEB/2026 | G83: Done | H83: 46069.495 | I83: =+H83-C83 -> 0.0012921296
A84: =+A83+1 -> 78 | B84: 1 | C84: 46069.55 | D84: SAP | F84: Buat UI Report Laporan Surat Jalan (P) | G84: Done | H84: 46069.652 | I84: =+H84-C84 -> 0.1020434 | J84: Data sebagian masih ambigu (belum konfirmasi dengan pihak soltius)
A85: =+A84+1 -> 79 | B85: 1 | C85: 46069.573 | D85: SAP | F85: Diskusi dengan pihak soltius (Pa agung) tentang Batch Karakter intruksi pa Bily di showroom 2 jam 2 siang | G85: Done | H85: 46069.652 | I85: =+H85-C85 -> 0.07985706 | J85: Batal, info dari pa agus belum ada kabar lagi dari pihak soltius
A86: =+A85+1 -> 80 | B86: 1 | C86: 46069.67 | D86: SAP | F86: Diskusi dengan pihak soltius (Pa agung) tentang Batch Karakter intruksi pa Bily | G86: Done | H86: 46069.728 | I86: =+H86-C86 -> 0.057370486
A87: =+A86+1 -> 81 | B87: 1 | C87: 46071.35 | D87: SAP | F87: Melanjutkan no 43 | G87: Done | H87: 46073.594 | I87: =+H87-C87 -> 2.2446874 | J87: Pending Ada UAT poin 82
A88: =+A87+1 -> 82 | B88: 1 | C88: 46071.391 | D88: SAP | F88: UAT di gedung meting BC jam 10.00 WIB | G88: Done | H88: 46071.689 | I88: =+H88-C88 -> 0.29731273
A89: =+A88+1 -> 83 | B89: 1 | C89: 46071.403 | D89: WA | E89: Meris | F89: Reservasi 91261046 (LJK) material tidak muncul seluruhnya | G89: Done | H89: 46071.411 | I89: =+H89-C89 -> 0.0082428241
A90: =+A89+1 -> 84 | B90: 1 | C90: 46071.553 | D90: WA | E90: Evi | F90: Material 3000000113 (LJK) tidak muncul di BBK | G90: Done | H90: 46071.56 | I90: =+H90-C90 -> 0.00741875
A91: =+A90+1 -> 85 | B91: 1 | C91: 46071.562 | D91: WA | E91: Evi | F91: Create SKEP S-32/KBC.0903/2026 dan S-33/KBC.0903/2026 (LJK) | G91: Done | H91: 46071.562 | I91: =+H91-C91 -> 0.00055671296
A92: =+A91+1 -> 86 | B92: 1 | C92: 46073.595 | D92: SAP | F92: Melanjutkan no 52 (API baru bisa diakses tgl 19/02/26) | G92: Done | H92: 46074.485 | I92: =+H92-C92 -> 0.89055486 | J92: Pending API masih tidak bisa dipakai (error)
A93: =+A92+1 -> 87 | B93: 1 | C93: 46073.61 | D93: SAP | F93: Meting di Showroom 2 terkait BBK | G93: Done | H93: 46073.651 | I93: =+H93-C93 -> 0.041720486
A94: =+A93+1 -> 88 | B94: 1 | C94: 46073.625 | D94: WA | E94: Bu Tati | F94: Revisi No Invoice (LJU) asa 700/PI/FEB/2026 menjadi 100/PI/FEB/2026 | G94: Done | H94: 46073.652 | I94: =+H94-C94 -> 0.027005787
A95: =+A94+1 -> 89 | B95: 1 | C95: 46074.349 | D95: WA | E95: Bu Ade | F95: Cek data PR 11260169 (LJK) belum rilis | G95: Done | H95: 46074.391 | I95: =+H95-C95 -> 0.041562731
A96: =+A95+1 -> 90 | B96: 1 | C96: 46074.419 | D96: Tiket | F96: Ticket #DV-DT24000007302 data duplicat | G96: Done | H96: 46074.428 | I96: =+H96-C96 -> 0.0089719907
A97: =+A96+1 -> 91 | B97: 1 | C97: 46076.351 | D97: SAP | F97: Laporan Surat Jalan (P) menambahkan data BBK, SO, Invoice, Tujuan, Nama Material | G97: Done | H97: 46076.387 | I97: =+H97-C97 -> 0.036126968 | J97: Kolom penghubung dengan tabel Invoice [ReferenceSDDocument] tidak ada pada APInya
A98: =+A97+1 -> 92 | B98: 1 | C98: 46076.388 | D98: SAP | F98: LAPORAN GUDANG PACKING LEAD TIME (template) | G98: Done | H98: 46077.446 | I98: =+H98-C98 -> 1.0579734
A99: =+A98+1 -> 93 | B99: 1 | C99: 46076.421 | D99: Tiket | F99: Ticket #DV-DT24000007310 revisi atas no doc 5026003475 no aju asal 000040LEC39520260221001137 menjadi 000040LEC39520260221001138 | G99: Done | H99: 46076.432 | I99: =+H99-C99 -> 0.01106169
A100: =+A99+1 -> 94 | B100: 1 | C100: 46076.592 | D100: Telphone | E100: Taufik | F100: Menambahkan kolom LOT pada menu cek Invoice (BC) | G100: Done | H100: 46077.437 | I100: =+H100-C100 -> 0.84481586 | J100: Tunggu Memo
A101: =+A100+1 -> 95 | B101: 1 | C101: 46077.393 | D101: Telphone | E101: Bara | F101: BBK BG-2602-00072 penamaann barangnya aneh (penamaan digabung antara desc, batch, dan beam) | G101: Done | H101: 46077.395 | I101: =+H101-C101 -> 0.0019726852
A102: =+A101+1 -> 96 | B102: 1 | C102: 46077.438 | D102: WA | E102: Evi | F102: PO 78260247 sama 78260234 amount tidak muncul di laproran pembelian | G102: Done | H102: 46077.445 | I102: =+H102-C102 -> 0.0075667824
...

Sheet bc 1
A1: BC(75% BC, 25% SAP)
B4: Project Start Date | C4: 46107 | G4: Display Week | H4: 1 | K4: ="Week "&(K6-($C$4-WEEKDAY($C$4,1)+2))/7+1 -> Week 1 | R4: ="Week "&(R6-($C$4-WEEKDAY($C$4,1)+2))/7+1 -> Week 2 | Y4: ="Week "&(Y6-($C$4-WEEKDAY($C$4,1)+2))/7+1 -> Week 3 | AF4: ="Week "&(AF6-($C$4-WEEKDAY($C$4,1)+2))/7+1 -> Week 4 | AM4: ="Week "&(AM6-($C$4-WEEKDAY($C$4,1)+2))/7+1 -> Week 5 | AT4: ="Week "&(AT6-($C$4-WEEKDAY($C$4,1)+2))/7+1 -> Week 6 | BA4: ="Week "&(BA6-($C$4-WEEKDAY($C$4,1)+2))/7+1 -> Week 7 | BH4: ="Week "&(BH6-($C$4-WEEKDAY($C$4,1)+2))/7+1 -> Week 8
B5: Project Lead | C5: Billy | K5: =K6 -> 46104 | R5: =R6 -> 46111 | Y5: =Y6 -> 46118 | AF5: =AF6 -> 46125 | AM5: =AM6 -> 46132 | AT5: =AT6 -> 46139 | BA5: =BA6 -> 46146 | BH5: =BH6 -> 46153
K6: =C4-WEEKDAY(C4,1)+2+7*(H4-1) -> 46104 | L6: =K6+1 -> 46105 | M6: =L6+1 -> 46106 | N6: =M6+1 -> 46107 | O6: =N6+1 -> 46108 | P6: =O6+1 -> 46109 | Q6: =P6+1 -> 46110 | R6: =Q6+1 -> 46111 | S6: =R6+1 -> 46112 | ... BN6: =BM6+1 -> 46159
A7: WBS | B7: TASK | C7: PIC | D7: MEMO | E7: START | F7: END | G7: DAYS | H7: % DONE | I7: WORK DAYS | K7: =CHOOSE(WEEKDAY(K6,1),"S","M","T","W","T","F","S") -> M | L7: =CHOOSE(WEEKDAY(L6,1),"S","M","T","W","T","F","S") -> T | M7: =CHOOSE(WEEKDAY(M6,1),"S","M","T","W","T","F","S") -> W | N7: =CHOOSE(WEEKDAY(N6,1),"S","M","T","W","T","F","S") -> T | O7: =CHOOSE(WEEKDAY(O6,1),"S","M","T","W","T","F","S") -> F | P7: =CHOOSE(WEEKDAY(P6,1),"S","M","T","W","T","F","S") -> S | Q7: =CHOOSE(WEEKDAY(Q6,1),"S","M","T","W","T","F","S") -> S | R7: =CHOOSE(WEEKDAY(R6,1),"S","M","T","W","T","F","S") -> M | ... BN7: =CHOOSE(WEEKDAY(BN6,1),"S","M","T","W","T","F","S") -> S
A8: =IF(ISERROR(VALUE(SUBSTITUTE(prevWBS,".",""))),"1",IF(ISERROR(FIND("`",SUBSTITUTE(prevWBS,".","`",1))),TEXT(VALUE(prevWBS)+1,"#"),TEXT(VALUE(LEFT(prevWBS,FIND("`",SUBSTITUTE(prevWBS,".","`",1))-1))+1,"#"))) -> 1 | B8: BC app development | F8: =IF(ISBLANK(E8)," - ",IF(G8=0,E8,E8+G8-1)) -> - | I8: =IF(OR(F8=0,E8=0)," - ",NETWORKDAYS(E8,F8)) -> -
A9: =IF(ISERROR(VALUE(SUBSTITUTE(prevWBS,".",""))),"0.1",IF(ISERROR(FIND("`",SUBSTITUTE(prevWBS,".","`",1))),prevWBS&".1",LEFT(prevWBS,FIND("`",SUBSTITUTE(prevWBS,".","`",1)))&IF(ISERROR(FIND("`",SUBSTITUTE(prevWBS,".","`",2))),VALUE(RIGHT(prevWBS,LEN(prevWBS)-FIND("`",SUBSTITUTE(prevWBS,".","`",1))))+1,VALUE(MID(prevWBS,FIND("`",SUBSTITUTE(prevWBS,".","`",1))+1,(FIND("`",SUBSTITUTE(prevWBS,".","`",2))-FIND("`",SUBSTITUTE(prevWBS,".","`",1))-1)))+1))) -> 1.1 | B9: Menu Beacukai, Sub Menu Update Dok Keluar Market, Form Traceability Belum Ada Di MCS LJK [http://192.168.255.84/pzzl/index.php/Legal/updateKeluar2] | C9: Baim | D9: 015/SL-AAA/LJ1/0326 | E9: 46107 | F9: =IF(ISBLANK(E9)," - ",IF(G9=0,E9,E9+G9-1)) -> 46107 | G9: 1 | H9: 1 | I9: =IF(OR(F9=0,E9=0)," - ",NETWORKDAYS(E9,F9)) -> 1
A10: =IF(ISERROR(VALUE(SUBSTITUTE(prevWBS,".",""))),"0.1",IF(ISERROR(FIND("`",SUBSTITUTE(prevWBS,".","`",1))),prevWBS&".1",LEFT(prevWBS,FIND("`",SUBSTITUTE(prevWBS,".","`",1)))&IF(ISERROR(FIND("`",SUBSTITUTE(prevWBS,".","`",2))),VALUE(RIGHT(prevWBS,LEN(prevWBS)-FIND("`",SUBSTITUTE(prevWBS,".","`",1))))+1,VALUE(MID(prevWBS,FIND("`",SUBSTITUTE(prevWBS,".","`",1))+1,(FIND("`",SUBSTITUTE(prevWBS,".","`",2))-FIND("`",SUBSTITUTE(prevWBS,".","`",1))-1)))+1))) -> 1.2 | B10: Menu Beacukai, Sub Menu Update Dok Non-Keluar Market, Form Traceability Belum Ada Di MCS LJK[http://192.168.255.84/pzzl/index.php/Legal/updateKeluar] | C10: Baim | D10: 015/SL-AAA/LJ1/0326 | E10: 46107 | F10: =IF(ISBLANK(E10)," - ",IF(G10=0,E10,E10+G10-1)) -> 46107 | G10: 1 | H10: 1 | I10: =IF(OR(F10=0,E10=0)," - ",NETWORKDAYS(E10,F10)) -> 1
A11: =IF(ISERROR(VALUE(SUBSTITUTE(prevWBS,".",""))),"0.1",IF(ISERROR(FIND("`",SUBSTITUTE(prevWBS,".","`",1))),prevWBS&".1",LEFT(prevWBS,FIND("`",SUBSTITUTE(prevWBS,".","`",1)))&IF(ISERROR(FIND("`",SUBSTITUTE(prevWBS,".","`",2))),VALUE(RIGHT(prevWBS,LEN(prevWBS)-FIND("`",SUBSTITUTE(prevWBS,".","`",1))))+1,VALUE(MID(prevWBS,FIND("`",SUBSTITUTE(prevWBS,".","`",1))+1,(FIND("`",SUBSTITUTE(prevWBS,".","`",2))-FIND("`",SUBSTITUTE(prevWBS,".","`",1))-1)))+1))) -> 1.3 | B11: Menu Laporan Keluar/Masuk, Sub Menu Balance Lokal Belum Ada Di MCS LJK[http://192.168.255.84/pzzl/index.php/Legal/balancing\_local] | C11: Baim | D11: 015/SL-AAA/LJ1/0326 | E11: 46108 | F11: =IF(ISBLANK(E11)," - ",IF(G11=0,E11,E11+G11-1)) -> 46108 | G11: 1 | H11: 1 | I11: =IF(OR(F11=0,E11=0)," - ",NETWORKDAYS(E11,F11)) -> 1
A12: =IF(ISERROR(VALUE(SUBSTITUTE(prevWBS,".",""))),"0.1",IF(ISERROR(FIND("`",SUBSTITUTE(prevWBS,".","`",1))),prevWBS&".1",LEFT(prevWBS,FIND("`",SUBSTITUTE(prevWBS,".","`",1)))&IF(ISERROR(FIND("`",SUBSTITUTE(prevWBS,".","`",2))),VALUE(RIGHT(prevWBS,LEN(prevWBS)-FIND("`",SUBSTITUTE(prevWBS,".","`",1))))+1,VALUE(MID(prevWBS,FIND("`",SUBSTITUTE(prevWBS,".","`",1))+1,(FIND("`",SUBSTITUTE(prevWBS,".","`",2))-FIND("`",SUBSTITUTE(prevWBS,".","`",1))-1)))+1))) -> 1.4 | B12: Menu Print, Sub menu Packing List Dan Invoice Belum Ada Di MCS LJK [http://192.168.255.84/pzzl/index.php/Legal/packingListInvoice] | C12: Baim | D12: 015/SL-AAA/LJ1/0326 | E12: 46109 | F12: =IF(ISBLANK(E12)," - ",IF(G12=0,E12,E12+G12-1)) -> 46111 | G12: 3 | H12: 1 | I12: =IF(OR(F12=0,E12=0)," - ",NETWORKDAYS(E12,F12)) -> 1
A13: =IF(ISERROR(VALUE(SUBSTITUTE(prevWBS,".",""))),"0.1",IF(ISERROR(FIND("`",SUBSTITUTE(prevWBS,".","`",1))),prevWBS&".1",LEFT(prevWBS,FIND("`",SUBSTITUTE(prevWBS,".","`",1)))&IF(ISERROR(FIND("`",SUBSTITUTE(prevWBS,".","`",2))),VALUE(RIGHT(prevWBS,LEN(prevWBS)-FIND("`",SUBSTITUTE(prevWBS,".","`",1))))+1,VALUE(MID(prevWBS,FIND("`",SUBSTITUTE(prevWBS,".","`",1))+1,(FIND("`",SUBSTITUTE(prevWBS,".","`",2))-FIND("`",SUBSTITUTE(prevWBS,".","`",1))-1)))+1))) -> 1.5 | B13: Menu Mutasi, Sub menu Bahan Bakar Belum Ada Di IT INVENTORY LJK[http://192.168.255.84/leuwitex/beacukai/rMutBBM] | C13: Baim | D13: 015/SL-AAA/LJ1/0326 | E13: 46111 | F13: =IF(ISBLANK(E13)," - ",IF(G13=0,E13,E13+G13-1)) -> 46111 | G13: 1 | H13: 0 | I13: =IF(OR(F13=0,E13=0)," - ",NETWORKDAYS(E13,F13)) -> 1
A14: =IF(ISERROR(VALUE(SUBSTITUTE(prevWBS,".",""))),"0.1",IF(ISERROR(FIND("`",SUBSTITUTE(prevWBS,".","`",1))),prevWBS&".1",LEFT(prevWBS,FIND("`",SUBSTITUTE(prevWBS,".","`",1)))&IF(ISERROR(FIND("`",SUBSTITUTE(prevWBS,".","`",2))),VALUE(RIGHT(prevWBS,LEN(prevWBS)-FIND("`",SUBSTITUTE(prevWBS,".","`",1))))+1,VALUE(MID(prevWBS,FIND("`",SUBSTITUTE(prevWBS,".","`",1))+1,(FIND("`",SUBSTITUTE(prevWBS,".","`",2))-FIND("`",SUBSTITUTE(prevWBS,".","`",1))-1)))+1))) -> 1.6 | B14: 1a Menambah kolom : Asal Doc , No Daftar dan Tanggal daftar(/pzzl/index.php/Warehouse/laporanKeluar) | C14: Baim | D14: 142/ML-OFF/LJ1/1125 | E14: 46112 | F14: =IF(ISBLANK(E14)," - ",IF(G14=0,E14,E14+G14-1)) -> 46112 | G14: 1 | H14: 0 | I14: =IF(OR(F14=0,E14=0)," - ",NETWORKDAYS(E14,F14)) -> 1
A15: =IF(ISERROR(VALUE(SUBSTITUTE(prevWBS,".",""))),"0.1",IF(ISERROR(FIND("`",SUBSTITUTE(prevWBS,".","`",1))),prevWBS&".1",LEFT(prevWBS,FIND("`",SUBSTITUTE(prevWBS,".","`",1)))&IF(ISERROR(FIND("`",SUBSTITUTE(prevWBS,".","`",2))),VALUE(RIGHT(prevWBS,LEN(prevWBS)-FIND("`",SUBSTITUTE(prevWBS,".","`",1))))+1,VALUE(MID(prevWBS,FIND("`",SUBSTITUTE(prevWBS,".","`",1))+1,(FIND("`",SUBSTITUTE(prevWBS,".","`",2))-FIND("`",SUBSTITUTE(prevWBS,".","`",1))-1)))+1))) -> 1.7 | B15: 1b Menambah menu Edit untuk Pengisian Asal DOC, No Daftar dan Tanggal Daftar(/pzzl/index.php/Warehouse/laporanMasuk) | C15: Baim | D15: 142/ML-OFF/LJ1/1125 | E15: 46113 | F15: =IF(ISBLANK(E15)," - ",IF(G15=0,E15,E15+G15-1)) -> 46113 | G15: 1 | H15: 0 | I15: =IF(OR(F15=0,E15=0)," - ",NETWORKDAYS(E15,F15)) -> 1
A16: =IF(ISERROR(VALUE(SUBSTITUTE(prevWBS,".",""))),"0.1",IF(ISERROR(FIND("`",SUBSTITUTE(prevWBS,".","`",1))),prevWBS&".1",LEFT(prevWBS,FIND("`",SUBSTITUTE(prevWBS,".","`",1)))&IF(ISERROR(FIND("`",SUBSTITUTE(prevWBS,".","`",2))),VALUE(RIGHT(prevWBS,LEN(prevWBS)-FIND("`",SUBSTITUTE(prevWBS,".","`",1))))+1,VALUE(MID(prevWBS,FIND("`",SUBSTITUTE(prevWBS,".","`",1))+1,(FIND("`",SUBSTITUTE(prevWBS,".","`",2))-FIND("`",SUBSTITUTE(prevWBS,".","`",1))-1)))+1))) -> 1.8 | B16: 2 Belum tersedia untuk user LJK(/pzzl/index.php/MIT/dashboard) | C16: Baim | D16: 142/ML-OFF/LJ1/1125 | E16: 46114 | F16: =IF(ISBLANK(E16)," - ",IF(G16=0,E16,E16+G16-1)) -> 46114 | G16: 1 | H16: 0 | I16: =IF(OR(F16=0,E16=0)," - ",NETWORKDAYS(E16,F16)) -> 1
A17: =IF(ISERROR(VALUE(SUBSTITUTE(prevWBS,".",""))),"0.1",IF(ISERROR(FIND("`",SUBSTITUTE(prevWBS,".","`",1))),prevWBS&".1",LEFT(prevWBS,FIND("`",SUBSTITUTE(prevWBS,".","`",1)))&IF(ISERROR(FIND("`",SUBSTITUTE(prevWBS,".","`",2))),VALUE(RIGHT(prevWBS,LEN(prevWBS)-FIND("`",SUBSTITUTE(prevWBS,".","`",1))))+1,VALUE(MID(prevWBS,FIND("`",SUBSTITUTE(prevWBS,".","`",1))+1,(FIND("`",SUBSTITUTE(prevWBS,".","`",2))-FIND("`",SUBSTITUTE(prevWBS,".","`",1))-1)))+1))) -> 1.9 | B17: 3a penambahan kolom dengan nama QTY Keluar Tunggu Doc BC(/pzzl/index.php/Reporting/reportMR) | C17: Baim | D17: 142/ML-OFF/LJ1/1125 | E17: 46115 | F17: =IF(ISBLANK(E17)," - ",IF(G17=0,E17,E17+G17-1)) -> 46115 | G17: 1 | H17: 0 | I17: =IF(OR(F17=0,E17=0)," - ",NETWORKDAYS(E17,F17)) -> 1
A18: =IF(ISERROR(VALUE(SUBSTITUTE(prevWBS,".",""))),"0.1",IF(ISERROR(FIND("`",SUBSTITUTE(prevWBS,".","`",1))),prevWBS&".1",LEFT(prevWBS,FIND("`",SUBSTITUTE(prevWBS,".","`",1)))&IF(ISERROR(FIND("`",SUBSTITUTE(prevWBS,".","`",2))),VALUE(RIGHT(prevWBS,LEN(prevWBS)-FIND("`",SUBSTITUTE(prevWBS,".","`",1))))+1,VALUE(MID(prevWBS,FIND("`",SUBSTITUTE(prevWBS,".","`",1))+1,(FIND("`",SUBSTITUTE(prevWBS,".","`",2))-FIND("`",SUBSTITUTE(prevWBS,".","`",1))-1)))+1))) -> 1.10 | B18: 3b saldo buku belum berkurang jika doc bc belum terupdate(/pzzl/index.php/Reporting/reportMR) | C18: Baim | D18: 142/ML-OFF/LJ1/1125 | E18: 46116 | F18: =IF(ISBLANK(E18)," - ",IF(G18=0,E18,E18+G18-1)) -> 46116 | G18: 1 | H18: 0 | I18: =IF(OR(F18=0,E18=0)," - ",NETWORKDAYS(E18,F18)) -> 0
A19: =IF(ISERROR(VALUE(SUBSTITUTE(prevWBS,".",""))),"0.1",IF(ISERROR(FIND("`",SUBSTITUTE(prevWBS,".","`",1))),prevWBS&".1",LEFT(prevWBS,FIND("`",SUBSTITUTE(prevWBS,".","`",1)))&IF(ISERROR(FIND("`",SUBSTITUTE(prevWBS,".","`",2))),VALUE(RIGHT(prevWBS,LEN(prevWBS)-FIND("`",SUBSTITUTE(prevWBS,".","`",1))))+1,VALUE(MID(prevWBS,FIND("`",SUBSTITUTE(prevWBS,".","`",1))+1,(FIND("`",SUBSTITUTE(prevWBS,".","`",2))-FIND("`",SUBSTITUTE(prevWBS,".","`",1))-1)))+1))) -> 1.11 | B19: 4 Laporan mutasi yg muncul sesuai dengan user yang digunakan(/pzzl/index.php/Reporting/reportMR) | C19: Baim | D19: 142/ML-OFF/LJ1/1125 | E19: 46117 | F19: =IF(ISBLANK(E19)," - ",IF(G19=0,E19,E19+G19-1)) -> 46117 | G19: 1 | H19: 0 | I19: =IF(OR(F19=0,E19=0)," - ",NETWORKDAYS(E19,F19)) -> 0
A76: =IF(ISERROR(VALUE(SUBSTITUTE(prevWBS,".",""))),"1",IF(ISERROR(FIND("`",SUBSTITUTE(prevWBS,".","`",1))),TEXT(VALUE(prevWBS)+1,"#"),TEXT(VALUE(LEFT(prevWBS,FIND("`",SUBSTITUTE(prevWBS,".","`",1))-1))+1,"#"))) -> 1 | B76: Report | F76: =IF(ISBLANK(E76)," - ",IF(G76=0,E76,E76+G76-1)) -> - | I76: =IF(OR(F76=0,E76=0)," - ",NETWORKDAYS(E76,F76)) -> -
A77: =IF(ISERROR(VALUE(SUBSTITUTE(prevWBS,".",""))),"0.1",IF(ISERROR(FIND("`",SUBSTITUTE(prevWBS,".","`",1))),prevWBS&".1",LEFT(prevWBS,FIND("`",SUBSTITUTE(prevWBS,".","`",1)))&IF(ISERROR(FIND("`",SUBSTITUTE(prevWBS,".","`",2))),VALUE(RIGHT(prevWBS,LEN(prevWBS)-FIND("`",SUBSTITUTE(prevWBS,".","`",1))))+1,VALUE(MID(prevWBS,FIND("`",SUBSTITUTE(prevWBS,".","`",1))+1,(FIND("`",SUBSTITUTE(prevWBS,".","`",2))-FIND("`",SUBSTITUTE(prevWBS,".","`",1))-1)))+1))) -> 1.1 | B77: REPORT - WM - MOVING HISTORY - GUDANG GREY | C77: Billy, Baim | E77: 46057 | F77: =IF(ISBLANK(E77)," - ",IF(G77=0,E77,E77+G77-1)) -> 46063 | G77: 7 | H77: 0 | I77: =IF(OR(F77=0,E77=0)," - ",NETWORKDAYS(E77,F77)) -> 5
A78: =IF(ISERROR(VALUE(SUBSTITUTE(prevWBS,".",""))),"0.1",IF(ISERROR(FIND("`",SUBSTITUTE(prevWBS,".","`",1))),prevWBS&".1",LEFT(prevWBS,FIND("`",SUBSTITUTE(prevWBS,".","`",1)))&IF(ISERROR(FIND("`",SUBSTITUTE(prevWBS,".","`",2))),VALUE(RIGHT(prevWBS,LEN(prevWBS)-FIND("`",SUBSTITUTE(prevWBS,".","`",1))))+1,VALUE(MID(prevWBS,FIND("`",SUBSTITUTE(prevWBS,".","`",1))+1,(FIND("`",SUBSTITUTE(prevWBS,".","`",2))-FIND("`",SUBSTITUTE(prevWBS,".","`",1))-1)))+1))) -> 1.2 | B78: REPORT - WM - STOCK PER BARCODE | C78: Baim | E78: 46064 | F78: =IF(ISBLANK(E78)," - ",IF(G78=0,E78,E78+G78-1)) -> 46070 | G78: 7 | H78: 0 | I78: =IF(OR(F78=0,E78=0)," - ",NETWORKDAYS(E78,F78)) -> 5
A79: =IF(ISERROR(VALUE(SUBSTITUTE(prevWBS,".",""))),"0.1",IF(ISERROR(FIND("`",SUBSTITUTE(prevWBS,".","`",1))),prevWBS&".1",LEFT(prevWBS,FIND("`",SUBSTITUTE(prevWBS,".","`",1)))&IF(ISERROR(FIND("`",SUBSTITUTE(prevWBS,".","`",2))),VALUE(RIGHT(prevWBS,LEN(prevWBS)-FIND("`",SUBSTITUTE(prevWBS,".","`",1))))+1,VALUE(MID(prevWBS,FIND("`",SUBSTITUTE(prevWBS,".","`",1))+1,(FIND("`",SUBSTITUTE(prevWBS,".","`",2))-FIND("`",SUBSTITUTE(prevWBS,".","`",1))-1)))+1))) -> 1.3 | B79: REPORT - WM - LAPORAN PERSEDIAAN GUDANG PACKING | C79: Budi | E79: 46064 | F79: =IF(ISBLANK(E79)," - ",IF(G79=0,E79,E79+G79-1)) -> 46070 | G79: 7 | H79: 0 | I79: =IF(OR(F79=0,E79=0)," - ",NETWORKDAYS(E79,F79)) -> 5
A80: =IF(ISERROR(VALUE(SUBSTITUTE(prevWBS,".",""))),"0.1",IF(ISERROR(FIND("`",SUBSTITUTE(prevWBS,".","`",1))),prevWBS&".1",LEFT(prevWBS,FIND("`",SUBSTITUTE(prevWBS,".","`",1)))&IF(ISERROR(FIND("`",SUBSTITUTE(prevWBS,".","`",2))),VALUE(RIGHT(prevWBS,LEN(prevWBS)-FIND("`",SUBSTITUTE(prevWBS,".","`",1))))+1,VALUE(MID(prevWBS,FIND("`",SUBSTITUTE(prevWBS,".","`",1))+1,(FIND("`",SUBSTITUTE(prevWBS,".","`",2))-FIND("`",SUBSTITUTE(prevWBS,".","`",1))-1)))+1))) -> 1.4 | B80: REPORT - WM - LAPORAN GUDANG PACKING LEAD TIME | C80: Baim | E80: 46071 | F80: =IF(ISBLANK(E80)," - ",IF(G80=0,E80,E80+G80-1)) -> 46077 | G80: 7 | H80: 0 | I80: =IF(OR(F80=0,E80=0)," - ",NETWORKDAYS(E80,F80)) -> 5
A81: =IF(ISERROR(VALUE(SUBSTITUTE(prevWBS,".",""))),"0.1",IF(ISERROR(FIND("`",SUBSTITUTE(prevWBS,".","`",1))),prevWBS&".1",LEFT(prevWBS,FIND("`",SUBSTITUTE(prevWBS,".","`",1)))&IF(ISERROR(FIND("`",SUBSTITUTE(prevWBS,".","`",2))),VALUE(RIGHT(prevWBS,LEN(prevWBS)-FIND("`",SUBSTITUTE(prevWBS,".","`",1))))+1,VALUE(MID(prevWBS,FIND("`",SUBSTITUTE(prevWBS,".","`",1))+1,(FIND("`",SUBSTITUTE(prevWBS,".","`",2))-FIND("`",SUBSTITUTE(prevWBS,".","`",1))-1)))+1))) -> 1.5 | B81: REPORT - WM - LIST KARTON PER KODE ORDER | C81: Budi | E81: 46071 | F81: =IF(ISBLANK(E81)," - ",IF(G81=0,E81,E81+G81-1)) -> 46077 | G81: 7 | H81: 0 | I81: =IF(OR(F81=0,E81=0)," - ",NETWORKDAYS(E81,F81)) -> 5
A82: =IF(ISERROR(VALUE(SUBSTITUTE(prevWBS,".",""))),"0.1",IF(ISERROR(FIND("`",SUBSTITUTE(prevWBS,".","`",1))),prevWBS&".1",LEFT(prevWBS,FIND("`",SUBSTITUTE(prevWBS,".","`",1)))&IF(ISERROR(FIND("`",SUBSTITUTE(prevWBS,".","`",2))),VALUE(RIGHT(prevWBS,LEN(prevWBS)-FIND("`",SUBSTITUTE(prevWBS,".","`",1))))+1,VALUE(MID(prevWBS,FIND("`",SUBSTITUTE(prevWBS,".","`",1))+1,(FIND("`",SUBSTITUTE(prevWBS,".","`",2))-FIND("`",SUBSTITUTE(prevWBS,".","`",1))-1)))+1))) -> 1.6 | B82: REPORT - WM - MOVING HISTORY PER BARCODE | C82: Baim | E82: 46078 | F82: =IF(ISBLANK(E82)," - ",IF(G82=0,E82,E82+G82-1)) -> 46084 | G82: 7 | H82: 0 | I82: =IF(OR(F82=0,E82=0)," - ",NETWORKDAYS(E82,F82)) -> 5
A83: =IF(ISERROR(VALUE(SUBSTITUTE(prevWBS,".",""))),"0.1",IF(ISERROR(FIND("`",SUBSTITUTE(prevWBS,".","`",1))),prevWBS&".1",LEFT(prevWBS,FIND("`",SUBSTITUTE(prevWBS,".","`",1)))&IF(ISERROR(FIND("`",SUBSTITUTE(prevWBS,".","`",2))),VALUE(RIGHT(prevWBS,LEN(prevWBS)-FIND("`",SUBSTITUTE(prevWBS,".","`",1))))+1,VALUE(MID(prevWBS,FIND("`",SUBSTITUTE(prevWBS,".","`",1))+1,(FIND("`",SUBSTITUTE(prevWBS,".","`",2))-FIND("`",SUBSTITUTE(prevWBS,".","`",1))-1)))+1))) -> 1.7 | B83: REPORT - WM - MOVING HISTORY PER LIST KARTON | C83: Budi | E83: 46078 | F83: =IF(ISBLANK(E83)," - ",IF(G83=0,E83,E83+G83-1)) -> 46084 | G83: 7 | H83: 0 | I83: =IF(OR(F83=0,E83=0)," - ",NETWORKDAYS(E83,F83)) -> 5
A84: =IF(ISERROR(VALUE(SUBSTITUTE(prevWBS,".",""))),"0.1",IF(ISERROR(FIND("`",SUBSTITUTE(prevWBS,".","`",1))),prevWBS&".1",LEFT(prevWBS,FIND("`",SUBSTITUTE(prevWBS,".","`",1)))&IF(ISERROR(FIND("`",SUBSTITUTE(prevWBS,".","`",2))),VALUE(RIGHT(prevWBS,LEN(prevWBS)-FIND("`",SUBSTITUTE(prevWBS,".","`",1))))+1,VALUE(MID(prevWBS,FIND("`",SUBSTITUTE(prevWBS,".","`",1))+1,(FIND("`",SUBSTITUTE(prevWBS,".","`",2))-FIND("`",SUBSTITUTE(prevWBS,".","`",1))-1)))+1))) -> 1.8 | B84: REPORT - MM - STOCK KAIN GREY (GRADE) | C84: Billy, Budi | E84: 46057 | F84: =IF(ISBLANK(E84)," - ",IF(G84=0,E84,E84+G84-1)) -> 46063 | G84: 7 | H84: 0 | I84: =IF(OR(F84=0,E84=0)," - ",NETWORKDAYS(E84,F84)) -> 5
A85: =IF(ISERROR(VALUE(SUBSTITUTE(prevWBS,".",""))),"0.1",IF(ISERROR(FIND("`",SUBSTITUTE(prevWBS,".","`",1))),prevWBS&".1",LEFT(prevWBS,FIND("`",SUBSTITUTE(prevWBS,".","`",1)))&IF(ISERROR(FIND("`",SUBSTITUTE(prevWBS,".","`",2))),VALUE(RIGHT(prevWBS,LEN(prevWBS)-FIND("`",SUBSTITUTE(prevWBS,".","`",1))))+1,VALUE(MID(prevWBS,FIND("`",SUBSTITUTE(prevWBS,".","`",1))+1,(FIND("`",SUBSTITUTE(prevWBS,".","`",2))-FIND("`",SUBSTITUTE(prevWBS,".","`",1))-1)))+1))) -> 1.9 | B85: REPORT - MM - STOCK LEADTIME | C85: Baim | E85: 46085 | F85: =IF(ISBLANK(E85)," - ",IF(G85=0,E85,E85+G85-1)) -> 46091 | G85: 7 | H85: 0 | I85: =IF(OR(F85=0,E85=0)," - ",NETWORKDAYS(E85,F85)) -> 5
A86: =IF(ISERROR(VALUE(SUBSTITUTE(prevWBS,".",""))),"0.1",IF(ISERROR(FIND("`",SUBSTITUTE(prevWBS,".","`",1))),prevWBS&".1",LEFT(prevWBS,FIND("`",SUBSTITUTE(prevWBS,".","`",1)))&IF(ISERROR(FIND("`",SUBSTITUTE(prevWBS,".","`",2))),VALUE(RIGHT(prevWBS,LEN(prevWBS)-FIND("`",SUBSTITUTE(prevWBS,".","`",1))))+1,VALUE(MID(prevWBS,FIND("`",SUBSTITUTE(prevWBS,".","`",1))+1,(FIND("`",SUBSTITUTE(prevWBS,".","`",2))-FIND("`",SUBSTITUTE(prevWBS,".","`",1))-1)))+1))) -> 1.10 | B86: REPORT - MM - STOCK GREY LEAD TIME PER GRADE | C86: Budi | E86: 46085 | F86: =IF(ISBLANK(E86)," - ",IF(G86=0,E86,E86+G86-1)) -> 46091 | G86: 7 | H86: 0 | I86: =IF(OR(F86=0,E86=0)," - ",NETWORKDAYS(E86,F86)) -> 5
A87: =IF(ISERROR(VALUE(SUBSTITUTE(prevWBS,".",""))),"0.1",IF(ISERROR(FIND("`",SUBSTITUTE(prevWBS,".","`",1))),prevWBS&".1",LEFT(prevWBS,FIND("`",SUBSTITUTE(prevWBS,".","`",1)))&IF(ISERROR(FIND("`",SUBSTITUTE(prevWBS,".","`",2))),VALUE(RIGHT(prevWBS,LEN(prevWBS)-FIND("`",SUBSTITUTE(prevWBS,".","`",1))))+1,VALUE(MID(prevWBS,FIND("`",SUBSTITUTE(prevWBS,".","`",1))+1,(FIND("`",SUBSTITUTE(prevWBS,".","`",2))-FIND("`",SUBSTITUTE(prevWBS,".","`",1))-1)))+1))) -> 1.11 | B87: REPORT - MM - STOCK BALANCE KAIN GREY | C87: Budi | E87: 46092 | F87: =IF(ISBLANK(E87)," - ",IF(G87=0,E87,E87+G87-1)) -> 46098 | G87: 7 | H87: 0 | I87: =IF(OR(F87=0,E87=0)," - ",NETWORKDAYS(E87,F87)) -> 5
A88: =IF(ISERROR(VALUE(SUBSTITUTE(prevWBS,".",""))),"0.1",IF(ISERROR(FIND("`",SUBSTITUTE(prevWBS,".","`",1))),prevWBS&".1",LEFT(prevWBS,FIND("`",SUBSTITUTE(prevWBS,".","`",1)))&IF(ISERROR(FIND("`",SUBSTITUTE(prevWBS,".","`",2))),VALUE(RIGHT(prevWBS,LEN(prevWBS)-FIND("`",SUBSTITUTE(prevWBS,".","`",1))))+1,VALUE(MID(prevWBS,FIND("`",SUBSTITUTE(prevWBS,".","`",1))+1,(FIND("`",SUBSTITUTE(prevWBS,".","`",2))-FIND("`",SUBSTITUTE(prevWBS,".","`",1))-1)))+1))) -> 1.12 | B88: REPORT - MM - STOCK KAIN PASIF (ALL AREA) | C88: Baim | E88: 46092 | F88: =IF(ISBLANK(E88)," - ",IF(G88=0,E88,E88+G88-1)) -> 46098 | G88: 7 | H88: 0 | I88: =IF(OR(F88=0,E88=0)," - ",NETWORKDAYS(E88,F88)) -> 5
... A103: =IF(ISERROR(VALUE(SUBSTITUTE(prevWBS,".",""))),"0.1",IF(ISERROR(FIND("`",SUBSTITUTE(prevWBS,".","`",1))),prevWBS&".1",LEFT(prevWBS,FIND("`",SUBSTITUTE(prevWBS,".","`",1)))&IF(ISERROR(FIND("`",SUBSTITUTE(prevWBS,".","`",2))),VALUE(RIGHT(prevWBS,LEN(prevWBS)-FIND("`",SUBSTITUTE(prevWBS,".","`",1))))+1,VALUE(MID(prevWBS,FIND("`",SUBSTITUTE(prevWBS,".","`",1))+1,(FIND("`",SUBSTITUTE(prevWBS,".","`",2))-FIND("`",SUBSTITUTE(prevWBS,".","`",1))-1)))+1))) -> 1.27 | B103: REPORT - MM - STK Blank Gd. Packing | C103: Budi | E103: 46148 | F103: =IF(ISBLANK(E103)," - ",IF(G103=0,E103,E103+G103-1)) -> 46154 | G103: 7 | H103: 0 | I103: =IF(OR(F103=0,E103=0)," - ",NETWORKDAYS(E103,F103)) -> 5
A104: =IF(ISERROR(VALUE(SUBSTITUTE(prevWBS,".",""))),"1",IF(ISERROR(FIND("`",SUBSTITUTE(prevWBS,".","`",1))),TEXT(VALUE(prevWBS)+1,"#"),TEXT(VALUE(LEFT(prevWBS,FIND("`",SUBSTITUTE(prevWBS,".","`",1))-1))+1,"#"))) -> 2 | B104: Interfaces | F104: =IF(ISBLANK(E104)," - ",IF(G104=0,E104,E104+G104-1)) -> - | I104: =IF(OR(F104=0,E104=0)," - ",NETWORKDAYS(E104,F104)) -> -
A105: =IF(ISERROR(VALUE(SUBSTITUTE(prevWBS,".",""))),"0.1",IF(ISERROR(FIND("`",SUBSTITUTE(prevWBS,".","`",1))),prevWBS&".1",LEFT(prevWBS,FIND("`",SUBSTITUTE(prevWBS,".","`",1)))&IF(ISERROR(FIND("`",SUBSTITUTE(prevWBS,".","`",2))),VALUE(RIGHT(prevWBS,LEN(prevWBS)-FIND("`",SUBSTITUTE(prevWBS,".","`",1))))+1,VALUE(MID(prevWBS,FIND("`",SUBSTITUTE(prevWBS,".","`",1))+1,(FIND("`",SUBSTITUTE(prevWBS,".","`",2))-FIND("`",SUBSTITUTE(prevWBS,".","`",1))-1)))+1))) -> 2.1 | B105: INTERFACE BEA CUKAI | C105: Billy, Budi | E105: 46034 | F105: =IF(ISBLANK(E105)," - ",IF(G105=0,E105,E105+G105-1)) -> 46038 | G105: 5 | H105: 0 | I105: =IF(OR(F105=0,E105=0)," - ",NETWORKDAYS(E105,F105)) -> 5
A106: =IF(ISERROR(VALUE(SUBSTITUTE(prevWBS,".",""))),"0.1",IF(ISERROR(FIND("`",SUBSTITUTE(prevWBS,".","`",1))),prevWBS&".1",LEFT(prevWBS,FIND("`",SUBSTITUTE(prevWBS,".","`",1)))&IF(ISERROR(FIND("`",SUBSTITUTE(prevWBS,".","`",2))),VALUE(RIGHT(prevWBS,LEN(prevWBS)-FIND("`",SUBSTITUTE(prevWBS,".","`",1))))+1,VALUE(MID(prevWBS,FIND("`",SUBSTITUTE(prevWBS,".","`",1))+1,(FIND("`",SUBSTITUTE(prevWBS,".","`",2))-FIND("`",SUBSTITUTE(prevWBS,".","`",1))-1)))+1))) -> 2.2 | B106: INTERFACE PRINT BARCODE | C106: Billy, Baim, Budi | E106: 46023 | F106: =IF(ISBLANK(E106)," - ",IF(G106=0,E106,E106+G106-1)) -> 46032 | G106: 10 | H106: 0 | I106: 6
A107: =IF(ISERROR(VALUE(SUBSTITUTE(prevWBS,".",""))),"0.1",IF(ISERROR(FIND("`",SUBSTITUTE(prevWBS,".","`",1))),prevWBS&".1",LEFT(prevWBS,FIND("`",SUBSTITUTE(prevWBS,".","`",1)))&IF(ISERROR(FIND("`",SUBSTITUTE(prevWBS,".","`",2))),VALUE(RIGHT(prevWBS,LEN(prevWBS)-FIND("`",SUBSTITUTE(prevWBS,".","`",1))))+1,VALUE(MID(prevWBS,FIND("`",SUBSTITUTE(prevWBS,".","`",1))+1,(FIND("`",SUBSTITUTE(prevWBS,".","`",2))-FIND("`",SUBSTITUTE(prevWBS,".","`",1))-1)))+1))) -> 2.3 | B107: INTERFACE PRINT BARCODE BANYAK LIST KARTON | C107: Billy, Baim | E107: 46034 | F107: =IF(ISBLANK(E107)," - ",IF(G107=0,E107,E107+G107-1)) -> 46038 | G107: 5 | H107: 0 | I107: 5
A108: =IF(ISERROR(VALUE(SUBSTITUTE(prevWBS,".",""))),"1",IF(ISERROR(FIND("`",SUBSTITUTE(prevWBS,".","`",1))),TEXT(VALUE(prevWBS)+1,"#"),TEXT(VALUE(LEFT(prevWBS,FIND("`",SUBSTITUTE(prevWBS,".","`",1))-1))+1,"#"))) -> 3 | B108: Forms | F108: =IF(ISBLANK(E108)," - ",IF(G108=0,E108,E108+G108-1)) -> - | I108: =IF(OR(F108=0,E108=0)," - ",NETWORKDAYS(E108,F108)) -> -
A109: =IF(ISERROR(VALUE(SUBSTITUTE(prevWBS,".",""))),"0.1",IF(ISERROR(FIND("`",SUBSTITUTE(prevWBS,".","`",1))),prevWBS&".1",LEFT(prevWBS,FIND("`",SUBSTITUTE(prevWBS,".","`",1)))&IF(ISERROR(FIND("`",SUBSTITUTE(prevWBS,".","`",2))),VALUE(RIGHT(prevWBS,LEN(prevWBS)-FIND("`",SUBSTITUTE(prevWBS,".","`",1))))+1,VALUE(MID(prevWBS,FIND("`",SUBSTITUTE(prevWBS,".","`",1))+1,(FIND("`",SUBSTITUTE(prevWBS,".","`",2))-FIND("`",SUBSTITUTE(prevWBS,".","`",1))-1)))+1))) -> 3.1 | B109: Form Transfer Posting (ZSCMF001) | C109: Billy, Budi | E109: 46041 | F109: =IF(ISBLANK(E109)," - ",IF(G109=0,E109,E109+G109-1)) -> 46044 | G109: 4 | H109: 0 | I109: 4
A110: =IF(ISERROR(VALUE(SUBSTITUTE(prevWBS,".",""))),"0.1",IF(ISERROR(FIND("`",SUBSTITUTE(prevWBS,".","`",1))),prevWBS&".1",LEFT(prevWBS,FIND("`",SUBSTITUTE(prevWBS,".","`",1)))&IF(ISERROR(FIND("`",SUBSTITUTE(prevWBS,".","`",2))),VALUE(RIGHT(prevWBS,LEN(prevWBS)-FIND("`",SUBSTITUTE(prevWBS,".","`",1))))+1,VALUE(MID(prevWBS,FIND("`",SUBSTITUTE(prevWBS,".","`",1))+1,(FIND("`",SUBSTITUTE(prevWBS,".","`",2))-FIND("`",SUBSTITUTE(prevWBS,".","`",1))-1)))+1))) -> 3.2 | B110: Form Purchase Order (ZSCMF002) | C110: Billy, Baim | E110: 46041 | F110: =IF(ISBLANK(E110)," - ",IF(G110=0,E110,E110+G110-1)) -> 46044 | G110: 4 | H110: 0 | I110: 4
A111: =IF(ISERROR(VALUE(SUBSTITUTE(prevWBS,".",""))),"0.1",IF(ISERROR(FIND("`",SUBSTITUTE(prevWBS,".","`",1))),prevWBS&".1",LEFT(prevWBS,FIND("`",SUBSTITUTE(prevWBS,".","`",1)))&IF(ISERROR(FIND("`",SUBSTITUTE(prevWBS,".","`",2))),VALUE(RIGHT(prevWBS,LEN(prevWBS)-FIND("`",SUBSTITUTE(prevWBS,".","`",1))))+1,VALUE(MID(prevWBS,FIND("`",SUBSTITUTE(prevWBS,".","`",1))+1,(FIND("`",SUBSTITUTE(prevWBS,".","`",2))-FIND("`",SUBSTITUTE(prevWBS,".","`",1))-1)))+1))) -> 3.3 | B111: Form Good Receipt (ZSCMF003) | C111: Baim | E111: 46045 | F111: =IF(ISBLANK(E111)," - ",IF(G111=0,E111,E111+G111-1)) -> 46050 | G111: 6 | H111: 0 | I111: 4
A112: =IF(ISERROR(VALUE(SUBSTITUTE(prevWBS,".",""))),"0.1",IF(ISERROR(FIND("`",SUBSTITUTE(prevWBS,".","`",1))),prevWBS&".1",LEFT(prevWBS,FIND("`",SUBSTITUTE(prevWBS,".","`",1)))&IF(ISERROR(FIND("`",SUBSTITUTE(prevWBS,".","`",2))),VALUE(RIGHT(prevWBS,LEN(prevWBS)-FIND("`",SUBSTITUTE(prevWBS,".","`",1))))+1,VALUE(MID(prevWBS,FIND("`",SUBSTITUTE(prevWBS,".","`",1))+1,(FIND("`",SUBSTITUTE(prevWBS,".","`",2))-FIND("`",SUBSTITUTE(prevWBS,".","`",1))-1)))+1))) -> 3.4 | B112: Form Good Issue (ZSCMF004) | C112: Baim | E112: 46051 | F112: =IF(ISBLANK(E112)," - ",IF(G112=0,E112,E112+G112-1)) -> 46056 | G112: 6 | H112: 0 | I112: 4
A113: =IF(ISERROR(VALUE(SUBSTITUTE(prevWBS,".",""))),"0.1",IF(ISERROR(FIND("`",SUBSTITUTE(prevWBS,".","`",1))),prevWBS&".1",LEFT(prevWBS,FIND("`",SUBSTITUTE(prevWBS,".","`",1)))&IF(ISERROR(FIND("`",SUBSTITUTE(prevWBS,".","`",2))),VALUE(RIGHT(prevWBS,LEN(prevWBS)-FIND("`",SUBSTITUTE(prevWBS,".","`",1))))+1,VALUE(MID(prevWBS,FIND("`",SUBSTITUTE(prevWBS,".","`",1))+1,(FIND("`",SUBSTITUTE(prevWBS,".","`",2))-FIND("`",SUBSTITUTE(prevWBS,".","`",1))-1)))+1))) -> 3.5 | B113: Form Bukti Tanda Terima | C113: Budi | E113: 46045 | F113: =IF(ISBLANK(E113)," - ",IF(G113=0,E113,E113+G113-1)) -> 46050 | G113: 6 | H113: 0 | I113: 4
A114: =IF(ISERROR(VALUE(SUBSTITUTE(prevWBS,".",""))),"1",IF(ISERROR(FIND("`",SUBSTITUTE(prevWBS,".","`",1))),TEXT(VALUE(prevWBS)+1,"#"),TEXT(VALUE(LEFT(prevWBS,FIND("`",SUBSTITUTE(prevWBS,".","`",1))-1))+1,"#"))) -> 4 | B114: Enhancement | F114: =IF(ISBLANK(E114)," - ",IF(G114=0,E114,E114+G114-1)) -> - | I114: =IF(OR(F114=0,E114=0)," - ",NETWORKDAYS(E114,F114)) -> -
A115: =IF(ISERROR(VALUE(SUBSTITUTE(prevWBS,".",""))),"0.1",IF(ISERROR(FIND("`",SUBSTITUTE(prevWBS,".","`",1))),prevWBS&".1",LEFT(prevWBS,FIND("`",SUBSTITUTE(prevWBS,".","`",1)))&IF(ISERROR(FIND("`",SUBSTITUTE(prevWBS,".","`",2))),VALUE(RIGHT(prevWBS,LEN(prevWBS)-FIND("`",SUBSTITUTE(prevWBS,".","`",1))))+1,VALUE(MID(prevWBS,FIND("`",SUBSTITUTE(prevWBS,".","`",1))+1,(FIND("`",SUBSTITUTE(prevWBS,".","`",2))-FIND("`",SUBSTITUTE(prevWBS,".","`",1))-1)))+1))) -> 4.1 | B115: Custom field for qty in PCS at Report Stock | C115: Billy, Budi | E115: 46051 | F115: =IF(ISBLANK(E115)," - ",IF(G115=0,E115,E115+G115-1)) -> 46056 | G115: 6 | H115: 0 | I115: 4

Sheet j
A1: RICEF BY LEUWITEX ( update 17 Maret 2026 )
B4: Project Start Date | C4: 45986 | G4: Display Week | H4: 1 | K4: ="Week "&(K6-($C$4-WEEKDAY($C$4,1)+2))/7+1 -> Week 1 | R4: ="Week "&(R6-($C$4-WEEKDAY($C$4,1)+2))/7+1 -> Week 2 | Y4: ="Week "&(Y6-($C$4-WEEKDAY($C$4,1)+2))/7+1 -> Week 3 | AF4: ="Week "&(AF6-($C$4-WEEKDAY($C$4,1)+2))/7+1 -> Week 4 | AM4: ="Week "&(AM6-($C$4-WEEKDAY($C$4,1)+2))/7+1 -> Week 5 | AT4: ="Week "&(AT6-($C$4-WEEKDAY($C$4,1)+2))/7+1 -> Week 6 | BA4: ="Week "&(BA6-($C$4-WEEKDAY($C$4,1)+2))/7+1 -> Week 7 | BH4: ="Week "&(BH6-($C$4-WEEKDAY($C$4,1)+2))/7+1 -> Week 8
B5: Project Lead | C5: Billy | K5: =K6 -> 45985 | R5: =R6 -> 45992 | Y5: =Y6 -> 45999 | AF5: =AF6 -> 46006 | AM5: =AM6 -> 46013 | AT5: =AT6 -> 46020 | BA5: =BA6 -> 46027 | BH5: =BH6 -> 46034
K6: =C4-WEEKDAY(C4,1)+2+7*(H4-1) -> 45985 | L6: =K6+1 -> 45986 | M6: =L6+1 -> 45987 | N6: =M6+1 -> 45988 | O6: =N6+1 -> 45989 | P6: =O6+1 -> 45990 | Q6: =P6+1 -> 45991 | R6: =Q6+1 -> 45992 | S6: =R6+1 -> 45993 | ... BN6: =BM6+1 -> 46040
A7: WBS | B7: TASK | C7: PIC | D7: NOTES | E7: START | F7: END | G7: DAYS | H7: % DONE | I7: WORK DAYS | K7: =CHOOSE(WEEKDAY(K6,1),"S","M","T","W","T","F","S") -> M | L7: =CHOOSE(WEEKDAY(L6,1),"S","M","T","W","T","F","S") -> T | M7: =CHOOSE(WEEKDAY(M6,1),"S","M","T","W","T","F","S") -> W | N7: =CHOOSE(WEEKDAY(N6,1),"S","M","T","W","T","F","S") -> T | O7: =CHOOSE(WEEKDAY(O6,1),"S","M","T","W","T","F","S") -> F | P7: =CHOOSE(WEEKDAY(P6,1),"S","M","T","W","T","F","S") -> S | Q7: =CHOOSE(WEEKDAY(Q6,1),"S","M","T","W","T","F","S") -> S | R7: =CHOOSE(WEEKDAY(R6,1),"S","M","T","W","T","F","S") -> M | ... BN7: =CHOOSE(WEEKDAY(BN6,1),"S","M","T","W","T","F","S") -> S
A8: =IF(ISERROR(VALUE(SUBSTITUTE(prevWBS,".",""))),"1",IF(ISERROR(FIND("`",SUBSTITUTE(prevWBS,".","`",1))),TEXT(VALUE(prevWBS)+1,"#"),TEXT(VALUE(LEFT(prevWBS,FIND("`",SUBSTITUTE(prevWBS,".","`",1))-1))+1,"#"))) -> 1 | B8: SAP API development | F8: =IF(ISBLANK(E8)," - ",IF(G8=0,E8,E8+G8-1)) -> - | I8: =IF(OR(F8=0,E8=0)," - ",NETWORKDAYS(E8,F8)) -> -
A9: =IF(ISERROR(VALUE(SUBSTITUTE(prevWBS,".",""))),"0.1",IF(ISERROR(FIND("`",SUBSTITUTE(prevWBS,".","`",1))),prevWBS&".1",LEFT(prevWBS,FIND("`",SUBSTITUTE(prevWBS,".","`",1)))&IF(ISERROR(FIND("`",SUBSTITUTE(prevWBS,".","`",2))),VALUE(RIGHT(prevWBS,LEN(prevWBS)-FIND("`",SUBSTITUTE(prevWBS,".","`",1))))+1,VALUE(MID(prevWBS,FIND("`",SUBSTITUTE(prevWBS,".","`",1))+1,(FIND("`",SUBSTITUTE(prevWBS,".","`",2))-FIND("`",SUBSTITUTE(prevWBS,".","`",1))-1)))+1))) -> 1.1 | B9: INSTALL ECLIPSE, ADOBE LIFECYCLE DI PC | C9: Baim, Budi | E9: 45987 | F9: =IF(ISBLANK(E9)," - ",IF(G9=0,E9,E9+G9-1)) -> 45987 | G9: 1 | H9: 1 | I9: =IF(OR(F9=0,E9=0)," - ",NETWORKDAYS(E9,F9)) -> 1
A10: =IF(ISERROR(VALUE(SUBSTITUTE(prevWBS,".",""))),"0.1",IF(ISERROR(FIND("`",SUBSTITUTE(prevWBS,".","`",1))),prevWBS&".1",LEFT(prevWBS,FIND("`",SUBSTITUTE(prevWBS,".","`",1)))&IF(ISERROR(FIND("`",SUBSTITUTE(prevWBS,".","`",2))),VALUE(RIGHT(prevWBS,LEN(prevWBS)-FIND("`",SUBSTITUTE(prevWBS,".","`",1))))+1,VALUE(MID(prevWBS,FIND("`",SUBSTITUTE(prevWBS,".","`",1))+1,(FIND("`",SUBSTITUTE(prevWBS,".","`",2))-FIND("`",SUBSTITUTE(prevWBS,".","`",1))-1)))+1))) -> 1.2 | B10: BELAJAR KE SOLTIUS TENTANG SAP | C10: Baim, Budi | E10: 45988 | F10: =IF(ISBLANK(E10)," - ",IF(G10=0,E10,E10+G10-1)) -> 46054 | G10: 67 | H10: 0.5 | I10: =IF(OR(F10=0,E10=0)," - ",NETWORKDAYS(E10,F10)) -> 47
A11: =IF(ISERROR(VALUE(SUBSTITUTE(prevWBS,".",""))),"0.1",IF(ISERROR(FIND("`",SUBSTITUTE(prevWBS,".","`",1))),prevWBS&".1",LEFT(prevWBS,FIND("`",SUBSTITUTE(prevWBS,".","`",1)))&IF(ISERROR(FIND("`",SUBSTITUTE(prevWBS,".","`",2))),VALUE(RIGHT(prevWBS,LEN(prevWBS)-FIND("`",SUBSTITUTE(prevWBS,".","`",1))))+1,VALUE(MID(prevWBS,FIND("`",SUBSTITUTE(prevWBS,".","`",1))+1,(FIND("`",SUBSTITUTE(prevWBS,".","`",2))-FIND("`",SUBSTITUTE(prevWBS,".","`",1))-1)))+1))) -> 1.3 | B11: INTEGRASI API SAP KE PRINT BARCODE INTERNAL | C11: Baim, Budi | E11: 45995 | F11: =IF(ISBLANK(E11)," - ",IF(G11=0,E11,E11+G11-1)) -> 46001 | G11: 7 | H11: 1 | I11: =IF(OR(F11=0,E11=0)," - ",NETWORKDAYS(E11,F11)) -> 5
A12: =IF(ISERROR(VALUE(SUBSTITUTE(prevWBS,".",""))),"0.1",IF(ISERROR(FIND("`",SUBSTITUTE(prevWBS,".","`",1))),prevWBS&".1",LEFT(prevWBS,FIND("`",SUBSTITUTE(prevWBS,".","`",1)))&IF(ISERROR(FIND("`",SUBSTITUTE(prevWBS,".","`",2))),VALUE(RIGHT(prevWBS,LEN(prevWBS)-FIND("`",SUBSTITUTE(prevWBS,".","`",1))))+1,VALUE(MID(prevWBS,FIND("`",SUBSTITUTE(prevWBS,".","`",1))+1,(FIND("`",SUBSTITUTE(prevWBS,".","`",2))-FIND("`",SUBSTITUTE(prevWBS,".","`",1))-1)))+1))) -> 1.4 | B12: MAPPING IT INVENTORY | C12: Baim | E12: 46009 | F12: =IF(ISBLANK(E12)," - ",IF(G12=0,E12,E12+G12-1)) -> 46014 | G12: 6 | H12: 1 | I12: =IF(OR(F12=0,E12=0)," - ",NETWORKDAYS(E12,F12)) -> 4
A13: =IF(ISERROR(VALUE(SUBSTITUTE(prevWBS,".",""))),"0.1",IF(ISERROR(FIND("`",SUBSTITUTE(prevWBS,".","`",1))),prevWBS&".1",LEFT(prevWBS,FIND("`",SUBSTITUTE(prevWBS,".","`",1)))&IF(ISERROR(FIND("`",SUBSTITUTE(prevWBS,".","`",2))),VALUE(RIGHT(prevWBS,LEN(prevWBS)-FIND("`",SUBSTITUTE(prevWBS,".","`",1))))+1,VALUE(MID(prevWBS,FIND("`",SUBSTITUTE(prevWBS,".","`",1))+1,(FIND("`",SUBSTITUTE(prevWBS,".","`",2))-FIND("`",SUBSTITUTE(prevWBS,".","`",1))-1)))+1))) -> 1.5 | B13: BELAJAR MENDAFTARKAN API SAP | C13: Baim, Budi | E13: 46021 | F13: =IF(ISBLANK(E13)," - ",IF(G13=0,E13,E13+G13-1)) -> 46021 | G13: 1 | H13: 1 | I13: =IF(OR(F13=0,E13=0)," - ",NETWORKDAYS(E13,F13)) -> 1
A14: =IF(ISERROR(VALUE(SUBSTITUTE(prevWBS,".",""))),"0.1",IF(ISERROR(FIND("`",SUBSTITUTE(prevWBS,".","`",1))),prevWBS&".1",LEFT(prevWBS,FIND("`",SUBSTITUTE(prevWBS,".","`",1)))&IF(ISERROR(FIND("`",SUBSTITUTE(prevWBS,".","`",2))),VALUE(RIGHT(prevWBS,LEN(prevWBS)-FIND("`",SUBSTITUTE(prevWBS,".","`",1))))+1,VALUE(MID(prevWBS,FIND("`",SUBSTITUTE(prevWBS,".","`",1))+1,(FIND("`",SUBSTITUTE(prevWBS,".","`",2))-FIND("`",SUBSTITUTE(prevWBS,".","`",1))-1)))+1))) -> 1.6 | B14: MAPPING TABEL TAMBAHAN BEA CUKAI | C14: Baim | E14: 46021 | F14: =IF(ISBLANK(E14)," - ",IF(G14=0,E14,E14+G14-1)) -> 46030 | G14: 10 | H14: 1 | I14: =IF(OR(F14=0,E14=0)," - ",NETWORKDAYS(E14,F14)) -> 8
A15: =IF(ISERROR(VALUE(SUBSTITUTE(prevWBS,".",""))),"0.1",IF(ISERROR(FIND("`",SUBSTITUTE(prevWBS,".","`",1))),prevWBS&".1",LEFT(prevWBS,FIND("`",SUBSTITUTE(prevWBS,".","`",1)))&IF(ISERROR(FIND("`",SUBSTITUTE(prevWBS,".","`",2))),VALUE(RIGHT(prevWBS,LEN(prevWBS)-FIND("`",SUBSTITUTE(prevWBS,".","`",1))))+1,VALUE(MID(prevWBS,FIND("`",SUBSTITUTE(prevWBS,".","`",1))+1,(FIND("`",SUBSTITUTE(prevWBS,".","`",2))-FIND("`",SUBSTITUTE(prevWBS,".","`",1))-1)))+1))) -> 1.7 | B15: SIT | C15: Baim, Budi | E15: 46028 | F15: =IF(ISBLANK(E15)," - ",IF(G15=0,E15,E15+G15-1)) -> 46030 | G15: 3 | H15: 1 | I15: =IF(OR(F15=0,E15=0)," - ",NETWORKDAYS(E15,F15)) -> 3
A16: =IF(ISERROR(VALUE(SUBSTITUTE(prevWBS,".",""))),"0.1",IF(ISERROR(FIND("`",SUBSTITUTE(prevWBS,".","`",1))),prevWBS&".1",LEFT(prevWBS,FIND("`",SUBSTITUTE(prevWBS,".","`",1)))&IF(ISERROR(FIND("`",SUBSTITUTE(prevWBS,".","`",2))),VALUE(RIGHT(prevWBS,LEN(prevWBS)-FIND("`",SUBSTITUTE(prevWBS,".","`",1))))+1,VALUE(MID(prevWBS,FIND("`",SUBSTITUTE(prevWBS,".","`",1))+1,(FIND("`",SUBSTITUTE(prevWBS,".","`",2))-FIND("`",SUBSTITUTE(prevWBS,".","`",1))-1)))+1))) -> 1.8 | B16: INTEGRASI API SAP UNTUK BEA CUKAI | C16: Baim, Budi, Jali, Star | E16: 46031 | F16: =IF(ISBLANK(E16)," - ",IF(G16=0,E16,E16+G16-1)) -> 46040 | G16: 10 | H16: 0.5 | I16: =IF(OR(F16=0,E16=0)," - ",NETWORKDAYS(E16,F16)) -> 6
A17: =IF(ISERROR(VALUE(SUBSTITUTE(prevWBS,".",""))),"0.1",IF(ISERROR(FIND("`",SUBSTITUTE(prevWBS,".","`",1))),prevWBS&".1",LEFT(prevWBS,FIND("`",SUBSTITUTE(prevWBS,".","`",1)))&IF(ISERROR(FIND("`",SUBSTITUTE(prevWBS,".","`",2))),VALUE(RIGHT(prevWBS,LEN(prevWBS)-FIND("`",SUBSTITUTE(prevWBS,".","`",1))))+1,VALUE(MID(prevWBS,FIND("`",SUBSTITUTE(prevWBS,".","`",1))+1,(FIND("`",SUBSTITUTE(prevWBS,".","`",2))-FIND("`",SUBSTITUTE(prevWBS,".","`",1))-1)))+1))) -> 1.9 | B17: BELAJAR MENGEDIT FORM SAP | C17: Baim, Budi | E17: 46030 | F17: =IF(ISBLANK(E17)," - ",IF(G17=0,E17,E17+G17-1)) -> 46030 | G17: 1 | H17: 1 | I17: =IF(OR(F17=0,E17=0)," - ",NETWORKDAYS(E17,F17)) -> 1
A18: =IF(ISERROR(VALUE(SUBSTITUTE(prevWBS,".",""))),"0.1",IF(ISERROR(FIND("`",SUBSTITUTE(prevWBS,".","`",1))),prevWBS&".1",LEFT(prevWBS,FIND("`",SUBSTITUTE(prevWBS,".","`",1)))&IF(ISERROR(FIND("`",SUBSTITUTE(prevWBS,".","`",2))),VALUE(RIGHT(prevWBS,LEN(prevWBS)-FIND("`",SUBSTITUTE(prevWBS,".","`",1))))+1,VALUE(MID(prevWBS,FIND("`",SUBSTITUTE(prevWBS,".","`",1))+1,(FIND("`",SUBSTITUTE(prevWBS,".","`",2))-FIND("`",SUBSTITUTE(prevWBS,".","`",1))-1)))+1))) -> 1.10 | B18: KUT SAP BAGIAN MASTER DATA MM | C18: Baim | E18: 46037 | F18: =IF(ISBLANK(E18)," - ",IF(G18=0,E18,E18+G18-1)) -> 46038 | G18: 2 | H18: 1 | I18: =IF(OR(F18=0,E18=0)," - ",NETWORKDAYS(E18,F18)) -> 2
A19: =IF(ISERROR(VALUE(SUBSTITUTE(prevWBS,".",""))),"0.1",IF(ISERROR(FIND("`",SUBSTITUTE(prevWBS,".","`",1))),prevWBS&".1",LEFT(prevWBS,FIND("`",SUBSTITUTE(prevWBS,".","`",1)))&IF(ISERROR(FIND("`",SUBSTITUTE(prevWBS,".","`",2))),VALUE(RIGHT(prevWBS,LEN(prevWBS)-FIND("`",SUBSTITUTE(prevWBS,".","`",1))))+1,VALUE(MID(prevWBS,FIND("`",SUBSTITUTE(prevWBS,".","`",1))+1,(FIND("`",SUBSTITUTE(prevWBS,".","`",2))-FIND("`",SUBSTITUTE(prevWBS,".","`",1))-1)))+1))) -> 1.11 | B19: KUT SAP BAGIAN MASTER DATA SD dan FICO | C19: Budi | E19: 46037 | F19: =IF(ISBLANK(E19)," - ",IF(G19=0,E19,E19+G19-1)) -> 46038 | G19: 2 | H19: 1 | I19: =IF(OR(F19=0,E19=0)," - ",NETWORKDAYS(E19,F19)) -> 2
A20: =IF(ISERROR(VALUE(SUBSTITUTE(prevWBS,".",""))),"0.1",IF(ISERROR(FIND("`",SUBSTITUTE(prevWBS,".","`",1))),prevWBS&".1",LEFT(prevWBS,FIND("`",SUBSTITUTE(prevWBS,".","`",1)))&IF(ISERROR(FIND("`",SUBSTITUTE(prevWBS,".","`",2))),VALUE(RIGHT(prevWBS,LEN(prevWBS)-FIND("`",SUBSTITUTE(prevWBS,".","`",1))))+1,VALUE(MID(prevWBS,FIND("`",SUBSTITUTE(prevWBS,".","`",1))+1,(FIND("`",SUBSTITUTE(prevWBS,".","`",2))-FIND("`",SUBSTITUTE(prevWBS,".","`",1))-1)))+1))) -> 1.12 | B20: Modifikasi Form Invoice (Barang Bekas, Avfal, BS, Maklon, Masker) | C20: Baim | E20: 46032 | F20: =IF(ISBLANK(E20)," - ",IF(G20=0,E20,E20+G20-1)) -> 46043 | G20: 12 | H20: 1 | I20: =IF(OR(F20=0,E20=0)," - ",NETWORKDAYS(E20,F20)) -> 8
... A23: =IF(ISERROR(VALUE(SUBSTITUTE(prevWBS,".",""))),"0.1",IF(ISERROR(FIND("`",SUBSTITUTE(prevWBS,".","`",1))),prevWBS&".1",LEFT(prevWBS,FIND("`",SUBSTITUTE(prevWBS,".","`",1)))&IF(ISERROR(FIND("`",SUBSTITUTE(prevWBS,".","`",2))),VALUE(RIGHT(prevWBS,LEN(prevWBS)-FIND("`",SUBSTITUTE(prevWBS,".","`",1))))+1,VALUE(MID(prevWBS,FIND("`",SUBSTITUTE(prevWBS,".","`",1))+1,(FIND("`",SUBSTITUTE(prevWBS,".","`",2))-FIND("`",SUBSTITUTE(prevWBS,".","`",1))-1)))+1))) -> 1.15 | B23: Buat UI penarikan data dari API dan insert data Material | C23: Budi | E23: 46056 | F23: =IF(ISBLANK(E23)," - ",IF(G23=0,E23,E23+G23-1)) -> 46057 | G23: 2 | H23: 1 | I23: =IF(OR(F23=0,E23=0)," - ",NETWORKDAYS(E23,F23)) -> 2
A24: =IF(ISERROR(VALUE(SUBSTITUTE(prevWBS,".",""))),"0.1",IF(ISERROR(FIND("`",SUBSTITUTE(prevWBS,".","`",1))),prevWBS&".1",LEFT(prevWBS,FIND("`",SUBSTITUTE(prevWBS,".","`",1)))&IF(ISERROR(FIND("`",SUBSTITUTE(prevWBS,".","`",2))),VALUE(RIGHT(prevWBS,LEN(prevWBS)-FIND("`",SUBSTITUTE(prevWBS,".","`",1))))+1,VALUE(MID(prevWBS,FIND("`",SUBSTITUTE(prevWBS,".","`",1))+1,(FIND("`",SUBSTITUTE(prevWBS,".","`",2))-FIND("`",SUBSTITUTE(prevWBS,".","`",1))-1)))+1))) -> 1.16 | B24: Buat UI penarikan data dari API dan insert data Warehouse | C24: Budi | E24: =F22+1 -> 46058 | F24: =IF(ISBLANK(E24)," - ",IF(G24=0,E24,E24+G24-1)) -> 46059 | G24: 2 | H24: 1 | I24: =IF(OR(F24=0,E24=0)," - ",NETWORKDAYS(E24,F24)) -> 2
A25: =IF(ISERROR(VALUE(SUBSTITUTE(prevWBS,".",""))),"0.1",IF(ISERROR(FIND("`",SUBSTITUTE(prevWBS,".","`",1))),prevWBS&".1",LEFT(prevWBS,FIND("`",SUBSTITUTE(prevWBS,".","`",1)))&IF(ISERROR(FIND("`",SUBSTITUTE(prevWBS,".","`",2))),VALUE(RIGHT(prevWBS,LEN(prevWBS)-FIND("`",SUBSTITUTE(prevWBS,".","`",1))))+1,VALUE(MID(prevWBS,FIND("`",SUBSTITUTE(prevWBS,".","`",1))+1,(FIND("`",SUBSTITUTE(prevWBS,".","`",2))-FIND("`",SUBSTITUTE(prevWBS,".","`",1))-1)))+1))) -> 1.17 | B25: Buat UI penarikan data dari API dan insert data Asset | C25: Baim | E25: =F22+1 -> 46058 | F25: =IF(ISBLANK(E25)," - ",IF(G25=0,E25,E25+G25-1)) -> 46059 | G25: 2 | H25: 1 | I25: =IF(OR(F25=0,E25=0)," - ",NETWORKDAYS(E25,F25)) -> 2
A26: =IF(ISERROR(VALUE(SUBSTITUTE(prevWBS,".",""))),"0.1",IF(ISERROR(FIND("`",SUBSTITUTE(prevWBS,".","`",1))),prevWBS&".1",LEFT(prevWBS,FIND("`",SUBSTITUTE(prevWBS,".","`",1)))&IF(ISERROR(FIND("`",SUBSTITUTE(prevWBS,".","`",2))),VALUE(RIGHT(prevWBS,LEN(prevWBS)-FIND("`",SUBSTITUTE(prevWBS,".","`",1))))+1,VALUE(MID(prevWBS,FIND("`",SUBSTITUTE(prevWBS,".","`",1))+1,(FIND("`",SUBSTITUTE(prevWBS,".","`",2))-FIND("`",SUBSTITUTE(prevWBS,".","`",1))-1)))+1))) -> 1.18 | B26: Buat UI penarikan data dari API dan insert data Invoice | C26: Budi | E26: =E23+1 -> 46057 | F26: =IF(ISBLANK(E26)," - ",IF(G26=0,E26,E26+G26-1)) -> 46058 | G26: 2 | H26: 1 | I26: =IF(OR(F26=0,E26=0)," - ",NETWORKDAYS(E26,F26)) -> 2
A27: =IF(ISERROR(VALUE(SUBSTITUTE(prevWBS,".",""))),"0.1",IF(ISERROR(FIND("`",SUBSTITUTE(prevWBS,".","`",1))),prevWBS&".1",LEFT(prevWBS,FIND("`",SUBSTITUTE(prevWBS,".","`",1)))&IF(ISERROR(FIND("`",SUBSTITUTE(prevWBS,".","`",2))),VALUE(RIGHT(prevWBS,LEN(prevWBS)-FIND("`",SUBSTITUTE(prevWBS,".","`",1))))+1,VALUE(MID(prevWBS,FIND("`",SUBSTITUTE(prevWBS,".","`",1))+1,(FIND("`",SUBSTITUTE(prevWBS,".","`",2))-FIND("`",SUBSTITUTE(prevWBS,".","`",1))-1)))+1))) -> 1.19 | B27: Buat UI penarikan data dari API dan insert data Supplier | C27: Baim | E27: =F23+1 -> 46058 | F27: =IF(ISBLANK(E27)," - ",IF(G27=0,E27,E27+G27-1)) -> 46059 | G27: 2 | H27: 1 | I27: =IF(OR(F27=0,E27=0)," - ",NETWORKDAYS(E27,F27)) -> 2
A28: =IF(ISERROR(VALUE(SUBSTITUTE(prevWBS,".",""))),"0.1",IF(ISERROR(FIND("`",SUBSTITUTE(prevWBS,".","`",1))),prevWBS&".1",LEFT(prevWBS,FIND("`",SUBSTITUTE(prevWBS,".","`",1)))&IF(ISERROR(FIND("`",SUBSTITUTE(prevWBS,".","`",2))),VALUE(RIGHT(prevWBS,LEN(prevWBS)-FIND("`",SUBSTITUTE(prevWBS,".","`",1))))+1,VALUE(MID(prevWBS,FIND("`",SUBSTITUTE(prevWBS,".","`",1))+1,(FIND("`",SUBSTITUTE(prevWBS,".","`",2))-FIND("`",SUBSTITUTE(prevWBS,".","`",1))-1)))+1))) -> 1.20 | B28: Buat UI penarikan data dari API dan insert data Master Customer | C28: Budi | E28: =F24+1 -> 46060 | F28: =IF(ISBLANK(E28)," - ",IF(G28=0,E28,E28+G28-1)) -> 46063 | G28: 4 | H28: 1 | I28: =IF(OR(F28=0,E28=0)," - ",NETWORKDAYS(E28,F28)) -> 2
A29: =IF(ISERROR(VALUE(SUBSTITUTE(prevWBS,".",""))),"0.1",IF(ISERROR(FIND("`",SUBSTITUTE(prevWBS,".","`",1))),prevWBS&".1",LEFT(prevWBS,FIND("`",SUBSTITUTE(prevWBS,".","`",1)))&IF(ISERROR(FIND("`",SUBSTITUTE(prevWBS,".","`",2))),VALUE(RIGHT(prevWBS,LEN(prevWBS)-FIND("`",SUBSTITUTE(prevWBS,".","`",1))))+1,VALUE(MID(prevWBS,FIND("`",SUBSTITUTE(prevWBS,".","`",1))+1,(FIND("`",SUBSTITUTE(prevWBS,".","`",2))-FIND("`",SUBSTITUTE(prevWBS,".","`",1))-1)))+1))) -> 1.21 | B29: Buat UI penarikan data dari API dan insert data PO | C29: Baim | E29: =F24+1 -> 46060 | F29: =IF(ISBLANK(E29)," - ",IF(G29=0,E29,E29+G29-1)) -> 46063 | G29: 4 | H29: 1 | I29: =IF(OR(F29=0,E29=0)," - ",NETWORKDAYS(E29,F29)) -> 2
A30: =IF(ISERROR(VALUE(SUBSTITUTE(prevWBS,".",""))),"0.1",IF(ISERROR(FIND("`",SUBSTITUTE(prevWBS,".","`",1))),prevWBS&".1",LEFT(prevWBS,FIND("`",SUBSTITUTE(prevWBS,".","`",1)))&IF(ISERROR(FIND("`",SUBSTITUTE(prevWBS,".","`",2))),VALUE(RIGHT(prevWBS,LEN(prevWBS)-FIND("`",SUBSTITUTE(prevWBS,".","`",1))))+1,VALUE(MID(prevWBS,FIND("`",SUBSTITUTE(prevWBS,".","`",1))+1,(FIND("`",SUBSTITUTE(prevWBS,".","`",2))-FIND("`",SUBSTITUTE(prevWBS,".","`",1))-1)))+1))) -> 1.22 | B30: Buat UI penarikan data dari API dan insert data Material Document | C30: Budi | E30: =F28+1 -> 46064 | F30: =IF(ISBLANK(E30)," - ",IF(G30=0,E30,E30+G30-1)) -> 46065 | G30: 2 | H30: 1 | I30: =IF(OR(F30=0,E30=0)," - ",NETWORKDAYS(E30,F30)) -> 2
A31: =IF(ISERROR(VALUE(SUBSTITUTE(prevWBS,".",""))),"0.1",IF(ISERROR(FIND("`",SUBSTITUTE(prevWBS,".","`",1))),prevWBS&".1",LEFT(prevWBS,FIND("`",SUBSTITUTE(prevWBS,".","`",1)))&IF(ISERROR(FIND("`",SUBSTITUTE(prevWBS,".","`",2))),VALUE(RIGHT(prevWBS,LEN(prevWBS)-FIND("`",SUBSTITUTE(prevWBS,".","`",1))))+1,VALUE(MID(prevWBS,FIND("`",SUBSTITUTE(prevWBS,".","`",1))+1,(FIND("`",SUBSTITUTE(prevWBS,".","`",2))-FIND("`",SUBSTITUTE(prevWBS,".","`",1))-1)))+1))) -> 1.23 | B31: Buat UI penarikan data dari API dan insert data BOM | C31: Baim | E31: =F29+1 -> 46064 | F31: =IF(ISBLANK(E31)," - ",IF(G31=0,E31,E31+G31-1)) -> 46065 | G31: 2 | H31: 1 | I31: =IF(OR(F31=0,E31=0)," - ",NETWORKDAYS(E31,F31)) -> 2
A32: =IF(ISERROR(VALUE(SUBSTITUTE(prevWBS,".",""))),"0.1",IF(ISERROR(FIND("`",SUBSTITUTE(prevWBS,".","`",1))),prevWBS&".1",LEFT(prevWBS,FIND("`",SUBSTITUTE(prevWBS,".","`",1)))&IF(ISERROR(FIND("`",SUBSTITUTE(prevWBS,".","`",2))),VALUE(RIGHT(prevWBS,LEN(prevWBS)-FIND("`",SUBSTITUTE(prevWBS,".","`",1))))+1,VALUE(MID(prevWBS,FIND("`",SUBSTITUTE(prevWBS,".","`",1))+1,(FIND("`",SUBSTITUTE(prevWBS,".","`",2))-FIND("`",SUBSTITUTE(prevWBS,".","`",1))-1)))+1))) -> 1.24 | B32: UAT | C32: Baim, Budi | E32: =F30 -> 46065 | F32: =IF(ISBLANK(E32)," - ",IF(G32=0,E32,E32+G32-1)) -> 46067 | G32: 3 | H32: 1 | I32: =IF(OR(F32=0,E32=0)," - ",NETWORKDAYS(E32,F32)) -> 2
A33: =IF(ISERROR(VALUE(SUBSTITUTE(prevWBS,".",""))),"0.1",IF(ISERROR(FIND("`",SUBSTITUTE(prevWBS,".","`",1))),prevWBS&".1",LEFT(prevWBS,FIND("`",SUBSTITUTE(prevWBS,".","`",1)))&IF(ISERROR(FIND("`",SUBSTITUTE(prevWBS,".","`",2))),VALUE(RIGHT(prevWBS,LEN(prevWBS)-FIND("`",SUBSTITUTE(prevWBS,".","`",1))))+1,VALUE(MID(prevWBS,FIND("`",SUBSTITUTE(prevWBS,".","`",1))+1,(FIND("`",SUBSTITUTE(prevWBS,".","`",2))-FIND("`",SUBSTITUTE(prevWBS,".","`",1))-1)))+1))) -> 1.25 | B33: BBK INTERN | C33: Budi | E33: =F32+1 -> 46068 | F33: =IF(ISBLANK(E33)," - ",IF(G33=0,E33,E33+G33-1)) -> 46072 | G33: 5 | H33: 1 | I33: =IF(OR(F33=0,E33=0)," - ",NETWORKDAYS(E33,F33)) -> 4
A34: =IF(ISERROR(VALUE(SUBSTITUTE(prevWBS,".",""))),"0.1",IF(ISERROR(FIND("`",SUBSTITUTE(prevWBS,".","`",1))),prevWBS&".1",LEFT(prevWBS,FIND("`",SUBSTITUTE(prevWBS,".","`",1)))&IF(ISERROR(FIND("`",SUBSTITUTE(prevWBS,".","`",2))),VALUE(RIGHT(prevWBS,LEN(prevWBS)-FIND("`",SUBSTITUTE(prevWBS,".","`",1))))+1,VALUE(MID(prevWBS,FIND("`",SUBSTITUTE(prevWBS,".","`",1))+1,(FIND("`",SUBSTITUTE(prevWBS,".","`",2))-FIND("`",SUBSTITUTE(prevWBS,".","`",1))-1)))+1))) -> 1.26 | B34: LAPORAN SURAT JALAN (P) | C34: Baim | E34: =F32+1 -> 46068 | F34: =IF(ISBLANK(E34)," - ",IF(G34=0,E34,E34+G34-1)) -> 46072 | G34: 5 | H34: 0.8 | I34: =IF(OR(F34=0,E34=0)," - ",NETWORKDAYS(E34,F34)) -> 4
A35: =IF(ISERROR(VALUE(SUBSTITUTE(prevWBS,".",""))),"0.1",IF(ISERROR(FIND("`",SUBSTITUTE(prevWBS,".","`",1))),prevWBS&".1",LEFT(prevWBS,FIND("`",SUBSTITUTE(prevWBS,".","`",1)))&IF(ISERROR(FIND("`",SUBSTITUTE(prevWBS,".","`",2))),VALUE(RIGHT(prevWBS,LEN(prevWBS)-FIND("`",SUBSTITUTE(prevWBS,".","`",1))))+1,VALUE(MID(prevWBS,FIND("`",SUBSTITUTE(prevWBS,".","`",1))+1,(FIND("`",SUBSTITUTE(prevWBS,".","`",2))-FIND("`",SUBSTITUTE(prevWBS,".","`",1))-1)))+1))) -> 1.27 | B35: DETAIL LIST KARTON PER RAK | C35: Star | E35: =F33+1 -> 46073 | F35: =IF(ISBLANK(E35)," - ",IF(G35=0,E35,E35+G35-1)) -> 46076 | G35: 4 | H35: 1 | I35: =IF(OR(F35=0,E35=0)," - ",NETWORKDAYS(E35,F35)) -> 2
A36: =IF(ISERROR(VALUE(SUBSTITUTE(prevWBS,".",""))),"0.1",IF(ISERROR(FIND("`",SUBSTITUTE(prevWBS,".","`",1))),prevWBS&".1",LEFT(prevWBS,FIND("`",SUBSTITUTE(prevWBS,".","`",1)))&IF(ISERROR(FIND("`",SUBSTITUTE(prevWBS,".","`",2))),VALUE(RIGHT(prevWBS,LEN(prevWBS)-FIND("`",SUBSTITUTE(prevWBS,".","`",1))))+1,VALUE(MID(prevWBS,FIND("`",SUBSTITUTE(prevWBS,".","`",1))+1,(FIND("`",SUBSTITUTE(prevWBS,".","`",2))-FIND("`",SUBSTITUTE(prevWBS,".","`",1))-1)))+1))) -> 1.28 | B36: LAPORAN GUDANG PACKING LEAD TIME | C36: Baim | E36: =F34+1 -> 46073 | F36: =IF(ISBLANK(E36)," - ",IF(G36=0,E36,E36+G36-1)) -> 46076 | G36: 4 | H36: 1 | I36: =IF(OR(F36=0,E36=0)," - ",NETWORKDAYS(E36,F36)) -> 2
A37: =IF(ISERROR(VALUE(SUBSTITUTE(prevWBS,".",""))),"0.1",IF(ISERROR(FIND("`",SUBSTITUTE(prevWBS,".","`",1))),prevWBS&".1",LEFT(prevWBS,FIND("`",SUBSTITUTE(prevWBS,".","`",1)))&IF(ISERROR(FIND("`",SUBSTITUTE(prevWBS,".","`",2))),VALUE(RIGHT(prevWBS,LEN(prevWBS)-FIND("`",SUBSTITUTE(prevWBS,".","`",1))))+1,VALUE(MID(prevWBS,FIND("`",SUBSTITUTE(prevWBS,".","`",1))+1,(FIND("`",SUBSTITUTE(prevWBS,".","`",2))-FIND("`",SUBSTITUTE(prevWBS,".","`",1))-1)))+1))) -> 1.29 | B37: MOVING HISTORY PER LIST KARTON | C37: Star | E37: =F35+1 -> 46077 | F37: =IF(ISBLANK(E37)," - ",IF(G37=0,E37,E37+G37-1)) -> 46078 | G37: 2 | H37: 1 | I37: =IF(OR(F37=0,E37=0)," - ",NETWORKDAYS(E37,F37)) -> 2
A38: =IF(ISERROR(VALUE(SUBSTITUTE(prevWBS,".",""))),"0.1",IF(ISERROR(FIND("`",SUBSTITUTE(prevWBS,".","`",1))),prevWBS&".1",LEFT(prevWBS,FIND("`",SUBSTITUTE(prevWBS,".","`",1)))&IF(ISERROR(FIND("`",SUBSTITUTE(prevWBS,".","`",2))),VALUE(RIGHT(prevWBS,LEN(prevWBS)-FIND("`",SUBSTITUTE(prevWBS,".","`",1))))+1,VALUE(MID(prevWBS,FIND("`",SUBSTITUTE(prevWBS,".","`",1))+1,(FIND("`",SUBSTITUTE(prevWBS,".","`",2))-FIND("`",SUBSTITUTE(prevWBS,".","`",1))-1)))+1))) -> 1.30 | B38: DASHBOARD LAYOUT PER BIN | C38: Budi | E38: =F36+1 -> 46077 | F38: =IF(ISBLANK(E38)," - ",IF(G38=0,E38,E38+G38-1)) -> 46078 | G38: 2 | H38: 0 | I38: =IF(OR(F38=0,E38=0)," - ",NETWORKDAYS(E38,F38)) -> 2
A39: =IF(ISERROR(VALUE(SUBSTITUTE(prevWBS,".",""))),"0.1",IF(ISERROR(FIND("`",SUBSTITUTE(prevWBS,".","`",1))),prevWBS&".1",LEFT(prevWBS,FIND("`",SUBSTITUTE(prevWBS,".","`",1)))&IF(ISERROR(FIND("`",SUBSTITUTE(prevWBS,".","`",2))),VALUE(RIGHT(prevWBS,LEN(prevWBS)-FIND("`",SUBSTITUTE(prevWBS,".","`",1))))+1,VALUE(MID(prevWBS,FIND("`",SUBSTITUTE(prevWBS,".","`",1))+1,(FIND("`",SUBSTITUTE(prevWBS,".","`",2))-FIND("`",SUBSTITUTE(prevWBS,".","`",1))-1)))+1))) -> 1.31 | B39: LAPORAN SURAT JALAN SLOC | C39: Star, Baim | E39: =F37+1 -> 46079 | F39: =IF(ISBLANK(E39)," - ",IF(G39=0,E39,E39+G39-1)) -> 46080 | G39: 2 | H39: 0.8 | I39: =IF(OR(F39=0,E39=0)," - ",NETWORKDAYS(E39,F39)) -> 2
A40: =IF(ISERROR(VALUE(SUBSTITUTE(prevWBS,".",""))),"0.1",IF(ISERROR(FIND("`",SUBSTITUTE(prevWBS,".","`",1))),prevWBS&".1",LEFT(prevWBS,FIND("`",SUBSTITUTE(prevWBS,".","`",1)))&IF(ISERROR(FIND("`",SUBSTITUTE(prevWBS,".","`",2))),VALUE(RIGHT(prevWBS,LEN(prevWBS)-FIND("`",SUBSTITUTE(prevWBS,".","`",1))))+1,VALUE(MID(prevWBS,FIND("`",SUBSTITUTE(prevWBS,".","`",1))+1,(FIND("`",SUBSTITUTE(prevWBS,".","`",2))-FIND("`",SUBSTITUTE(prevWBS,".","`",1))-1)))+1))) -> 1.32 | B40: LIST KARTON PER KODE ORDER | C40: Baim | E40: =F38+1 -> 46079 | F40: =IF(ISBLANK(E40)," - ",IF(G40=0,E40,E40+G40-1)) -> 46080 | G40: 2 | H40: 1 | I40: =IF(OR(F40=0,E40=0)," - ",NETWORKDAYS(E40,F40)) -> 2
A41: =IF(ISERROR(VALUE(SUBSTITUTE(prevWBS,".",""))),"0.1",IF(ISERROR(FIND("`",SUBSTITUTE(prevWBS,".","`",1))),prevWBS&".1",LEFT(prevWBS,FIND("`",SUBSTITUTE(prevWBS,".","`",1)))&IF(ISERROR(FIND("`",SUBSTITUTE(prevWBS,".","`",2))),VALUE(RIGHT(prevWBS,LEN(prevWBS)-FIND("`",SUBSTITUTE(prevWBS,".","`",1))))+1,VALUE(MID(prevWBS,FIND("`",SUBSTITUTE(prevWBS,".","`",1))+1,(FIND("`",SUBSTITUTE(prevWBS,".","`",2))-FIND("`",SUBSTITUTE(prevWBS,".","`",1))-1)))+1))) -> 1.33 | B41: LIST STK INTERN DAN EXTERN | C41: Jali | E41: =F39+1 -> 46081 | F41: =IF(ISBLANK(E41)," - ",IF(G41=0,E41,E41+G41-1)) -> 46084 | G41: 4 | H41: 1 | I41: =IF(OR(F41=0,E41=0)," - ",NETWORKDAYS(E41,F41)) -> 2
A42: =IF(ISERROR(VALUE(SUBSTITUTE(prevWBS,".",""))),"0.1",IF(ISERROR(FIND("`",SUBSTITUTE(prevWBS,".","`",1))),prevWBS&".1",LEFT(prevWBS,FIND("`",SUBSTITUTE(prevWBS,".","`",1)))&IF(ISERROR(FIND("`",SUBSTITUTE(prevWBS,".","`",2))),VALUE(RIGHT(prevWBS,LEN(prevWBS)-FIND("`",SUBSTITUTE(prevWBS,".","`",1))))+1,VALUE(MID(prevWBS,FIND("`",SUBSTITUTE(prevWBS,".","`",1))+1,(FIND("`",SUBSTITUTE(prevWBS,".","`",2))-FIND("`",SUBSTITUTE(prevWBS,".","`",1))-1)))+1))) -> 1.34 | B42: MONITORING KAIN GREY | C42: Budi | E42: =F40+1 -> 46081 | F42: =IF(ISBLANK(E42)," - ",IF(G42=0,E42,E42+G42-1)) -> 46084 | G42: 4 | H42: 0 | I42: =IF(OR(F42=0,E42=0)," - ",NETWORKDAYS(E42,F42)) -> 2
A43: =IF(ISERROR(VALUE(SUBSTITUTE(prevWBS,".",""))),"0.1",IF(ISERROR(FIND("`",SUBSTITUTE(prevWBS,".","`",1))),prevWBS&".1",LEFT(prevWBS,FIND("`",SUBSTITUTE(prevWBS,".","`",1)))&IF(ISERROR(FIND("`",SUBSTITUTE(prevWBS,".","`",2))),VALUE(RIGHT(prevWBS,LEN(prevWBS)-FIND("`",SUBSTITUTE(prevWBS,".","`",1))))+1,VALUE(MID(prevWBS,FIND("`",SUBSTITUTE(prevWBS,".","`",1))+1,(FIND("`",SUBSTITUTE(prevWBS,".","`",2))-FIND("`",SUBSTITUTE(prevWBS,".","`",1))-1)))+1))) -> 1.35 | B43: LAPORAN PERSEDIAAN GUDANG PACKING | C43: Star | E43: =F41 -> 46084 | F43: =IF(ISBLANK(E43)," - ",IF(G43=0,E43,E43+G43-1)) -> 46086 | G43: 3 | H43: 1 | I43: =IF(OR(F43=0,E43=0)," - ",NETWORKDAYS(E43,F43)) -> 3
A44: =IF(ISERROR(VALUE(SUBSTITUTE(prevWBS,".",""))),"0.1",IF(ISERROR(FIND("`",SUBSTITUTE(prevWBS,".","`",1))),prevWBS&".1",LEFT(prevWBS,FIND("`",SUBSTITUTE(prevWBS,".","`",1)))&IF(ISERROR(FIND("`",SUBSTITUTE(prevWBS,".","`",2))),VALUE(RIGHT(prevWBS,LEN(prevWBS)-FIND("`",SUBSTITUTE(prevWBS,".","`",1))))+1,VALUE(MID(prevWBS,FIND("`",SUBSTITUTE(prevWBS,".","`",1))+1,(FIND("`",SUBSTITUTE(prevWBS,".","`",2))-FIND("`",SUBSTITUTE(prevWBS,".","`",1))-1)))+1))) -> 1.36 | B44: STOCK PER BARCODE | C44: Jali | E44: =F42 -> 46084 | F44: =IF(ISBLANK(E44)," - ",IF(G44=0,E44,E44+G44-1)) -> 46086 | G44: 3 | H44: 1 | I44: =IF(OR(F44=0,E44=0)," - ",NETWORKDAYS(E44,F44)) -> 3
A45: =IF(ISERROR(VALUE(SUBSTITUTE(prevWBS,".",""))),"0.1",IF(ISERROR(FIND("`",SUBSTITUTE(prevWBS,".","`",1))),prevWBS&".1",LEFT(prevWBS,FIND("`",SUBSTITUTE(prevWBS,".","`",1)))&IF(ISERROR(FIND("`",SUBSTITUTE(prevWBS,".","`",2))),VALUE(RIGHT(prevWBS,LEN(prevWBS)-FIND("`",SUBSTITUTE(prevWBS,".","`",1))))+1,VALUE(MID(prevWBS,FIND("`",SUBSTITUTE(prevWBS,".","`",1))+1,(FIND("`",SUBSTITUTE(prevWBS,".","`",2))-FIND("`",SUBSTITUTE(prevWBS,".","`",1))-1)))+1))) -> 1.37 | B45: Buat UI penarikan data dari API dan insert data Reservasi | C45: Jali | E45: =F41+3 -> 46087 | F45: =IF(ISBLANK(E45)," - ",IF(G45=0,E45,E45+G45-1)) -> 46088 | G45: 2 | H45: 1 | I45: =IF(OR(F45=0,E45=0)," - ",NETWORKDAYS(E45,F45)) -> 1
A46: =IF(ISERROR(VALUE(SUBSTITUTE(prevWBS,".",""))),"0.1",IF(ISERROR(FIND("`",SUBSTITUTE(prevWBS,".","`",1))),prevWBS&".1",LEFT(prevWBS,FIND("`",SUBSTITUTE(prevWBS,".","`",1)))&IF(ISERROR(FIND("`",SUBSTITUTE(prevWBS,".","`",2))),VALUE(RIGHT(prevWBS,LEN(prevWBS)-FIND("`",SUBSTITUTE(prevWBS,".","`",1))))+1,VALUE(MID(prevWBS,FIND("`",SUBSTITUTE(prevWBS,".","`",1))+1,(FIND("`",SUBSTITUTE(prevWBS,".","`",2))-FIND("`",SUBSTITUTE(prevWBS,".","`",1))-1)))+1))) -> 1.38 | B46: REPORT CANCEL KAIN KELUAR(TIDAK DIBUAT) | C46: Budi | E46: =F43+1 -> 46087 | F46: =IF(ISBLANK(E46)," - ",IF(G46=0,E46,E46+G46-1)) -> 46090 | G46: 4 | H46: CANCEL | I46: =IF(OR(F46=0,E46=0)," - ",NETWORKDAYS(E46,F46)) -> 2
A47: =IF(ISERROR(VALUE(SUBSTITUTE(prevWBS,".",""))),"0.1",IF(ISERROR(FIND("`",SUBSTITUTE(prevWBS,".","`",1))),prevWBS&".1",LEFT(prevWBS,FIND("`",SUBSTITUTE(prevWBS,".","`",1)))&IF(ISERROR(FIND("`",SUBSTITUTE(prevWBS,".","`",2))),VALUE(RIGHT(prevWBS,LEN(prevWBS)-FIND("`",SUBSTITUTE(prevWBS,".","`",1))))+1,VALUE(MID(prevWBS,FIND("`",SUBSTITUTE(prevWBS,".","`",1))+1,(FIND("`",SUBSTITUTE(prevWBS,".","`",2))-FIND("`",SUBSTITUTE(prevWBS,".","`",1))-1)))+1))) -> 1.39 | B47: REPORT CANCEL KAIN MASUK(TIDAK DIBUAT) | C47: Baim | E47: =F44+1 -> 46087 | F47: =IF(ISBLANK(E47)," - ",IF(G47=0,E47,E47+G47-1)) -> 46090 | G47: 4 | H47: CANCEL | I47: =IF(OR(F47=0,E47=0)," - ",NETWORKDAYS(E47,F47)) -> 2
A48: =IF(ISERROR(VALUE(SUBSTITUTE(prevWBS,".",""))),"0.1",IF(ISERROR(FIND("`",SUBSTITUTE(prevWBS,".","`",1))),prevWBS&".1",LEFT(prevWBS,FIND("`",SUBSTITUTE(prevWBS,".","`",1)))&IF(ISERROR(FIND("`",SUBSTITUTE(prevWBS,".","`",2))),VALUE(RIGHT(prevWBS,LEN(prevWBS)-FIND("`",SUBSTITUTE(prevWBS,".","`",1))))+1,VALUE(MID(prevWBS,FIND("`",SUBSTITUTE(prevWBS,".","`",1))+1,(FIND("`",SUBSTITUTE(prevWBS,".","`",2))-FIND("`",SUBSTITUTE(prevWBS,".","`",1))-1)))+1))) -> 1.40 | B48: REPORT COSTING ? | C48: Budi | E48: =F46+1 -> 46091 | F48: =IF(ISBLANK(E48)," - ",IF(G48=0,E48,E48+G48-1)) -> 46092 | G48: 2 | H48: 0 | I48: =IF(OR(F48=0,E48=0)," - ",NETWORKDAYS(E48,F48)) -> 2
A49: =IF(ISERROR(VALUE(SUBSTITUTE(prevWBS,".",""))),"0.1",IF(ISERROR(FIND("`",SUBSTITUTE(prevWBS,".","`",1))),prevWBS&".1",LEFT(prevWBS,FIND("`",SUBSTITUTE(prevWBS,".","`",1)))&IF(ISERROR(FIND("`",SUBSTITUTE(prevWBS,".","`",2))),VALUE(RIGHT(prevWBS,LEN(prevWBS)-FIND("`",SUBSTITUTE(prevWBS,".","`",1))))+1,VALUE(MID(prevWBS,FIND("`",SUBSTITUTE(prevWBS,".","`",1))+1,(FIND("`",SUBSTITUTE(prevWBS,".","`",2))-FIND("`",SUBSTITUTE(prevWBS,".","`",1))-1)))+1))) -> 1.41 | B49: REPORT PEMARTAIAN | C49: Budi | E49: =F47+1 -> 46091 | F49: =IF(ISBLANK(E49)," - ",IF(G49=0,E49,E49+G49-1)) -> 46092 | G49: 2 | H49: 0 | I49: =IF(OR(F49=0,E49=0)," - ",NETWORKDAYS(E49,F49)) -> 2
A50: =IF(ISERROR(VALUE(SUBSTITUTE(prevWBS,".",""))),"0.1",IF(ISERROR(FIND("`",SUBSTITUTE(prevWBS,".","`",1))),prevWBS&".1",LEFT(prevWBS,FIND("`",SUBSTITUTE(prevWBS,".","`",1)))&IF(ISERROR(FIND("`",SUBSTITUTE(prevWBS,".","`",2))),VALUE(RIGHT(prevWBS,LEN(prevWBS)-FIND("`",SUBSTITUTE(prevWBS,".","`",1))))+1,VALUE(MID(prevWBS,FIND("`",SUBSTITUTE(prevWBS,".","`",1))+1,(FIND("`",SUBSTITUTE(prevWBS,".","`",2))-FIND("`",SUBSTITUTE(prevWBS,".","`",1))-1)))+1))) -> 1.42 | B50: REPORT RESERVASI | C50: Budi | E50: =F48+1 -> 46093 | F50: =IF(ISBLANK(E50)," - ",IF(G50=0,E50,E50+G50-1)) -> 46094 | G50: 2 | H50: 0 | I50: =IF(OR(F50=0,E50=0)," - ",NETWORKDAYS(E50,F50)) -> 2
A51: =IF(ISERROR(VALUE(SUBSTITUTE(prevWBS,".",""))),"0.1",IF(ISERROR(FIND("`",SUBSTITUTE(prevWBS,".","`",1))),prevWBS&".1",LEFT(prevWBS,FIND("`",SUBSTITUTE(prevWBS,".","`",1)))&IF(ISERROR(FIND("`",SUBSTITUTE(prevWBS,".","`",2))),VALUE(RIGHT(prevWBS,LEN(prevWBS)-FIND("`",SUBSTITUTE(prevWBS,".","`",1))))+1,VALUE(MID(prevWBS,FIND("`",SUBSTITUTE(prevWBS,".","`",1))+1,(FIND("`",SUBSTITUTE(prevWBS,".","`",2))-FIND("`",SUBSTITUTE(prevWBS,".","`",1))-1)))+1))) -> 1.43 | B51: REPORT RESUME KODE PARTAI | C51: Budi | E51: =F49+1 -> 46093 | F51: =IF(ISBLANK(E51)," - ",IF(G51=0,E51,E51+G51-1)) -> 46094 | G51: 2 | H51: 0 | I51: =IF(OR(F51=0,E51=0)," - ",NETWORKDAYS(E51,F51)) -> 2
A52: =IF(ISERROR(VALUE(SUBSTITUTE(prevWBS,".",""))),"0.1",IF(ISERROR(FIND("`",SUBSTITUTE(prevWBS,".","`",1))),prevWBS&".1",LEFT(prevWBS,FIND("`",SUBSTITUTE(prevWBS,".","`",1)))&IF(ISERROR(FIND("`",SUBSTITUTE(prevWBS,".","`",2))),VALUE(RIGHT(prevWBS,LEN(prevWBS)-FIND("`",SUBSTITUTE(prevWBS,".","`",1))))+1,VALUE(MID(prevWBS,FIND("`",SUBSTITUTE(prevWBS,".","`",1))+1,(FIND("`",SUBSTITUTE(prevWBS,".","`",2))-FIND("`",SUBSTITUTE(prevWBS,".","`",1))-1)))+1))) -> 1.44 | B52: STK BLANK GD. PACKING | C52: Budi | E52: =F50+1 -> 46095 | F52: =IF(ISBLANK(E52)," - ",IF(G52=0,E52,E52+G52-1)) -> 46098 | G52: 4 | H52: 1 | I52: =IF(OR(F52=0,E52=0)," - ",NETWORKDAYS(E52,F52)) -> 2
A53: =IF(ISERROR(VALUE(SUBSTITUTE(prevWBS,".",""))),"0.1",IF(ISERROR(FIND("`",SUBSTITUTE(prevWBS,".","`",1))),prevWBS&".1",LEFT(prevWBS,FIND("`",SUBSTITUTE(prevWBS,".","`",1)))&IF(ISERROR(FIND("`",SUBSTITUTE(prevWBS,".","`",2))),VALUE(RIGHT(prevWBS,LEN(prevWBS)-FIND("`",SUBSTITUTE(prevWBS,".","`",1))))+1,VALUE(MID(prevWBS,FIND("`",SUBSTITUTE(prevWBS,".","`",1))+1,(FIND("`",SUBSTITUTE(prevWBS,".","`",2))-FIND("`",SUBSTITUTE(prevWBS,".","`",1))-1)))+1))) -> 1.45 | B53: STOCK BALANCE KAIN GREY | C53: Jali | E53: =F51+1 -> 46095 | F53: =IF(ISBLANK(E53)," - ",IF(G53=0,E53,E53+G53-1)) -> 46098 | G53: 4 | H53: 1 | I53: =IF(OR(F53=0,E53=0)," - ",NETWORKDAYS(E53,F53)) -> 2
A54: =IF(ISERROR(VALUE(SUBSTITUTE(prevWBS,".",""))),"0.1",IF(ISERROR(FIND("`",SUBSTITUTE(prevWBS,".","`",1))),prevWBS&".1",LEFT(prevWBS,FIND("`",SUBSTITUTE(prevWBS,".","`",1)))&IF(ISERROR(FIND("`",SUBSTITUTE(prevWBS,".","`",2))),VALUE(RIGHT(prevWBS,LEN(prevWBS)-FIND("`",SUBSTITUTE(prevWBS,".","`",1))))+1,VALUE(MID(prevWBS,FIND("`",SUBSTITUTE(prevWBS,".","`",1))+1,(FIND("`",SUBSTITUTE(prevWBS,".","`",2))-FIND("`",SUBSTITUTE(prevWBS,".","`",1))-1)))+1))) -> 1.46 | B54: STOCK GREY LEAD TIME PER GRADE | C54: Budi | E54: =F52+10 -> 46108 | F54: =IF(ISBLANK(E54)," - ",IF(G54=0,E54,E54+G54-1)) -> 46111 | G54: 4 | H54: 1 | I54: =IF(OR(F54=0,E54=0)," - ",NETWORKDAYS(E54,F54)) -> 2
A55: =IF(ISERROR(VALUE(SUBSTITUTE(prevWBS,".",""))),"0.1",IF(ISERROR(FIND("`",SUBSTITUTE(prevWBS,".","`",1))),prevWBS&".1",LEFT(prevWBS,FIND("`",SUBSTITUTE(prevWBS,".","`",1)))&IF(ISERROR(FIND("`",SUBSTITUTE(prevWBS,".","`",2))),VALUE(RIGHT(prevWBS,LEN(prevWBS)-FIND("`",SUBSTITUTE(prevWBS,".","`",1))))+1,VALUE(MID(prevWBS,FIND("`",SUBSTITUTE(prevWBS,".","`",1))+1,(FIND("`",SUBSTITUTE(prevWBS,".","`",2))-FIND("`",SUBSTITUTE(prevWBS,".","`",1))-1)))+1))) -> 1.47 | B55: STOCK KAIN GREY (GRADE) | C55: Jali | E55: =F53+10 -> 46108 | F55: =IF(ISBLANK(E55)," - ",IF(G55=0,E55,E55+G55-1)) -> 46111 | G55: 4 | H55: 1 | I55: =IF(OR(F55=0,E55=0)," - ",NETWORKDAYS(E55,F55)) -> 2
A56: =IF(ISERROR(VALUE(SUBSTITUTE(prevWBS,".",""))),"0.1",IF(ISERROR(FIND("`",SUBSTITUTE(prevWBS,".","`",1))),prevWBS&".1",LEFT(prevWBS,FIND("`",SUBSTITUTE(prevWBS,".","`",1)))&IF(ISERROR(FIND("`",SUBSTITUTE(prevWBS,".","`",2))),VALUE(RIGHT(prevWBS,LEN(prevWBS)-FIND("`",SUBSTITUTE(prevWBS,".","`",1))))+1,VALUE(MID(prevWBS,FIND("`",SUBSTITUTE(prevWBS,".","`",1))+1,(FIND("`",SUBSTITUTE(prevWBS,".","`",2))-FIND("`",SUBSTITUTE(prevWBS,".","`",1))-1)))+1))) -> 1.48 | B56: STOCK KAIN GREY (LW 22) | C56: Budi | E56: =F54+1 -> 46112 | F56: =IF(ISBLANK(E56)," - ",IF(G56=0,E56,E56+G56-1)) -> 46113 | G56: 2 | H56: 1 | I56: =IF(OR(F56=0,E56=0)," - ",NETWORKDAYS(E56,F56)) -> 2
A57: =IF(ISERROR(VALUE(SUBSTITUTE(prevWBS,".",""))),"0.1",IF(ISERROR(FIND("`",SUBSTITUTE(prevWBS,".","`",1))),prevWBS&".1",LEFT(prevWBS,FIND("`",SUBSTITUTE(prevWBS,".","`",1)))&IF(ISERROR(FIND("`",SUBSTITUTE(prevWBS,".","`",2))),VALUE(RIGHT(prevWBS,LEN(prevWBS)-FIND("`",SUBSTITUTE(prevWBS,".","`",1))))+1,VALUE(MID(prevWBS,FIND("`",SUBSTITUTE(prevWBS,".","`",1))+1,(FIND("`",SUBSTITUTE(prevWBS,".","`",2))-FIND("`",SUBSTITUTE(prevWBS,".","`",1))-1)))+1))) -> 1.49 | B57: STOCK KAIN PASIF (ALL AREA) | C57: Budi | E57: =F55+1 -> 46112 | F57: =IF(ISBLANK(E57)," - ",IF(G57=0,E57,E57+G57-1)) -> 46113 | G57: 2 | H57: 0 | I57: =IF(OR(F57=0,E57=0)," - ",NETWORKDAYS(E57,F57)) -> 2
A58: =IF(ISERROR(VALUE(SUBSTITUTE(prevWBS,".",""))),"0.1",IF(ISERROR(FIND("`",SUBSTITUTE(prevWBS,".","`",1))),prevWBS&".1",LEFT(prevWBS,FIND("`",SUBSTITUTE(prevWBS,".","`",1)))&IF(ISERROR(FIND("`",SUBSTITUTE(prevWBS,".","`",2))),VALUE(RIGHT(prevWBS,LEN(prevWBS)-FIND("`",SUBSTITUTE(prevWBS,".","`",1))))+1,VALUE(MID(prevWBS,FIND("`",SUBSTITUTE(prevWBS,".","`",1))+1,(FIND("`",SUBSTITUTE(prevWBS,".","`",2))-FIND("`",SUBSTITUTE(prevWBS,".","`",1))-1)))+1))) -> 1.50 | B58: STOCK LEADTIME | C58: Jali | E58: =F56+1 -> 46114 | F58: =IF(ISBLANK(E58)," - ",IF(G58=0,E58,E58+G58-1)) -> 46115 | G58: 2 | H58: 1 | I58: =IF(OR(F58=0,E58=0)," - ",NETWORKDAYS(E58,F58)) -> 2
A59: =IF(ISERROR(VALUE(SUBSTITUTE(prevWBS,".",""))),"0.1",IF(ISERROR(FIND("`",SUBSTITUTE(prevWBS,".","`",1))),prevWBS&".1",LEFT(prevWBS,FIND("`",SUBSTITUTE(prevWBS,".","`",1)))&IF(ISERROR(FIND("`",SUBSTITUTE(prevWBS,".","`",2))),VALUE(RIGHT(prevWBS,LEN(prevWBS)-FIND("`",SUBSTITUTE(prevWBS,".","`",1))))+1,VALUE(MID(prevWBS,FIND("`",SUBSTITUTE(prevWBS,".","`",1))+1,(FIND("`",SUBSTITUTE(prevWBS,".","`",2))-FIND("`",SUBSTITUTE(prevWBS,".","`",1))-1)))+1))) -> 1.51 | B59: MOVING HISTORY PER LIST BARCODE | C59: Star | E59: =F57+1 -> 46114 | F59: =IF(ISBLANK(E59)," - ",IF(G59=0,E59,E59+G59-1)) -> 46115 | G59: 2 | H59: 1 | I59: =IF(OR(F59=0,E59=0)," - ",NETWORKDAYS(E59,F59)) -> 2
A60: =IF(ISERROR(VALUE(SUBSTITUTE(prevWBS,".",""))),"0.1",IF(ISERROR(FIND("`",SUBSTITUTE(prevWBS,".","`",1))),prevWBS&".1",LEFT(prevWBS,FIND("`",SUBSTITUTE(prevWBS,".","`",1)))&IF(ISERROR(FIND("`",SUBSTITUTE(prevWBS,".","`",2))),VALUE(RIGHT(prevWBS,LEN(prevWBS)-FIND("`",SUBSTITUTE(prevWBS,".","`",1))))+1,VALUE(MID(prevWBS,FIND("`",SUBSTITUTE(prevWBS,".","`",1))+1,(FIND("`",SUBSTITUTE(prevWBS,".","`",2))-FIND("`",SUBSTITUTE(prevWBS,".","`",1))-1)))+1))) -> 1.52 | B60: MOVING HISTORY - GUDANG GREY | C60: Budi | E60: =F58+1 -> 46116 | F60: =IF(ISBLANK(E60)," - ",IF(G60=0,E60,E60+G60-1)) -> 46119 | G60: 4 | H60: 0 | I60: =IF(OR(F60=0,E60=0)," - ",NETWORKDAYS(E60,F60)) -> 2
A61: =IF(ISERROR(VALUE(SUBSTITUTE(prevWBS,".",""))),"0.1",IF(ISERROR(FIND("`",SUBSTITUTE(prevWBS,".","`",1))),prevWBS&".1",LEFT(prevWBS,FIND("`",SUBSTITUTE(prevWBS,".","`",1)))&IF(ISERROR(FIND("`",SUBSTITUTE(prevWBS,".","`",2))),VALUE(RIGHT(prevWBS,LEN(prevWBS)-FIND("`",SUBSTITUTE(prevWBS,".","`",1))))+1,VALUE(MID(prevWBS,FIND("`",SUBSTITUTE(prevWBS,".","`",1))+1,(FIND("`",SUBSTITUTE(prevWBS,".","`",2))-FIND("`",SUBSTITUTE(prevWBS,".","`",1))-1)))+1))) -> 1.53 | B61: INTERFACE PRINT BARCODE BANYAK LIST KARTON | C61: Baim | E61: =F59+1 -> 46116 | F61: =IF(ISBLANK(E61)," - ",IF(G61=0,E61,E61+G61-1)) -> 46119 | G61: 4 | H61: 0 | I61: =IF(OR(F61=0,E61=0)," - ",NETWORKDAYS(E61,F61)) -> 2
A76: =IF(ISERROR(VALUE(SUBSTITUTE(prevWBS,".",""))),"1",IF(ISERROR(FIND("`",SUBSTITUTE(prevWBS,".","`",1))),TEXT(VALUE(prevWBS)+1,"#"),TEXT(VALUE(LEFT(prevWBS,FIND("`",SUBSTITUTE(prevWBS,".","`",1))-1))+1,"#"))) -> 1 | B76: Report | F76: =IF(ISBLANK(E76)," - ",IF(G76=0,E76,E76+G76-1)) -> - | I76: =IF(OR(F76=0,E76=0)," - ",NETWORKDAYS(E76,F76)) -> -
A77: =IF(ISERROR(VALUE(SUBSTITUTE(prevWBS,".",""))),"0.1",IF(ISERROR(FIND("`",SUBSTITUTE(prevWBS,".","`",1))),prevWBS&".1",LEFT(prevWBS,FIND("`",SUBSTITUTE(prevWBS,".","`",1)))&IF(ISERROR(FIND("`",SUBSTITUTE(prevWBS,".","`",2))),VALUE(RIGHT(prevWBS,LEN(prevWBS)-FIND("`",SUBSTITUTE(prevWBS,".","`",1))))+1,VALUE(MID(prevWBS,FIND("`",SUBSTITUTE(prevWBS,".","`",1))+1,(FIND("`",SUBSTITUTE(prevWBS,".","`",2))-FIND("`",SUBSTITUTE(prevWBS,".","`",1))-1)))+1))) -> 1.1 | B77: REPORT - WM - MOVING HISTORY - GUDANG GREY | C77: Billy, Baim | E77: 46057 | F77: =IF(ISBLANK(E77)," - ",IF(G77=0,E77,E77+G77-1)) -> 46063 | G77: 7 | H77: 0 | I77: =IF(OR(F77=0,E77=0)," - ",NETWORKDAYS(E77,F77)) -> 5
A78: =IF(ISERROR(VALUE(SUBSTITUTE(prevWBS,".",""))),"0.1",IF(ISERROR(FIND("`",SUBSTITUTE(prevWBS,".","`",1))),prevWBS&".1",LEFT(prevWBS,FIND("`",SUBSTITUTE(prevWBS,".","`",1)))&IF(ISERROR(FIND("`",SUBSTITUTE(prevWBS,".","`",2))),VALUE(RIGHT(prevWBS,LEN(prevWBS)-FIND("`",SUBSTITUTE(prevWBS,".","`",1))))+1,VALUE(MID(prevWBS,FIND("`",SUBSTITUTE(prevWBS,".","`",1))+1,(FIND("`",SUBSTITUTE(prevWBS,".","`",2))-FIND("`",SUBSTITUTE(prevWBS,".","`",1))-1)))+1))) -> 1.2 | B78: REPORT - WM - STOCK PER BARCODE | C78: Baim | E78: 46064 | F78: =IF(ISBLANK(E78)," - ",IF(G78=0,E78,E78+G78-1)) -> 46070 | G78: 7 | H78: 0 | I78: =IF(OR(F78=0,E78=0)," - ",NETWORKDAYS(E78,F78)) -> 5
A79: =IF(ISERROR(VALUE(SUBSTITUTE(prevWBS,".",""))),"0.1",IF(ISERROR(FIND("`",SUBSTITUTE(prevWBS,".","`",1))),prevWBS&".1",LEFT(prevWBS,FIND("`",SUBSTITUTE(prevWBS,".","`",1)))&IF(ISERROR(FIND("`",SUBSTITUTE(prevWBS,".","`",2))),VALUE(RIGHT(prevWBS,LEN(prevWBS)-FIND("`",SUBSTITUTE(prevWBS,".","`",1))))+1,VALUE(MID(prevWBS,FIND("`",SUBSTITUTE(prevWBS,".","`",1))+1,(FIND("`",SUBSTITUTE(prevWBS,".","`",2))-FIND("`",SUBSTITUTE(prevWBS,".","`",1))-1)))+1))) -> 1.3 | B79: REPORT - WM - LAPORAN PERSEDIAAN GUDANG PACKING | C79: Budi | E79: 46064 | F79: =IF(ISBLANK(E79)," - ",IF(G79=0,E79,E79+G79-1)) -> 46070 | G79: 7 | H79: 0 | I79: =IF(OR(F79=0,E79=0)," - ",NETWORKDAYS(E79,F79)) -> 5
A80: =IF(ISERROR(VALUE(SUBSTITUTE(prevWBS,".",""))),"0.1",IF(ISERROR(FIND("`",SUBSTITUTE(prevWBS,".","`",1))),prevWBS&".1",LEFT(prevWBS,FIND("`",SUBSTITUTE(prevWBS,".","`",1)))&IF(ISERROR(FIND("`",SUBSTITUTE(prevWBS,".","`",2))),VALUE(RIGHT(prevWBS,LEN(prevWBS)-FIND("`",SUBSTITUTE(prevWBS,".","`",1))))+1,VALUE(MID(prevWBS,FIND("`",SUBSTITUTE(prevWBS,".","`",1))+1,(FIND("`",SUBSTITUTE(prevWBS,".","`",2))-FIND("`",SUBSTITUTE(prevWBS,".","`",1))-1)))+1))) -> 1.4 | B80: REPORT - WM - LAPORAN GUDANG PACKING LEAD TIME | C80: Baim | E80: 46071 | F80: =IF(ISBLANK(E80)," - ",IF(G80=0,E80,E80+G80-1)) -> 46077 | G80: 7 | H80: 0 | I80: =IF(OR(F80=0,E80=0)," - ",NETWORKDAYS(E80,F80)) -> 5
A81: =IF(ISERROR(VALUE(SUBSTITUTE(prevWBS,".",""))),"0.1",IF(ISERROR(FIND("`",SUBSTITUTE(prevWBS,".","`",1))),prevWBS&".1",LEFT(prevWBS,FIND("`",SUBSTITUTE(prevWBS,".","`",1)))&IF(ISERROR(FIND("`",SUBSTITUTE(prevWBS,".","`",2))),VALUE(RIGHT(prevWBS,LEN(prevWBS)-FIND("`",SUBSTITUTE(prevWBS,".","`",1))))+1,VALUE(MID(prevWBS,FIND("`",SUBSTITUTE(prevWBS,".","`",1))+1,(FIND("`",SUBSTITUTE(prevWBS,".","`",2))-FIND("`",SUBSTITUTE(prevWBS,".","`",1))-1)))+1))) -> 1.5 | B81: REPORT - WM - LIST KARTON PER KODE ORDER | C81: Budi | E81: 46071 | F81: =IF(ISBLANK(E81)," - ",IF(G81=0,E81,E81+G81-1)) -> 46077 | G81: 7 | H81: 0 | I81: =IF(OR(F81=0,E81=0)," - ",NETWORKDAYS(E81,F81)) -> 5
A82: =IF(ISERROR(VALUE(SUBSTITUTE(prevWBS,".",""))),"0.1",IF(ISERROR(FIND("`",SUBSTITUTE(prevWBS,".","`",1))),prevWBS&".1",LEFT(prevWBS,FIND("`",SUBSTITUTE(prevWBS,".","`",1)))&IF(ISERROR(FIND("`",SUBSTITUTE(prevWBS,".","`",2))),VALUE(RIGHT(prevWBS,LEN(prevWBS)-FIND("`",SUBSTITUTE(prevWBS,".","`",1))))+1,VALUE(MID(prevWBS,FIND("`",SUBSTITUTE(prevWBS,".","`",1))+1,(FIND("`",SUBSTITUTE(prevWBS,".","`",2))-FIND("`",SUBSTITUTE(prevWBS,".","`",1))-1)))+1))) -> 1.6 | B82: REPORT - WM - MOVING HISTORY PER BARCODE | C82: Baim | E82: 46078 | F82: =IF(ISBLANK(E82)," - ",IF(G82=0,E82,E82+G82-1)) -> 46084 | G82: 7 | H82: 0 | I82: =IF(OR(F82=0,E82=0)," - ",NETWORKDAYS(E82,F82)) -> 5
A83: =IF(ISERROR(VALUE(SUBSTITUTE(prevWBS,".",""))),"0.1",IF(ISERROR(FIND("`",SUBSTITUTE(prevWBS,".","`",1))),prevWBS&".1",LEFT(prevWBS,FIND("`",SUBSTITUTE(prevWBS,".","`",1)))&IF(ISERROR(FIND("`",SUBSTITUTE(prevWBS,".","`",2))),VALUE(RIGHT(prevWBS,LEN(prevWBS)-FIND("`",SUBSTITUTE(prevWBS,".","`",1))))+1,VALUE(MID(prevWBS,FIND("`",SUBSTITUTE(prevWBS,".","`",1))+1,(FIND("`",SUBSTITUTE(prevWBS,".","`",2))-FIND("`",SUBSTITUTE(prevWBS,".","`",1))-1)))+1))) -> 1.7 | B83: REPORT - WM - MOVING HISTORY PER LIST KARTON | C83: Budi | E83: 46078 | F83: =IF(ISBLANK(E83)," - ",IF(G83=0,E83,E83+G83-1)) -> 46084 | G83: 7 | H83: 0 | I83: =IF(OR(F83=0,E83=0)," - ",NETWORKDAYS(E83,F83)) -> 5
A84: =IF(ISERROR(VALUE(SUBSTITUTE(prevWBS,".",""))),"0.1",IF(ISERROR(FIND("`",SUBSTITUTE(prevWBS,".","`",1))),prevWBS&".1",LEFT(prevWBS,FIND("`",SUBSTITUTE(prevWBS,".","`",1)))&IF(ISERROR(FIND("`",SUBSTITUTE(prevWBS,".","`",2))),VALUE(RIGHT(prevWBS,LEN(prevWBS)-FIND("`",SUBSTITUTE(prevWBS,".","`",1))))+1,VALUE(MID(prevWBS,FIND("`",SUBSTITUTE(prevWBS,".","`",1))+1,(FIND("`",SUBSTITUTE(prevWBS,".","`",2))-FIND("`",SUBSTITUTE(prevWBS,".","`",1))-1)))+1))) -> 1.8 | B84: REPORT - MM - STOCK KAIN GREY (GRADE) | C84: Billy, Budi | E84: 46057 | F84: =IF(ISBLANK(E84)," - ",IF(G84=0,E84,E84+G84-1)) -> 46063 | G84: 7 | H84: 0 | I84: =IF(OR(F84=0,E84=0)," - ",NETWORKDAYS(E84,F84)) -> 5
A85: =IF(ISERROR(VALUE(SUBSTITUTE(prevWBS,".",""))),"0.1",IF(ISERROR(FIND("`",SUBSTITUTE(prevWBS,".","`",1))),prevWBS&".1",LEFT(prevWBS,FIND("`",SUBSTITUTE(prevWBS,".","`",1)))&IF(ISERROR(FIND("`",SUBSTITUTE(prevWBS,".","`",2))),VALUE(RIGHT(prevWBS,LEN(prevWBS)-FIND("`",SUBSTITUTE(prevWBS,".","`",1))))+1,VALUE(MID(prevWBS,FIND("`",SUBSTITUTE(prevWBS,".","`",1))+1,(FIND("`",SUBSTITUTE(prevWBS,".","`",2))-FIND("`",SUBSTITUTE(prevWBS,".","`",1))-1)))+1))) -> 1.9 | B85: REPORT - MM - STOCK LEADTIME | C85: Baim | E85: 46085 | F85: =IF(ISBLANK(E85)," - ",IF(G85=0,E85,E85+G85-1)) -> 46091 | G85: 7 | H85: 0 | I85: =IF(OR(F85=0,E85=0)," - ",NETWORKDAYS(E85,F85)) -> 5
A86: =IF(ISERROR(VALUE(SUBSTITUTE(prevWBS,".",""))),"0.1",IF(ISERROR(FIND("`",SUBSTITUTE(prevWBS,".","`",1))),prevWBS&".1",LEFT(prevWBS,FIND("`",SUBSTITUTE(prevWBS,".","`",1)))&IF(ISERROR(FIND("`",SUBSTITUTE(prevWBS,".","`",2))),VALUE(RIGHT(prevWBS,LEN(prevWBS)-FIND("`",SUBSTITUTE(prevWBS,".","`",1))))+1,VALUE(MID(prevWBS,FIND("`",SUBSTITUTE(prevWBS,".","`",1))+1,(FIND("`",SUBSTITUTE(prevWBS,".","`",2))-FIND("`",SUBSTITUTE(prevWBS,".","`",1))-1)))+1))) -> 1.10 | B86: REPORT - MM - STOCK GREY LEAD TIME PER GRADE | C86: Budi | E86: 46085 | F86: =IF(ISBLANK(E86)," - ",IF(G86=0,E86,E86+G86-1)) -> 46091 | G86: 7 | H86: 0 | I86: =IF(OR(F86=0,E86=0)," - ",NETWORKDAYS(E86,F86)) -> 5
A87: =IF(ISERROR(VALUE(SUBSTITUTE(prevWBS,".",""))),"0.1",IF(ISERROR(FIND("`",SUBSTITUTE(prevWBS,".","`",1))),prevWBS&".1",LEFT(prevWBS,FIND("`",SUBSTITUTE(prevWBS,".","`",1)))&IF(ISERROR(FIND("`",SUBSTITUTE(prevWBS,".","`",2))),VALUE(RIGHT(prevWBS,LEN(prevWBS)-FIND("`",SUBSTITUTE(prevWBS,".","`",1))))+1,VALUE(MID(prevWBS,FIND("`",SUBSTITUTE(prevWBS,".","`",1))+1,(FIND("`",SUBSTITUTE(prevWBS,".","`",2))-FIND("`",SUBSTITUTE(prevWBS,".","`",1))-1)))+1))) -> 1.11 | B87: REPORT - MM - STOCK BALANCE KAIN GREY | C87: Budi | E87: 46092 | F87: =IF(ISBLANK(E87)," - ",IF(G87=0,E87,E87+G87-1)) -> 46098 | G87: 7 | H87: 0 | I87: =IF(OR(F87=0,E87=0)," - ",NETWORKDAYS(E87,F87)) -> 5
A88: =IF(ISERROR(VALUE(SUBSTITUTE(prevWBS,".",""))),"0.1",IF(ISERROR(FIND("`",SUBSTITUTE(prevWBS,".","`",1))),prevWBS&".1",LEFT(prevWBS,FIND("`",SUBSTITUTE(prevWBS,".","`",1)))&IF(ISERROR(FIND("`",SUBSTITUTE(prevWBS,".","`",2))),VALUE(RIGHT(prevWBS,LEN(prevWBS)-FIND("`",SUBSTITUTE(prevWBS,".","`",1))))+1,VALUE(MID(prevWBS,FIND("`",SUBSTITUTE(prevWBS,".","`",1))+1,(FIND("`",SUBSTITUTE(prevWBS,".","`",2))-FIND("`",SUBSTITUTE(prevWBS,".","`",1))-1)))+1))) -> 1.12 | B88: REPORT - MM - STOCK KAIN PASIF (ALL AREA) | C88: Baim | E88: 46092 | F88: =IF(ISBLANK(E88)," - ",IF(G88=0,E88,E88+G88-1)) -> 46098 | G88: 7 | H88: 0 | I88: =IF(OR(F88=0,E88=0)," - ",NETWORKDAYS(E88,F88)) -> 5
... A103: =IF(ISERROR(VALUE(SUBSTITUTE(prevWBS,".",""))),"0.1",IF(ISERROR(FIND("`",SUBSTITUTE(prevWBS,".","`",1))),prevWBS&".1",LEFT(prevWBS,FIND("`",SUBSTITUTE(prevWBS,".","`",1)))&IF(ISERROR(FIND("`",SUBSTITUTE(prevWBS,".","`",2))),VALUE(RIGHT(prevWBS,LEN(prevWBS)-FIND("`",SUBSTITUTE(prevWBS,".","`",1))))+1,VALUE(MID(prevWBS,FIND("`",SUBSTITUTE(prevWBS,".","`",1))+1,(FIND("`",SUBSTITUTE(prevWBS,".","`",2))-FIND("`",SUBSTITUTE(prevWBS,".","`",1))-1)))+1))) -> 1.27 | B103: REPORT - MM - STK Blank Gd. Packing | C103: Budi | E103: 46148 | F103: =IF(ISBLANK(E103)," - ",IF(G103=0,E103,E103+G103-1)) -> 46154 | G103: 7 | H103: 0 | I103: =IF(OR(F103=0,E103=0)," - ",NETWORKDAYS(E103,F103)) -> 5
A104: =IF(ISERROR(VALUE(SUBSTITUTE(prevWBS,".",""))),"1",IF(ISERROR(FIND("`",SUBSTITUTE(prevWBS,".","`",1))),TEXT(VALUE(prevWBS)+1,"#"),TEXT(VALUE(LEFT(prevWBS,FIND("`",SUBSTITUTE(prevWBS,".","`",1))-1))+1,"#"))) -> 2 | B104: Interfaces | F104: =IF(ISBLANK(E104)," - ",IF(G104=0,E104,E104+G104-1)) -> - | I104: =IF(OR(F104=0,E104=0)," - ",NETWORKDAYS(E104,F104)) -> -
A105: =IF(ISERROR(VALUE(SUBSTITUTE(prevWBS,".",""))),"0.1",IF(ISERROR(FIND("`",SUBSTITUTE(prevWBS,".","`",1))),prevWBS&".1",LEFT(prevWBS,FIND("`",SUBSTITUTE(prevWBS,".","`",1)))&IF(ISERROR(FIND("`",SUBSTITUTE(prevWBS,".","`",2))),VALUE(RIGHT(prevWBS,LEN(prevWBS)-FIND("`",SUBSTITUTE(prevWBS,".","`",1))))+1,VALUE(MID(prevWBS,FIND("`",SUBSTITUTE(prevWBS,".","`",1))+1,(FIND("`",SUBSTITUTE(prevWBS,".","`",2))-FIND("`",SUBSTITUTE(prevWBS,".","`",1))-1)))+1))) -> 2.1 | B105: INTERFACE BEA CUKAI | C105: Billy, Budi | E105: 46034 | F105: =IF(ISBLANK(E105)," - ",IF(G105=0,E105,E105+G105-1)) -> 46038 | G105: 5 | H105: 0 | I105: =IF(OR(F105=0,E105=0)," - ",NETWORKDAYS(E105,F105)) -> 5
A106: =IF(ISERROR(VALUE(SUBSTITUTE(prevWBS,".",""))),"0.1",IF(ISERROR(FIND("`",SUBSTITUTE(prevWBS,".","`",1))),prevWBS&".1",LEFT(prevWBS,FIND("`",SUBSTITUTE(prevWBS,".","`",1)))&IF(ISERROR(FIND("`",SUBSTITUTE(prevWBS,".","`",2))),VALUE(RIGHT(prevWBS,LEN(prevWBS)-FIND("`",SUBSTITUTE(prevWBS,".","`",1))))+1,VALUE(MID(prevWBS,FIND("`",SUBSTITUTE(prevWBS,".","`",1))+1,(FIND("`",SUBSTITUTE(prevWBS,".","`",2))-FIND("`",SUBSTITUTE(prevWBS,".","`",1))-1)))+1))) -> 2.2 | B106: INTERFACE PRINT BARCODE | C106: Billy, Baim, Budi | E106: 46023 | F106: =IF(ISBLANK(E106)," - ",IF(G106=0,E106,E106+G106-1)) -> 46032 | G106: 10 | H106: 0 | I106: 6
A107: =IF(ISERROR(VALUE(SUBSTITUTE(prevWBS,".",""))),"0.1",IF(ISERROR(FIND("`",SUBSTITUTE(prevWBS,".","`",1))),prevWBS&".1",LEFT(prevWBS,FIND("`",SUBSTITUTE(prevWBS,".","`",1)))&IF(ISERROR(FIND("`",SUBSTITUTE(prevWBS,".","`",2))),VALUE(RIGHT(prevWBS,LEN(prevWBS)-FIND("`",SUBSTITUTE(prevWBS,".","`",1))))+1,VALUE(MID(prevWBS,FIND("`",SUBSTITUTE(prevWBS,".","`",1))+1,(FIND("`",SUBSTITUTE(prevWBS,".","`",2))-FIND("`",SUBSTITUTE(prevWBS,".","`",1))-1)))+1))) -> 2.3 | B107: INTERFACE PRINT BARCODE BANYAK LIST KARTON | C107: Billy, Baim | E107: 46034 | F107: =IF(ISBLANK(E107)," - ",IF(G107=0,E107,E107+G107-1)) -> 46038 | G107: 5 | H107: 0 | I107: 5
A108: =IF(ISERROR(VALUE(SUBSTITUTE(prevWBS,".",""))),"1",IF(ISERROR(FIND("`",SUBSTITUTE(prevWBS,".","`",1))),TEXT(VALUE(prevWBS)+1,"#"),TEXT(VALUE(LEFT(prevWBS,FIND("`",SUBSTITUTE(prevWBS,".","`",1))-1))+1,"#"))) -> 3 | B108: Forms | F108: =IF(ISBLANK(E108)," - ",IF(G108=0,E108,E108+G108-1)) -> - | I108: =IF(OR(F108=0,E108=0)," - ",NETWORKDAYS(E108,F108)) -> -
A109: =IF(ISERROR(VALUE(SUBSTITUTE(prevWBS,".",""))),"0.1",IF(ISERROR(FIND("`",SUBSTITUTE(prevWBS,".","`",1))),prevWBS&".1",LEFT(prevWBS,FIND("`",SUBSTITUTE(prevWBS,".","`",1)))&IF(ISERROR(FIND("`",SUBSTITUTE(prevWBS,".","`",2))),VALUE(RIGHT(prevWBS,LEN(prevWBS)-FIND("`",SUBSTITUTE(prevWBS,".","`",1))))+1,VALUE(MID(prevWBS,FIND("`",SUBSTITUTE(prevWBS,".","`",1))+1,(FIND("`",SUBSTITUTE(prevWBS,".","`",2))-FIND("`",SUBSTITUTE(prevWBS,".","`",1))-1)))+1))) -> 3.1 | B109: Form Transfer Posting (ZSCMF001) | C109: Billy, Budi | E109: 46041 | F109: =IF(ISBLANK(E109)," - ",IF(G109=0,E109,E109+G109-1)) -> 46044 | G109: 4 | H109: 0 | I109: 4
A110: =IF(ISERROR(VALUE(SUBSTITUTE(prevWBS,".",""))),"0.1",IF(ISERROR(FIND("`",SUBSTITUTE(prevWBS,".","`",1))),prevWBS&".1",LEFT(prevWBS,FIND("`",SUBSTITUTE(prevWBS,".","`",1)))&IF(ISERROR(FIND("`",SUBSTITUTE(prevWBS,".","`",2))),VALUE(RIGHT(prevWBS,LEN(prevWBS)-FIND("`",SUBSTITUTE(prevWBS,".","`",1))))+1,VALUE(MID(prevWBS,FIND("`",SUBSTITUTE(prevWBS,".","`",1))+1,(FIND("`",SUBSTITUTE(prevWBS,".","`",2))-FIND("`",SUBSTITUTE(prevWBS,".","`",1))-1)))+1))) -> 3.2 | B110: Form Purchase Order (ZSCMF002) | C110: Billy, Baim | E110: 46041 | F110: =IF(ISBLANK(E110)," - ",IF(G110=0,E110,E110+G110-1)) -> 46044 | G110: 4 | H110: 0 | I110: 4
A111: =IF(ISERROR(VALUE(SUBSTITUTE(prevWBS,".",""))),"0.1",IF(ISERROR(FIND("`",SUBSTITUTE(prevWBS,".","`",1))),prevWBS&".1",LEFT(prevWBS,FIND("`",SUBSTITUTE(prevWBS,".","`",1)))&IF(ISERROR(FIND("`",SUBSTITUTE(prevWBS,".","`",2))),VALUE(RIGHT(prevWBS,LEN(prevWBS)-FIND("`",SUBSTITUTE(prevWBS,".","`",1))))+1,VALUE(MID(prevWBS,FIND("`",SUBSTITUTE(prevWBS,".","`",1))+1,(FIND("`",SUBSTITUTE(prevWBS,".","`",2))-FIND("`",SUBSTITUTE(prevWBS,".","`",1))-1)))+1))) -> 3.3 | B111: Form Good Receipt (ZSCMF003) | C111: Baim | E111: 46045 | F111: =IF(ISBLANK(E111)," - ",IF(G111=0,E111,E111+G111-1)) -> 46050 | G111: 6 | H111: 0 | I111: 4
A112: =IF(ISERROR(VALUE(SUBSTITUTE(prevWBS,".",""))),"0.1",IF(ISERROR(FIND("`",SUBSTITUTE(prevWBS,".","`",1))),prevWBS&".1",LEFT(prevWBS,FIND("`",SUBSTITUTE(prevWBS,".","`",1)))&IF(ISERROR(FIND("`",SUBSTITUTE(prevWBS,".","`",2))),VALUE(RIGHT(prevWBS,LEN(prevWBS)-FIND("`",SUBSTITUTE(prevWBS,".","`",1))))+1,VALUE(MID(prevWBS,FIND("`",SUBSTITUTE(prevWBS,".","`",1))+1,(FIND("`",SUBSTITUTE(prevWBS,".","`",2))-FIND("`",SUBSTITUTE(prevWBS,".","`",1))-1)))+1))) -> 3.4 | B112: Form Good Issue (ZSCMF004) | C112: Baim | E112: 46051 | F112: =IF(ISBLANK(E112)," - ",IF(G112=0,E112,E112+G112-1)) -> 46056 | G112: 6 | H112: 0 | I112: 4
A113: =IF(ISERROR(VALUE(SUBSTITUTE(prevWBS,".",""))),"0.1",IF(ISERROR(FIND("`",SUBSTITUTE(prevWBS,".","`",1))),prevWBS&".1",LEFT(prevWBS,FIND("`",SUBSTITUTE(prevWBS,".","`",1)))&IF(ISERROR(FIND("`",SUBSTITUTE(prevWBS,".","`",2))),VALUE(RIGHT(prevWBS,LEN(prevWBS)-FIND("`",SUBSTITUTE(prevWBS,".","`",1))))+1,VALUE(MID(prevWBS,FIND("`",SUBSTITUTE(prevWBS,".","`",1))+1,(FIND("`",SUBSTITUTE(prevWBS,".","`",2))-FIND("`",SUBSTITUTE(prevWBS,".","`",1))-1)))+1))) -> 3.5 | B113: Form Bukti Tanda Terima | C113: Budi | E113: 46045 | F113: =IF(ISBLANK(E113)," - ",IF(G113=0,E113,E113+G113-1)) -> 46050 | G113: 6 | H113: 0 | I113: 4
A114: =IF(ISERROR(VALUE(SUBSTITUTE(prevWBS,".",""))),"1",IF(ISERROR(FIND("`",SUBSTITUTE(prevWBS,".","`",1))),TEXT(VALUE(prevWBS)+1,"#"),TEXT(VALUE(LEFT(prevWBS,FIND("`",SUBSTITUTE(prevWBS,".","`",1))-1))+1,"#"))) -> 4 | B114: Enhancement | F114: =IF(ISBLANK(E114)," - ",IF(G114=0,E114,E114+G114-1)) -> - | I114: =IF(OR(F114=0,E114=0)," - ",NETWORKDAYS(E114,F114)) -> -
A115: =IF(ISERROR(VALUE(SUBSTITUTE(prevWBS,".",""))),"0.1",IF(ISERROR(FIND("`",SUBSTITUTE(prevWBS,".","`",1))),prevWBS&".1",LEFT(prevWBS,FIND("`",SUBSTITUTE(prevWBS,".","`",1)))&IF(ISERROR(FIND("`",SUBSTITUTE(prevWBS,".","`",2))),VALUE(RIGHT(prevWBS,LEN(prevWBS)-FIND("`",SUBSTITUTE(prevWBS,".","`",1))))+1,VALUE(MID(prevWBS,FIND("`",SUBSTITUTE(prevWBS,".","`",1))+1,(FIND("`",SUBSTITUTE(prevWBS,".","`",2))-FIND("`",SUBSTITUTE(prevWBS,".","`",1))-1)))+1))) -> 4.1 | B115: Custom field for qty in PCS at Report Stock | C115: Billy, Budi | E115: 46051 | F115: =IF(ISBLANK(E115)," - ",IF(G115=0,E115,E115+G115-1)) -> 46056 | G115: 6 | H115: 0 | I115: 4

Sheet Sheet4

Sheet i
A1: RICEF BY LEUWITEX ( update 3 Maret 2026 )
B4: Project Start Date | C4: 45986 | G4: Display Week | H4: 1 | K4: ="Week "&(K6-($C$4-WEEKDAY($C$4,1)+2))/7+1 -> Week 1 | R4: ="Week "&(R6-($C$4-WEEKDAY($C$4,1)+2))/7+1 -> Week 2 | Y4: ="Week "&(Y6-($C$4-WEEKDAY($C$4,1)+2))/7+1 -> Week 3 | AF4: ="Week "&(AF6-($C$4-WEEKDAY($C$4,1)+2))/7+1 -> Week 4 | AM4: ="Week "&(AM6-($C$4-WEEKDAY($C$4,1)+2))/7+1 -> Week 5 | AT4: ="Week "&(AT6-($C$4-WEEKDAY($C$4,1)+2))/7+1 -> Week 6 | BA4: ="Week "&(BA6-($C$4-WEEKDAY($C$4,1)+2))/7+1 -> Week 7 | BH4: ="Week "&(BH6-($C$4-WEEKDAY($C$4,1)+2))/7+1 -> Week 8
B5: Project Lead | C5: Billy | K5: =K6 -> 45985 | R5: =R6 -> 45992 | Y5: =Y6 -> 45999 | AF5: =AF6 -> 46006 | AM5: =AM6 -> 46013 | AT5: =AT6 -> 46020 | BA5: =BA6 -> 46027 | BH5: =BH6 -> 46034
K6: =C4-WEEKDAY(C4,1)+2+7*(H4-1) -> 45985 | L6: =K6+1 -> 45986 | M6: =L6+1 -> 45987 | N6: =M6+1 -> 45988 | O6: =N6+1 -> 45989 | P6: =O6+1 -> 45990 | Q6: =P6+1 -> 45991 | R6: =Q6+1 -> 45992 | S6: =R6+1 -> 45993 | ... BN6: =BM6+1 -> 46040
A7: WBS | B7: TASK | C7: PIC | D7: NOTES | E7: START | F7: END | G7: DAYS | H7: % DONE | I7: WORK DAYS | K7: =CHOOSE(WEEKDAY(K6,1),"S","M","T","W","T","F","S") -> M | L7: =CHOOSE(WEEKDAY(L6,1),"S","M","T","W","T","F","S") -> T | M7: =CHOOSE(WEEKDAY(M6,1),"S","M","T","W","T","F","S") -> W | N7: =CHOOSE(WEEKDAY(N6,1),"S","M","T","W","T","F","S") -> T | O7: =CHOOSE(WEEKDAY(O6,1),"S","M","T","W","T","F","S") -> F | P7: =CHOOSE(WEEKDAY(P6,1),"S","M","T","W","T","F","S") -> S | Q7: =CHOOSE(WEEKDAY(Q6,1),"S","M","T","W","T","F","S") -> S | R7: =CHOOSE(WEEKDAY(R6,1),"S","M","T","W","T","F","S") -> M | ... BN7: =CHOOSE(WEEKDAY(BN6,1),"S","M","T","W","T","F","S") -> S
A8: =IF(ISERROR(VALUE(SUBSTITUTE(prevWBS,".",""))),"1",IF(ISERROR(FIND("`",SUBSTITUTE(prevWBS,".","`",1))),TEXT(VALUE(prevWBS)+1,"#"),TEXT(VALUE(LEFT(prevWBS,FIND("`",SUBSTITUTE(prevWBS,".","`",1))-1))+1,"#"))) -> 1 | B8: SAP API development | F8: =IF(ISBLANK(E8)," - ",IF(G8=0,E8,E8+G8-1)) -> - | I8: =IF(OR(F8=0,E8=0)," - ",NETWORKDAYS(E8,F8)) -> -
A9: =IF(ISERROR(VALUE(SUBSTITUTE(prevWBS,".",""))),"0.1",IF(ISERROR(FIND("`",SUBSTITUTE(prevWBS,".","`",1))),prevWBS&".1",LEFT(prevWBS,FIND("`",SUBSTITUTE(prevWBS,".","`",1)))&IF(ISERROR(FIND("`",SUBSTITUTE(prevWBS,".","`",2))),VALUE(RIGHT(prevWBS,LEN(prevWBS)-FIND("`",SUBSTITUTE(prevWBS,".","`",1))))+1,VALUE(MID(prevWBS,FIND("`",SUBSTITUTE(prevWBS,".","`",1))+1,(FIND("`",SUBSTITUTE(prevWBS,".","`",2))-FIND("`",SUBSTITUTE(prevWBS,".","`",1))-1)))+1))) -> 1.1 | B9: INSTALL ECLIPSE, ADOBE LIFECYCLE DI PC | C9: Baim, Budi | E9: 45987 | F9: =IF(ISBLANK(E9)," - ",IF(G9=0,E9,E9+G9-1)) -> 45987 | G9: 1 | H9: 1 | I9: =IF(OR(F9=0,E9=0)," - ",NETWORKDAYS(E9,F9)) -> 1
A10: =IF(ISERROR(VALUE(SUBSTITUTE(prevWBS,".",""))),"0.1",IF(ISERROR(FIND("`",SUBSTITUTE(prevWBS,".","`",1))),prevWBS&".1",LEFT(prevWBS,FIND("`",SUBSTITUTE(prevWBS,".","`",1)))&IF(ISERROR(FIND("`",SUBSTITUTE(prevWBS,".","`",2))),VALUE(RIGHT(prevWBS,LEN(prevWBS)-FIND("`",SUBSTITUTE(prevWBS,".","`",1))))+1,VALUE(MID(prevWBS,FIND("`",SUBSTITUTE(prevWBS,".","`",1))+1,(FIND("`",SUBSTITUTE(prevWBS,".","`",2))-FIND("`",SUBSTITUTE(prevWBS,".","`",1))-1)))+1))) -> 1.2 | B10: BELAJAR KE SOLTIUS TENTANG SAP | C10: Baim, Budi | E10: 45988 | F10: =IF(ISBLANK(E10)," - ",IF(G10=0,E10,E10+G10-1)) -> 46054 | G10: 67 | H10: 0.4 | I10: =IF(OR(F10=0,E10=0)," - ",NETWORKDAYS(E10,F10)) -> 47
A11: =IF(ISERROR(VALUE(SUBSTITUTE(prevWBS,".",""))),"0.1",IF(ISERROR(FIND("`",SUBSTITUTE(prevWBS,".","`",1))),prevWBS&".1",LEFT(prevWBS,FIND("`",SUBSTITUTE(prevWBS,".","`",1)))&IF(ISERROR(FIND("`",SUBSTITUTE(prevWBS,".","`",2))),VALUE(RIGHT(prevWBS,LEN(prevWBS)-FIND("`",SUBSTITUTE(prevWBS,".","`",1))))+1,VALUE(MID(prevWBS,FIND("`",SUBSTITUTE(prevWBS,".","`",1))+1,(FIND("`",SUBSTITUTE(prevWBS,".","`",2))-FIND("`",SUBSTITUTE(prevWBS,".","`",1))-1)))+1))) -> 1.3 | B11: INTEGRASI API SAP KE PRINT BARCODE INTERNAL | C11: Baim, Budi | E11: 45995 | F11: =IF(ISBLANK(E11)," - ",IF(G11=0,E11,E11+G11-1)) -> 46001 | G11: 7 | H11: 1 | I11: =IF(OR(F11=0,E11=0)," - ",NETWORKDAYS(E11,F11)) -> 5
A12: =IF(ISERROR(VALUE(SUBSTITUTE(prevWBS,".",""))),"0.1",IF(ISERROR(FIND("`",SUBSTITUTE(prevWBS,".","`",1))),prevWBS&".1",LEFT(prevWBS,FIND("`",SUBSTITUTE(prevWBS,".","`",1)))&IF(ISERROR(FIND("`",SUBSTITUTE(prevWBS,".","`",2))),VALUE(RIGHT(prevWBS,LEN(prevWBS)-FIND("`",SUBSTITUTE(prevWBS,".","`",1))))+1,VALUE(MID(prevWBS,FIND("`",SUBSTITUTE(prevWBS,".","`",1))+1,(FIND("`",SUBSTITUTE(prevWBS,".","`",2))-FIND("`",SUBSTITUTE(prevWBS,".","`",1))-1)))+1))) -> 1.4 | B12: MAPPING IT INVENTORY | C12: Baim | E12: 46009 | F12: =IF(ISBLANK(E12)," - ",IF(G12=0,E12,E12+G12-1)) -> 46014 | G12: 6 | H12: 1 | I12: =IF(OR(F12=0,E12=0)," - ",NETWORKDAYS(E12,F12)) -> 4
A13: =IF(ISERROR(VALUE(SUBSTITUTE(prevWBS,".",""))),"0.1",IF(ISERROR(FIND("`",SUBSTITUTE(prevWBS,".","`",1))),prevWBS&".1",LEFT(prevWBS,FIND("`",SUBSTITUTE(prevWBS,".","`",1)))&IF(ISERROR(FIND("`",SUBSTITUTE(prevWBS,".","`",2))),VALUE(RIGHT(prevWBS,LEN(prevWBS)-FIND("`",SUBSTITUTE(prevWBS,".","`",1))))+1,VALUE(MID(prevWBS,FIND("`",SUBSTITUTE(prevWBS,".","`",1))+1,(FIND("`",SUBSTITUTE(prevWBS,".","`",2))-FIND("`",SUBSTITUTE(prevWBS,".","`",1))-1)))+1))) -> 1.5 | B13: BELAJAR MENDAFTARKAN API SAP | C13: Baim, Budi | E13: 46021 | F13: =IF(ISBLANK(E13)," - ",IF(G13=0,E13,E13+G13-1)) -> 46021 | G13: 1 | H13: 1 | I13: =IF(OR(F13=0,E13=0)," - ",NETWORKDAYS(E13,F13)) -> 1
A14: =IF(ISERROR(VALUE(SUBSTITUTE(prevWBS,".",""))),"0.1",IF(ISERROR(FIND("`",SUBSTITUTE(prevWBS,".","`",1))),prevWBS&".1",LEFT(prevWBS,FIND("`",SUBSTITUTE(prevWBS,".","`",1)))&IF(ISERROR(FIND("`",SUBSTITUTE(prevWBS,".","`",2))),VALUE(RIGHT(prevWBS,LEN(prevWBS)-FIND("`",SUBSTITUTE(prevWBS,".","`",1))))+1,VALUE(MID(prevWBS,FIND("`",SUBSTITUTE(prevWBS,".","`",1))+1,(FIND("`",SUBSTITUTE(prevWBS,".","`",2))-FIND("`",SUBSTITUTE(prevWBS,".","`",1))-1)))+1))) -> 1.6 | B14: MAPPING TABEL TAMBAHAN BEA CUKAI | C14: Baim | E14: 46021 | F14: =IF(ISBLANK(E14)," - ",IF(G14=0,E14,E14+G14-1)) -> 46030 | G14: 10 | H14: 1 | I14: =IF(OR(F14=0,E14=0)," - ",NETWORKDAYS(E14,F14)) -> 8
A15: =IF(ISERROR(VALUE(SUBSTITUTE(prevWBS,".",""))),"0.1",IF(ISERROR(FIND("`",SUBSTITUTE(prevWBS,".","`",1))),prevWBS&".1",LEFT(prevWBS,FIND("`",SUBSTITUTE(prevWBS,".","`",1)))&IF(ISERROR(FIND("`",SUBSTITUTE(prevWBS,".","`",2))),VALUE(RIGHT(prevWBS,LEN(prevWBS)-FIND("`",SUBSTITUTE(prevWBS,".","`",1))))+1,VALUE(MID(prevWBS,FIND("`",SUBSTITUTE(prevWBS,".","`",1))+1,(FIND("`",SUBSTITUTE(prevWBS,".","`",2))-FIND("`",SUBSTITUTE(prevWBS,".","`",1))-1)))+1))) -> 1.7 | B15: SIT | C15: Baim, Budi | E15: 46028 | F15: =IF(ISBLANK(E15)," - ",IF(G15=0,E15,E15+G15-1)) -> 46030 | G15: 3 | H15: 1 | I15: =IF(OR(F15=0,E15=0)," - ",NETWORKDAYS(E15,F15)) -> 3
A16: =IF(ISERROR(VALUE(SUBSTITUTE(prevWBS,".",""))),"0.1",IF(ISERROR(FIND("`",SUBSTITUTE(prevWBS,".","`",1))),prevWBS&".1",LEFT(prevWBS,FIND("`",SUBSTITUTE(prevWBS,".","`",1)))&IF(ISERROR(FIND("`",SUBSTITUTE(prevWBS,".","`",2))),VALUE(RIGHT(prevWBS,LEN(prevWBS)-FIND("`",SUBSTITUTE(prevWBS,".","`",1))))+1,VALUE(MID(prevWBS,FIND("`",SUBSTITUTE(prevWBS,".","`",1))+1,(FIND("`",SUBSTITUTE(prevWBS,".","`",2))-FIND("`",SUBSTITUTE(prevWBS,".","`",1))-1)))+1))) -> 1.8 | B16: INTEGRASI API SAP UNTUK BEA CUKAI | C16: Baim, Budi, Jali, Star | E16: 46031 | F16: =IF(ISBLANK(E16)," - ",IF(G16=0,E16,E16+G16-1)) -> 46040 | G16: 10 | H16: 0.5 | I16: =IF(OR(F16=0,E16=0)," - ",NETWORKDAYS(E16,F16)) -> 6
A17: =IF(ISERROR(VALUE(SUBSTITUTE(prevWBS,".",""))),"0.1",IF(ISERROR(FIND("`",SUBSTITUTE(prevWBS,".","`",1))),prevWBS&".1",LEFT(prevWBS,FIND("`",SUBSTITUTE(prevWBS,".","`",1)))&IF(ISERROR(FIND("`",SUBSTITUTE(prevWBS,".","`",2))),VALUE(RIGHT(prevWBS,LEN(prevWBS)-FIND("`",SUBSTITUTE(prevWBS,".","`",1))))+1,VALUE(MID(prevWBS,FIND("`",SUBSTITUTE(prevWBS,".","`",1))+1,(FIND("`",SUBSTITUTE(prevWBS,".","`",2))-FIND("`",SUBSTITUTE(prevWBS,".","`",1))-1)))+1))) -> 1.9 | B17: BELAJAR MENGEDIT FORM SAP | C17: Baim, Budi | E17: 46030 | F17: =IF(ISBLANK(E17)," - ",IF(G17=0,E17,E17+G17-1)) -> 46030 | G17: 1 | H17: 1 | I17: =IF(OR(F17=0,E17=0)," - ",NETWORKDAYS(E17,F17)) -> 1
A18: =IF(ISERROR(VALUE(SUBSTITUTE(prevWBS,".",""))),"0.1",IF(ISERROR(FIND("`",SUBSTITUTE(prevWBS,".","`",1))),prevWBS&".1",LEFT(prevWBS,FIND("`",SUBSTITUTE(prevWBS,".","`",1)))&IF(ISERROR(FIND("`",SUBSTITUTE(prevWBS,".","`",2))),VALUE(RIGHT(prevWBS,LEN(prevWBS)-FIND("`",SUBSTITUTE(prevWBS,".","`",1))))+1,VALUE(MID(prevWBS,FIND("`",SUBSTITUTE(prevWBS,".","`",1))+1,(FIND("`",SUBSTITUTE(prevWBS,".","`",2))-FIND("`",SUBSTITUTE(prevWBS,".","`",1))-1)))+1))) -> 1.10 | B18: KUT SAP BAGIAN MASTER DATA MM | C18: Baim | E18: 46037 | F18: =IF(ISBLANK(E18)," - ",IF(G18=0,E18,E18+G18-1)) -> 46038 | G18: 2 | H18: 1 | I18: =IF(OR(F18=0,E18=0)," - ",NETWORKDAYS(E18,F18)) -> 2
A19: =IF(ISERROR(VALUE(SUBSTITUTE(prevWBS,".",""))),"0.1",IF(ISERROR(FIND("`",SUBSTITUTE(prevWBS,".","`",1))),prevWBS&".1",LEFT(prevWBS,FIND("`",SUBSTITUTE(prevWBS,".","`",1)))&IF(ISERROR(FIND("`",SUBSTITUTE(prevWBS,".","`",2))),VALUE(RIGHT(prevWBS,LEN(prevWBS)-FIND("`",SUBSTITUTE(prevWBS,".","`",1))))+1,VALUE(MID(prevWBS,FIND("`",SUBSTITUTE(prevWBS,".","`",1))+1,(FIND("`",SUBSTITUTE(prevWBS,".","`",2))-FIND("`",SUBSTITUTE(prevWBS,".","`",1))-1)))+1))) -> 1.11 | B19: KUT SAP BAGIAN MASTER DATA SD dan FICO | C19: Budi | E19: 46037 | F19: =IF(ISBLANK(E19)," - ",IF(G19=0,E19,E19+G19-1)) -> 46038 | G19: 2 | H19: 1 | I19: =IF(OR(F19=0,E19=0)," - ",NETWORKDAYS(E19,F19)) -> 2
A20: =IF(ISERROR(VALUE(SUBSTITUTE(prevWBS,".",""))),"0.1",IF(ISERROR(FIND("`",SUBSTITUTE(prevWBS,".","`",1))),prevWBS&".1",LEFT(prevWBS,FIND("`",SUBSTITUTE(prevWBS,".","`",1)))&IF(ISERROR(FIND("`",SUBSTITUTE(prevWBS,".","`",2))),VALUE(RIGHT(prevWBS,LEN(prevWBS)-FIND("`",SUBSTITUTE(prevWBS,".","`",1))))+1,VALUE(MID(prevWBS,FIND("`",SUBSTITUTE(prevWBS,".","`",1))+1,(FIND("`",SUBSTITUTE(prevWBS,".","`",2))-FIND("`",SUBSTITUTE(prevWBS,".","`",1))-1)))+1))) -> 1.12 | B20: Modifikasi Form Invoice (Barang Bekas, Avfal, BS, Maklon, Masker) | C20: Baim | E20: 46032 | F20: =IF(ISBLANK(E20)," - ",IF(G20=0,E20,E20+G20-1)) -> 46043 | G20: 12 | H20: 1 | I20: =IF(OR(F20=0,E20=0)," - ",NETWORKDAYS(E20,F20)) -> 8
A21: =IF(ISERROR(VALUE(SUBSTITUTE(prevWBS,".",""))),"0.1",IF(ISERROR(FIND("`",SUBSTITUTE(prevWBS,".","`",1))),prevWBS&".1",LEFT(prevWBS,FIND("`",SUBSTITUTE(prevWBS,".","`",1)))&IF(ISERROR(FIND("`",SUBSTITUTE(prevWBS,".","`",2))),VALUE(RIGHT(prevWBS,LEN(prevWBS)-FIND("`",SUBSTITUTE(prevWBS,".","`",1))))+1,VALUE(MID(prevWBS,FIND("`",SUBSTITUTE(prevWBS,".","`",1))+1,(FIND("`",SUBSTITUTE(prevWBS,".","`",2))-FIND("`",SUBSTITUTE(prevWBS,".","`",1))-1)))+1))) -> 1.13 | B21: Modifikasi Form Surat Jalan (Barang Bekas, Avfal, BS, Maklon, Masker) | C21: Budi | E21: 46032 | F21: =IF(ISBLANK(E21)," - ",IF(G21=0,E21,E21+G21-1)) -> 46043 | G21: 12 | H21: 0.9 | I21: =IF(OR(F21=0,E21=0)," - ",NETWORKDAYS(E21,F21)) -> 8
A22: =IF(ISERROR(VALUE(SUBSTITUTE(prevWBS,".",""))),"0.1",IF(ISERROR(FIND("`",SUBSTITUTE(prevWBS,".","`",1))),prevWBS&".1",LEFT(prevWBS,FIND("`",SUBSTITUTE(prevWBS,".","`",1)))&IF(ISERROR(FIND("`",SUBSTITUTE(prevWBS,".","`",2))),VALUE(RIGHT(prevWBS,LEN(prevWBS)-FIND("`",SUBSTITUTE(prevWBS,".","`",1))))+1,VALUE(MID(prevWBS,FIND("`",SUBSTITUTE(prevWBS,".","`",1))+1,(FIND("`",SUBSTITUTE(prevWBS,".","`",2))-FIND("`",SUBSTITUTE(prevWBS,".","`",1))-1)))+1))) -> 1.14 | B22: Buat UI penarikan data dari API dan insert data Delivery | C22: Baim | D22: Sudah Tenant | E22: 46056 | F22: =IF(ISBLANK(E22)," - ",IF(G22=0,E22,E22+G22-1)) -> 46057 | G22: 2 | H22: 1 | I22: =IF(OR(F22=0,E22=0)," - ",NETWORKDAYS(E22,F22)) -> 2
A23: =IF(ISERROR(VALUE(SUBSTITUTE(prevWBS,".",""))),"0.1",IF(ISERROR(FIND("`",SUBSTITUTE(prevWBS,".","`",1))),prevWBS&".1",LEFT(prevWBS,FIND("`",SUBSTITUTE(prevWBS,".","`",1)))&IF(ISERROR(FIND("`",SUBSTITUTE(prevWBS,".","`",2))),VALUE(RIGHT(prevWBS,LEN(prevWBS)-FIND("`",SUBSTITUTE(prevWBS,".","`",1))))+1,VALUE(MID(prevWBS,FIND("`",SUBSTITUTE(prevWBS,".","`",1))+1,(FIND("`",SUBSTITUTE(prevWBS,".","`",2))-FIND("`",SUBSTITUTE(prevWBS,".","`",1))-1)))+1))) -> 1.15 | B23: Buat UI penarikan data dari API dan insert data Material | C23: Budi | E23: 46056 | F23: =IF(ISBLANK(E23)," - ",IF(G23=0,E23,E23+G23-1)) -> 46057 | G23: 2 | H23: 1 | I23: =IF(OR(F23=0,E23=0)," - ",NETWORKDAYS(E23,F23)) -> 2
A24: =IF(ISERROR(VALUE(SUBSTITUTE(prevWBS,".",""))),"0.1",IF(ISERROR(FIND("`",SUBSTITUTE(prevWBS,".","`",1))),prevWBS&".1",LEFT(prevWBS,FIND("`",SUBSTITUTE(prevWBS,".","`",1)))&IF(ISERROR(FIND("`",SUBSTITUTE(prevWBS,".","`",2))),VALUE(RIGHT(prevWBS,LEN(prevWBS)-FIND("`",SUBSTITUTE(prevWBS,".","`",1))))+1,VALUE(MID(prevWBS,FIND("`",SUBSTITUTE(prevWBS,".","`",1))+1,(FIND("`",SUBSTITUTE(prevWBS,".","`",2))-FIND("`",SUBSTITUTE(prevWBS,".","`",1))-1)))+1))) -> 1.16 | B24: Buat UI penarikan data dari API dan insert data Warehouse | C24: Budi | E24: =F22+1 -> 46058 | F24: =IF(ISBLANK(E24)," - ",IF(G24=0,E24,E24+G24-1)) -> 46059 | G24: 2 | H24: 1 | I24: =IF(OR(F24=0,E24=0)," - ",NETWORKDAYS(E24,F24)) -> 2
A25: =IF(ISERROR(VALUE(SUBSTITUTE(prevWBS,".",""))),"0.1",IF(ISERROR(FIND("`",SUBSTITUTE(prevWBS,".","`",1))),prevWBS&".1",LEFT(prevWBS,FIND("`",SUBSTITUTE(prevWBS,".","`",1)))&IF(ISERROR(FIND("`",SUBSTITUTE(prevWBS,".","`",2))),VALUE(RIGHT(prevWBS,LEN(prevWBS)-FIND("`",SUBSTITUTE(prevWBS,".","`",1))))+1,VALUE(MID(prevWBS,FIND("`",SUBSTITUTE(prevWBS,".","`",1))+1,(FIND("`",SUBSTITUTE(prevWBS,".","`",2))-FIND("`",SUBSTITUTE(prevWBS,".","`",1))-1)))+1))) -> 1.17 | B25: Buat UI penarikan data dari API dan insert data Asset | C25: Baim | D25: Sudah Tenant | E25: =F22+1 -> 46058 | F25: =IF(ISBLANK(E25)," - ",IF(G25=0,E25,E25+G25-1)) -> 46059 | G25: 2 | H25: 1 | I25: =IF(OR(F25=0,E25=0)," - ",NETWORKDAYS(E25,F25)) -> 2
A26: =IF(ISERROR(VALUE(SUBSTITUTE(prevWBS,".",""))),"0.1",IF(ISERROR(FIND("`",SUBSTITUTE(prevWBS,".","`",1))),prevWBS&".1",LEFT(prevWBS,FIND("`",SUBSTITUTE(prevWBS,".","`",1)))&IF(ISERROR(FIND("`",SUBSTITUTE(prevWBS,".","`",2))),VALUE(RIGHT(prevWBS,LEN(prevWBS)-FIND("`",SUBSTITUTE(prevWBS,".","`",1))))+1,VALUE(MID(prevWBS,FIND("`",SUBSTITUTE(prevWBS,".","`",1))+1,(FIND("`",SUBSTITUTE(prevWBS,".","`",2))-FIND("`",SUBSTITUTE(prevWBS,".","`",1))-1)))+1))) -> 1.18 | B26: Buat UI penarikan data dari API dan insert data Invoice | C26: Budi | E26: =E23+1 -> 46057 | F26: =IF(ISBLANK(E26)," - ",IF(G26=0,E26,E26+G26-1)) -> 46058 | G26: 2 | H26: 1 | I26: =IF(OR(F26=0,E26=0)," - ",NETWORKDAYS(E26,F26)) -> 2
A27: =IF(ISERROR(VALUE(SUBSTITUTE(prevWBS,".",""))),"0.1",IF(ISERROR(FIND("`",SUBSTITUTE(prevWBS,".","`",1))),prevWBS&".1",LEFT(prevWBS,FIND("`",SUBSTITUTE(prevWBS,".","`",1)))&IF(ISERROR(FIND("`",SUBSTITUTE(prevWBS,".","`",2))),VALUE(RIGHT(prevWBS,LEN(prevWBS)-FIND("`",SUBSTITUTE(prevWBS,".","`",1))))+1,VALUE(MID(prevWBS,FIND("`",SUBSTITUTE(prevWBS,".","`",1))+1,(FIND("`",SUBSTITUTE(prevWBS,".","`",2))-FIND("`",SUBSTITUTE(prevWBS,".","`",1))-1)))+1))) -> 1.19 | B27: Buat UI penarikan data dari API dan insert data Supplier | C27: Baim | E27: =F23+1 -> 46058 | F27: =IF(ISBLANK(E27)," - ",IF(G27=0,E27,E27+G27-1)) -> 46059 | G27: 2 | H27: 1 | I27: =IF(OR(F27=0,E27=0)," - ",NETWORKDAYS(E27,F27)) -> 2
A28: =IF(ISERROR(VALUE(SUBSTITUTE(prevWBS,".",""))),"0.1",IF(ISERROR(FIND("`",SUBSTITUTE(prevWBS,".","`",1))),prevWBS&".1",LEFT(prevWBS,FIND("`",SUBSTITUTE(prevWBS,".","`",1)))&IF(ISERROR(FIND("`",SUBSTITUTE(prevWBS,".","`",2))),VALUE(RIGHT(prevWBS,LEN(prevWBS)-FIND("`",SUBSTITUTE(prevWBS,".","`",1))))+1,VALUE(MID(prevWBS,FIND("`",SUBSTITUTE(prevWBS,".","`",1))+1,(FIND("`",SUBSTITUTE(prevWBS,".","`",2))-FIND("`",SUBSTITUTE(prevWBS,".","`",1))-1)))+1))) -> 1.20 | B28: Buat UI penarikan data dari API dan insert data Master Customer | C28: Budi | E28: =F24+1 -> 46060 | F28: =IF(ISBLANK(E28)," - ",IF(G28=0,E28,E28+G28-1)) -> 46063 | G28: 4 | H28: 1 | I28: =IF(OR(F28=0,E28=0)," - ",NETWORKDAYS(E28,F28)) -> 2
A29: =IF(ISERROR(VALUE(SUBSTITUTE(prevWBS,".",""))),"0.1",IF(ISERROR(FIND("`",SUBSTITUTE(prevWBS,".","`",1))),prevWBS&".1",LEFT(prevWBS,FIND("`",SUBSTITUTE(prevWBS,".","`",1)))&IF(ISERROR(FIND("`",SUBSTITUTE(prevWBS,".","`",2))),VALUE(RIGHT(prevWBS,LEN(prevWBS)-FIND("`",SUBSTITUTE(prevWBS,".","`",1))))+1,VALUE(MID(prevWBS,FIND("`",SUBSTITUTE(prevWBS,".","`",1))+1,(FIND("`",SUBSTITUTE(prevWBS,".","`",2))-FIND("`",SUBSTITUTE(prevWBS,".","`",1))-1)))+1))) -> 1.21 | B29: Buat UI penarikan data dari API dan insert data PO | C29: Baim | D29: Sudah Tenant | E29: =F24+1 -> 46060 | F29: =IF(ISBLANK(E29)," - ",IF(G29=0,E29,E29+G29-1)) -> 46063 | G29: 4 | H29: 1 | I29: =IF(OR(F29=0,E29=0)," - ",NETWORKDAYS(E29,F29)) -> 2
A30: =IF(ISERROR(VALUE(SUBSTITUTE(prevWBS,".",""))),"0.1",IF(ISERROR(FIND("`",SUBSTITUTE(prevWBS,".","`",1))),prevWBS&".1",LEFT(prevWBS,FIND("`",SUBSTITUTE(prevWBS,".","`",1)))&IF(ISERROR(FIND("`",SUBSTITUTE(prevWBS,".","`",2))),VALUE(RIGHT(prevWBS,LEN(prevWBS)-FIND("`",SUBSTITUTE(prevWBS,".","`",1))))+1,VALUE(MID(prevWBS,FIND("`",SUBSTITUTE(prevWBS,".","`",1))+1,(FIND("`",SUBSTITUTE(prevWBS,".","`",2))-FIND("`",SUBSTITUTE(prevWBS,".","`",1))-1)))+1))) -> 1.22 | B30: Buat UI penarikan data dari API dan insert data Material Document | C30: Budi | E30: =F28+1 -> 46064 | F30: =IF(ISBLANK(E30)," - ",IF(G30=0,E30,E30+G30-1)) -> 46065 | G30: 2 | H30: 1 | I30: =IF(OR(F30=0,E30=0)," - ",NETWORKDAYS(E30,F30)) -> 2
A31: =IF(ISERROR(VALUE(SUBSTITUTE(prevWBS,".",""))),"0.1",IF(ISERROR(FIND("`",SUBSTITUTE(prevWBS,".","`",1))),prevWBS&".1",LEFT(prevWBS,FIND("`",SUBSTITUTE(prevWBS,".","`",1)))&IF(ISERROR(FIND("`",SUBSTITUTE(prevWBS,".","`",2))),VALUE(RIGHT(prevWBS,LEN(prevWBS)-FIND("`",SUBSTITUTE(prevWBS,".","`",1))))+1,VALUE(MID(prevWBS,FIND("`",SUBSTITUTE(prevWBS,".","`",1))+1,(FIND("`",SUBSTITUTE(prevWBS,".","`",2))-FIND("`",SUBSTITUTE(prevWBS,".","`",1))-1)))+1))) -> 1.23 | B31: Buat UI penarikan data dari API dan insert data BOM | C31: Baim | D31: Sudah Tenant | E31: =F29+1 -> 46064 | F31: =IF(ISBLANK(E31)," - ",IF(G31=0,E31,E31+G31-1)) -> 46065 | G31: 2 | H31: 1 | I31: =IF(OR(F31=0,E31=0)," - ",NETWORKDAYS(E31,F31)) -> 2
A32: =IF(ISERROR(VALUE(SUBSTITUTE(prevWBS,".",""))),"0.1",IF(ISERROR(FIND("`",SUBSTITUTE(prevWBS,".","`",1))),prevWBS&".1",LEFT(prevWBS,FIND("`",SUBSTITUTE(prevWBS,".","`",1)))&IF(ISERROR(FIND("`",SUBSTITUTE(prevWBS,".","`",2))),VALUE(RIGHT(prevWBS,LEN(prevWBS)-FIND("`",SUBSTITUTE(prevWBS,".","`",1))))+1,VALUE(MID(prevWBS,FIND("`",SUBSTITUTE(prevWBS,".","`",1))+1,(FIND("`",SUBSTITUTE(prevWBS,".","`",2))-FIND("`",SUBSTITUTE(prevWBS,".","`",1))-1)))+1))) -> 1.24 | B32: UAT | C32: Baim, Budi | E32: =F30 -> 46065 | F32: =IF(ISBLANK(E32)," - ",IF(G32=0,E32,E32+G32-1)) -> 46067 | G32: 3 | H32: 1 | I32: =IF(OR(F32=0,E32=0)," - ",NETWORKDAYS(E32,F32)) -> 2
A33: =IF(ISERROR(VALUE(SUBSTITUTE(prevWBS,".",""))),"0.1",IF(ISERROR(FIND("`",SUBSTITUTE(prevWBS,".","`",1))),prevWBS&".1",LEFT(prevWBS,FIND("`",SUBSTITUTE(prevWBS,".","`",1)))&IF(ISERROR(FIND("`",SUBSTITUTE(prevWBS,".","`",2))),VALUE(RIGHT(prevWBS,LEN(prevWBS)-FIND("`",SUBSTITUTE(prevWBS,".","`",1))))+1,VALUE(MID(prevWBS,FIND("`",SUBSTITUTE(prevWBS,".","`",1))+1,(FIND("`",SUBSTITUTE(prevWBS,".","`",2))-FIND("`",SUBSTITUTE(prevWBS,".","`",1))-1)))+1))) -> 1.25 | B33: BBK INTERN | C33: Budi | E33: =F32+1 -> 46068 | F33: =IF(ISBLANK(E33)," - ",IF(G33=0,E33,E33+G33-1)) -> 46072 | G33: 5 | H33: 0 | I33: =IF(OR(F33=0,E33=0)," - ",NETWORKDAYS(E33,F33)) -> 4
A34: =IF(ISERROR(VALUE(SUBSTITUTE(prevWBS,".",""))),"0.1",IF(ISERROR(FIND("`",SUBSTITUTE(prevWBS,".","`",1))),prevWBS&".1",LEFT(prevWBS,FIND("`",SUBSTITUTE(prevWBS,".","`",1)))&IF(ISERROR(FIND("`",SUBSTITUTE(prevWBS,".","`",2))),VALUE(RIGHT(prevWBS,LEN(prevWBS)-FIND("`",SUBSTITUTE(prevWBS,".","`",1))))+1,VALUE(MID(prevWBS,FIND("`",SUBSTITUTE(prevWBS,".","`",1))+1,(FIND("`",SUBSTITUTE(prevWBS,".","`",2))-FIND("`",SUBSTITUTE(prevWBS,".","`",1))-1)))+1))) -> 1.26 | B34: LAPORAN SURAT JALAN (P) | C34: Baim | E34: =F32+1 -> 46068 | F34: =IF(ISBLANK(E34)," - ",IF(G34=0,E34,E34+G34-1)) -> 46072 | G34: 5 | H34: 0.8 | I34: =IF(OR(F34=0,E34=0)," - ",NETWORKDAYS(E34,F34)) -> 4
A35: =IF(ISERROR(VALUE(SUBSTITUTE(prevWBS,".",""))),"0.1",IF(ISERROR(FIND("`",SUBSTITUTE(prevWBS,".","`",1))),prevWBS&".1",LEFT(prevWBS,FIND("`",SUBSTITUTE(prevWBS,".","`",1)))&IF(ISERROR(FIND("`",SUBSTITUTE(prevWBS,".","`",2))),VALUE(RIGHT(prevWBS,LEN(prevWBS)-FIND("`",SUBSTITUTE(prevWBS,".","`",1))))+1,VALUE(MID(prevWBS,FIND("`",SUBSTITUTE(prevWBS,".","`",1))+1,(FIND("`",SUBSTITUTE(prevWBS,".","`",2))-FIND("`",SUBSTITUTE(prevWBS,".","`",1))-1)))+1))) -> 1.27 | B35: DETAIL LIST KARTON PER RAK | C35: Star | E35: =F33+1 -> 46073 | F35: =IF(ISBLANK(E35)," - ",IF(G35=0,E35,E35+G35-1)) -> 46076 | G35: 4 | H35: 0 | I35: =IF(OR(F35=0,E35=0)," - ",NETWORKDAYS(E35,F35)) -> 2
A36: =IF(ISERROR(VALUE(SUBSTITUTE(prevWBS,".",""))),"0.1",IF(ISERROR(FIND("`",SUBSTITUTE(prevWBS,".","`",1))),prevWBS&".1",LEFT(prevWBS,FIND("`",SUBSTITUTE(prevWBS,".","`",1)))&IF(ISERROR(FIND("`",SUBSTITUTE(prevWBS,".","`",2))),VALUE(RIGHT(prevWBS,LEN(prevWBS)-FIND("`",SUBSTITUTE(prevWBS,".","`",1))))+1,VALUE(MID(prevWBS,FIND("`",SUBSTITUTE(prevWBS,".","`",1))+1,(FIND("`",SUBSTITUTE(prevWBS,".","`",2))-FIND("`",SUBSTITUTE(prevWBS,".","`",1))-1)))+1))) -> 1.28 | B36: LAPORAN GUDANG PACKING LEAD TIME | C36: Baim | E36: =F34+1 -> 46073 | F36: =IF(ISBLANK(E36)," - ",IF(G36=0,E36,E36+G36-1)) -> 46076 | G36: 4 | H36: 0.5 | I36: =IF(OR(F36=0,E36=0)," - ",NETWORKDAYS(E36,F36)) -> 2
A37: =IF(ISERROR(VALUE(SUBSTITUTE(prevWBS,".",""))),"0.1",IF(ISERROR(FIND("`",SUBSTITUTE(prevWBS,".","`",1))),prevWBS&".1",LEFT(prevWBS,FIND("`",SUBSTITUTE(prevWBS,".","`",1)))&IF(ISERROR(FIND("`",SUBSTITUTE(prevWBS,".","`",2))),VALUE(RIGHT(prevWBS,LEN(prevWBS)-FIND("`",SUBSTITUTE(prevWBS,".","`",1))))+1,VALUE(MID(prevWBS,FIND("`",SUBSTITUTE(prevWBS,".","`",1))+1,(FIND("`",SUBSTITUTE(prevWBS,".","`",2))-FIND("`",SUBSTITUTE(prevWBS,".","`",1))-1)))+1))) -> 1.29 | B37: MOVING HISTORY PER LIST KARTON | C37: Star | E37: =F35+1 -> 46077 | F37: =IF(ISBLANK(E37)," - ",IF(G37=0,E37,E37+G37-1)) -> 46078 | G37: 2 | H37: 0 | I37: =IF(OR(F37=0,E37=0)," - ",NETWORKDAYS(E37,F37)) -> 2
A38: =IF(ISERROR(VALUE(SUBSTITUTE(prevWBS,".",""))),"0.1",IF(ISERROR(FIND("`",SUBSTITUTE(prevWBS,".","`",1))),prevWBS&".1",LEFT(prevWBS,FIND("`",SUBSTITUTE(prevWBS,".","`",1)))&IF(ISERROR(FIND("`",SUBSTITUTE(prevWBS,".","`",2))),VALUE(RIGHT(prevWBS,LEN(prevWBS)-FIND("`",SUBSTITUTE(prevWBS,".","`",1))))+1,VALUE(MID(prevWBS,FIND("`",SUBSTITUTE(prevWBS,".","`",1))+1,(FIND("`",SUBSTITUTE(prevWBS,".","`",2))-FIND("`",SUBSTITUTE(prevWBS,".","`",1))-1)))+1))) -> 1.30 | B38: DASHBOARD LAYOUT PER BIN | C38: Jali | E38: =F36+1 -> 46077 | F38: =IF(ISBLANK(E38)," - ",IF(G38=0,E38,E38+G38-1)) -> 46078 | G38: 2 | H38: 0 | I38: =IF(OR(F38=0,E38=0)," - ",NETWORKDAYS(E38,F38)) -> 2
A39: =IF(ISERROR(VALUE(SUBSTITUTE(prevWBS,".",""))),"0.1",IF(ISERROR(FIND("`",SUBSTITUTE(prevWBS,".","`",1))),prevWBS&".1",LEFT(prevWBS,FIND("`",SUBSTITUTE(prevWBS,".","`",1)))&IF(ISERROR(FIND("`",SUBSTITUTE(prevWBS,".","`",2))),VALUE(RIGHT(prevWBS,LEN(prevWBS)-FIND("`",SUBSTITUTE(prevWBS,".","`",1))))+1,VALUE(MID(prevWBS,FIND("`",SUBSTITUTE(prevWBS,".","`",1))+1,(FIND("`",SUBSTITUTE(prevWBS,".","`",2))-FIND("`",SUBSTITUTE(prevWBS,".","`",1))-1)))+1))) -> 1.31 | B39: LAPORAN SURAT JALAN SLOC | C39: Baim | D39: Baim | E39: =F37+1 -> 46079 | F39: =IF(ISBLANK(E39)," - ",IF(G39=0,E39,E39+G39-1)) -> 46080 | G39: 2 | H39: 0 | I39: =IF(OR(F39=0,E39=0)," - ",NETWORKDAYS(E39,F39)) -> 2
A40: =IF(ISERROR(VALUE(SUBSTITUTE(prevWBS,".",""))),"0.1",IF(ISERROR(FIND("`",SUBSTITUTE(prevWBS,".","`",1))),prevWBS&".1",LEFT(prevWBS,FIND("`",SUBSTITUTE(prevWBS,".","`",1)))&IF(ISERROR(FIND("`",SUBSTITUTE(prevWBS,".","`",2))),VALUE(RIGHT(prevWBS,LEN(prevWBS)-FIND("`",SUBSTITUTE(prevWBS,".","`",1))))+1,VALUE(MID(prevWBS,FIND("`",SUBSTITUTE(prevWBS,".","`",1))+1,(FIND("`",SUBSTITUTE(prevWBS,".","`",2))-FIND("`",SUBSTITUTE(prevWBS,".","`",1))-1)))+1))) -> 1.32 | B40: LIST KARTON PER KODE ORDER | C40: Baim | E40: =F38+1 -> 46079 | F40: =IF(ISBLANK(E40)," - ",IF(G40=0,E40,E40+G40-1)) -> 46080 | G40: 2 | H40: 0.5 | I40: =IF(OR(F40=0,E40=0)," - ",NETWORKDAYS(E40,F40)) -> 2
A41: =IF(ISERROR(VALUE(SUBSTITUTE(prevWBS,".",""))),"0.1",IF(ISERROR(FIND("`",SUBSTITUTE(prevWBS,".","`",1))),prevWBS&".1",LEFT(prevWBS,FIND("`",SUBSTITUTE(prevWBS,".","`",1)))&IF(ISERROR(FIND("`",SUBSTITUTE(prevWBS,".","`",2))),VALUE(RIGHT(prevWBS,LEN(prevWBS)-FIND("`",SUBSTITUTE(prevWBS,".","`",1))))+1,VALUE(MID(prevWBS,FIND("`",SUBSTITUTE(prevWBS,".","`",1))+1,(FIND("`",SUBSTITUTE(prevWBS,".","`",2))-FIND("`",SUBSTITUTE(prevWBS,".","`",1))-1)))+1))) -> 1.33 | B41: LIST STK INTERN DAN EXTERN | C41: Jali | E41: =F39+1 -> 46081 | F41: =IF(ISBLANK(E41)," - ",IF(G41=0,E41,E41+G41-1)) -> 46084 | G41: 4 | H41: 1 | I41: =IF(OR(F41=0,E41=0)," - ",NETWORKDAYS(E41,F41)) -> 2
A42: =IF(ISERROR(VALUE(SUBSTITUTE(prevWBS,".",""))),"0.1",IF(ISERROR(FIND("`",SUBSTITUTE(prevWBS,".","`",1))),prevWBS&".1",LEFT(prevWBS,FIND("`",SUBSTITUTE(prevWBS,".","`",1)))&IF(ISERROR(FIND("`",SUBSTITUTE(prevWBS,".","`",2))),VALUE(RIGHT(prevWBS,LEN(prevWBS)-FIND("`",SUBSTITUTE(prevWBS,".","`",1))))+1,VALUE(MID(prevWBS,FIND("`",SUBSTITUTE(prevWBS,".","`",1))+1,(FIND("`",SUBSTITUTE(prevWBS,".","`",2))-FIND("`",SUBSTITUTE(prevWBS,".","`",1))-1)))+1))) -> 1.34 | B42: MONITORING KAIN GREY | C42: Jali | E42: =F40+1 -> 46081 | F42: =IF(ISBLANK(E42)," - ",IF(G42=0,E42,E42+G42-1)) -> 46084 | G42: 4 | H42: 0 | I42: =IF(OR(F42=0,E42=0)," - ",NETWORKDAYS(E42,F42)) -> 2
A43: =IF(ISERROR(VALUE(SUBSTITUTE(prevWBS,".",""))),"0.1",IF(ISERROR(FIND("`",SUBSTITUTE(prevWBS,".","`",1))),prevWBS&".1",LEFT(prevWBS,FIND("`",SUBSTITUTE(prevWBS,".","`",1)))&IF(ISERROR(FIND("`",SUBSTITUTE(prevWBS,".","`",2))),VALUE(RIGHT(prevWBS,LEN(prevWBS)-FIND("`",SUBSTITUTE(prevWBS,".","`",1))))+1,VALUE(MID(prevWBS,FIND("`",SUBSTITUTE(prevWBS,".","`",1))+1,(FIND("`",SUBSTITUTE(prevWBS,".","`",2))-FIND("`",SUBSTITUTE(prevWBS,".","`",1))-1)))+1))) -> 1.35 | B43: LAPORAN PERSEDIAAN GUDANG PACKING | C43: Star | E43: =F41 -> 46084 | F43: =IF(ISBLANK(E43)," - ",IF(G43=0,E43,E43+G43-1)) -> 46086 | G43: 3 | H43: 0 | I43: =IF(OR(F43=0,E43=0)," - ",NETWORKDAYS(E43,F43)) -> 3
A44: =IF(ISERROR(VALUE(SUBSTITUTE(prevWBS,".",""))),"0.1",IF(ISERROR(FIND("`",SUBSTITUTE(prevWBS,".","`",1))),prevWBS&".1",LEFT(prevWBS,FIND("`",SUBSTITUTE(prevWBS,".","`",1)))&IF(ISERROR(FIND("`",SUBSTITUTE(prevWBS,".","`",2))),VALUE(RIGHT(prevWBS,LEN(prevWBS)-FIND("`",SUBSTITUTE(prevWBS,".","`",1))))+1,VALUE(MID(prevWBS,FIND("`",SUBSTITUTE(prevWBS,".","`",1))+1,(FIND("`",SUBSTITUTE(prevWBS,".","`",2))-FIND("`",SUBSTITUTE(prevWBS,".","`",1))-1)))+1))) -> 1.36 | B44: STOCK PER BARCODE | C44: Jali | E44: =F42 -> 46084 | F44: =IF(ISBLANK(E44)," - ",IF(G44=0,E44,E44+G44-1)) -> 46086 | G44: 3 | H44: 0 | I44: =IF(OR(F44=0,E44=0)," - ",NETWORKDAYS(E44,F44)) -> 3
A45: =IF(ISERROR(VALUE(SUBSTITUTE(prevWBS,".",""))),"0.1",IF(ISERROR(FIND("`",SUBSTITUTE(prevWBS,".","`",1))),prevWBS&".1",LEFT(prevWBS,FIND("`",SUBSTITUTE(prevWBS,".","`",1)))&IF(ISERROR(FIND("`",SUBSTITUTE(prevWBS,".","`",2))),VALUE(RIGHT(prevWBS,LEN(prevWBS)-FIND("`",SUBSTITUTE(prevWBS,".","`",1))))+1,VALUE(MID(prevWBS,FIND("`",SUBSTITUTE(prevWBS,".","`",1))+1,(FIND("`",SUBSTITUTE(prevWBS,".","`",2))-FIND("`",SUBSTITUTE(prevWBS,".","`",1))-1)))+1))) -> 1.37 | B45: Buat UI penarikan data dari API dan insert data Reservasi | C45: Jali | E45: =F41+3 -> 46087 | F45: =IF(ISBLANK(E45)," - ",IF(G45=0,E45,E45+G45-1)) -> 46088 | G45: 2 | H45: 0 | I45: =IF(OR(F45=0,E45=0)," - ",NETWORKDAYS(E45,F45)) -> 1
A46: =IF(ISERROR(VALUE(SUBSTITUTE(prevWBS,".",""))),"0.1",IF(ISERROR(FIND("`",SUBSTITUTE(prevWBS,".","`",1))),prevWBS&".1",LEFT(prevWBS,FIND("`",SUBSTITUTE(prevWBS,".","`",1)))&IF(ISERROR(FIND("`",SUBSTITUTE(prevWBS,".","`",2))),VALUE(RIGHT(prevWBS,LEN(prevWBS)-FIND("`",SUBSTITUTE(prevWBS,".","`",1))))+1,VALUE(MID(prevWBS,FIND("`",SUBSTITUTE(prevWBS,".","`",1))+1,(FIND("`",SUBSTITUTE(prevWBS,".","`",2))-FIND("`",SUBSTITUTE(prevWBS,".","`",1))-1)))+1))) -> 1.38 | B46: REPORT CANCEL KAIN KELUAR | C46: Budi | E46: =F43+1 -> 46087 | F46: =IF(ISBLANK(E46)," - ",IF(G46=0,E46,E46+G46-1)) -> 46090 | G46: 4 | H46: 0 | I46: =IF(OR(F46=0,E46=0)," - ",NETWORKDAYS(E46,F46)) -> 2
A47: =IF(ISERROR(VALUE(SUBSTITUTE(prevWBS,".",""))),"0.1",IF(ISERROR(FIND("`",SUBSTITUTE(prevWBS,".","`",1))),prevWBS&".1",LEFT(prevWBS,FIND("`",SUBSTITUTE(prevWBS,".","`",1)))&IF(ISERROR(FIND("`",SUBSTITUTE(prevWBS,".","`",2))),VALUE(RIGHT(prevWBS,LEN(prevWBS)-FIND("`",SUBSTITUTE(prevWBS,".","`",1))))+1,VALUE(MID(prevWBS,FIND("`",SUBSTITUTE(prevWBS,".","`",1))+1,(FIND("`",SUBSTITUTE(prevWBS,".","`",2))-FIND("`",SUBSTITUTE(prevWBS,".","`",1))-1)))+1))) -> 1.39 | B47: REPORT CANCEL KAIN MASUK | C47: Baim | E47: =F44+1 -> 46087 | F47: =IF(ISBLANK(E47)," - ",IF(G47=0,E47,E47+G47-1)) -> 46090 | G47: 4 | H47: 0 | I47: =IF(OR(F47=0,E47=0)," - ",NETWORKDAYS(E47,F47)) -> 2
A48: =IF(ISERROR(VALUE(SUBSTITUTE(prevWBS,".",""))),"0.1",IF(ISERROR(FIND("`",SUBSTITUTE(prevWBS,".","`",1))),prevWBS&".1",LEFT(prevWBS,FIND("`",SUBSTITUTE(prevWBS,".","`",1)))&IF(ISERROR(FIND("`",SUBSTITUTE(prevWBS,".","`",2))),VALUE(RIGHT(prevWBS,LEN(prevWBS)-FIND("`",SUBSTITUTE(prevWBS,".","`",1))))+1,VALUE(MID(prevWBS,FIND("`",SUBSTITUTE(prevWBS,".","`",1))+1,(FIND("`",SUBSTITUTE(prevWBS,".","`",2))-FIND("`",SUBSTITUTE(prevWBS,".","`",1))-1)))+1))) -> 1.40 | B48: REPORT COSTING ? | C48: Budi | E48: =F46+1 -> 46091 | F48: =IF(ISBLANK(E48)," - ",IF(G48=0,E48,E48+G48-1)) -> 46092 | G48: 2 | H48: 0 | I48: =IF(OR(F48=0,E48=0)," - ",NETWORKDAYS(E48,F48)) -> 2
A49: =IF(ISERROR(VALUE(SUBSTITUTE(prevWBS,".",""))),"0.1",IF(ISERROR(FIND("`",SUBSTITUTE(prevWBS,".","`",1))),prevWBS&".1",LEFT(prevWBS,FIND("`",SUBSTITUTE(prevWBS,".","`",1)))&IF(ISERROR(FIND("`",SUBSTITUTE(prevWBS,".","`",2))),VALUE(RIGHT(prevWBS,LEN(prevWBS)-FIND("`",SUBSTITUTE(prevWBS,".","`",1))))+1,VALUE(MID(prevWBS,FIND("`",SUBSTITUTE(prevWBS,".","`",1))+1,(FIND("`",SUBSTITUTE(prevWBS,".","`",2))-FIND("`",SUBSTITUTE(prevWBS,".","`",1))-1)))+1))) -> 1.41 | B49: REPORT PEMARTAIAN | C49: Jali | E49: =F47+1 -> 46091 | F49: =IF(ISBLANK(E49)," - ",IF(G49=0,E49,E49+G49-1)) -> 46092 | G49: 2 | H49: 0 | I49: =IF(OR(F49=0,E49=0)," - ",NETWORKDAYS(E49,F49)) -> 2
A50: =IF(ISERROR(VALUE(SUBSTITUTE(prevWBS,".",""))),"0.1",IF(ISERROR(FIND("`",SUBSTITUTE(prevWBS,".","`",1))),prevWBS&".1",LEFT(prevWBS,FIND("`",SUBSTITUTE(prevWBS,".","`",1)))&IF(ISERROR(FIND("`",SUBSTITUTE(prevWBS,".","`",2))),VALUE(RIGHT(prevWBS,LEN(prevWBS)-FIND("`",SUBSTITUTE(prevWBS,".","`",1))))+1,VALUE(MID(prevWBS,FIND("`",SUBSTITUTE(prevWBS,".","`",1))+1,(FIND("`",SUBSTITUTE(prevWBS,".","`",2))-FIND("`",SUBSTITUTE(prevWBS,".","`",1))-1)))+1))) -> 1.42 | B50: REPORT RESERVASI | C50: Budi | E50: =F48+1 -> 46093 | F50: =IF(ISBLANK(E50)," - ",IF(G50=0,E50,E50+G50-1)) -> 46094 | G50: 2 | H50: 0 | I50: =IF(OR(F50=0,E50=0)," - ",NETWORKDAYS(E50,F50)) -> 2
A51: =IF(ISERROR(VALUE(SUBSTITUTE(prevWBS,".",""))),"0.1",IF(ISERROR(FIND("`",SUBSTITUTE(prevWBS,".","`",1))),prevWBS&".1",LEFT(prevWBS,FIND("`",SUBSTITUTE(prevWBS,".","`",1)))&IF(ISERROR(FIND("`",SUBSTITUTE(prevWBS,".","`",2))),VALUE(RIGHT(prevWBS,LEN(prevWBS)-FIND("`",SUBSTITUTE(prevWBS,".","`",1))))+1,VALUE(MID(prevWBS,FIND("`",SUBSTITUTE(prevWBS,".","`",1))+1,(FIND("`",SUBSTITUTE(prevWBS,".","`",2))-FIND("`",SUBSTITUTE(prevWBS,".","`",1))-1)))+1))) -> 1.43 | B51: REPORT RESUME KODE PARTAI | C51: Jali | E51: =F49+1 -> 46093 | F51: =IF(ISBLANK(E51)," - ",IF(G51=0,E51,E51+G51-1)) -> 46094 | G51: 2 | H51: 0 | I51: =IF(OR(F51=0,E51=0)," - ",NETWORKDAYS(E51,F51)) -> 2
A52: =IF(ISERROR(VALUE(SUBSTITUTE(prevWBS,".",""))),"0.1",IF(ISERROR(FIND("`",SUBSTITUTE(prevWBS,".","`",1))),prevWBS&".1",LEFT(prevWBS,FIND("`",SUBSTITUTE(prevWBS,".","`",1)))&IF(ISERROR(FIND("`",SUBSTITUTE(prevWBS,".","`",2))),VALUE(RIGHT(prevWBS,LEN(prevWBS)-FIND("`",SUBSTITUTE(prevWBS,".","`",1))))+1,VALUE(MID(prevWBS,FIND("`",SUBSTITUTE(prevWBS,".","`",1))+1,(FIND("`",SUBSTITUTE(prevWBS,".","`",2))-FIND("`",SUBSTITUTE(prevWBS,".","`",1))-1)))+1))) -> 1.44 | B52: STK BLANK GD. PACKING | C52: Budi | E52: =F50+1 -> 46095 | F52: =IF(ISBLANK(E52)," - ",IF(G52=0,E52,E52+G52-1)) -> 46098 | G52: 4 | H52: 0 | I52: =IF(OR(F52=0,E52=0)," - ",NETWORKDAYS(E52,F52)) -> 2
A53: =IF(ISERROR(VALUE(SUBSTITUTE(prevWBS,".",""))),"0.1",IF(ISERROR(FIND("`",SUBSTITUTE(prevWBS,".","`",1))),prevWBS&".1",LEFT(prevWBS,FIND("`",SUBSTITUTE(prevWBS,".","`",1)))&IF(ISERROR(FIND("`",SUBSTITUTE(prevWBS,".","`",2))),VALUE(RIGHT(prevWBS,LEN(prevWBS)-FIND("`",SUBSTITUTE(prevWBS,".","`",1))))+1,VALUE(MID(prevWBS,FIND("`",SUBSTITUTE(prevWBS,".","`",1))+1,(FIND("`",SUBSTITUTE(prevWBS,".","`",2))-FIND("`",SUBSTITUTE(prevWBS,".","`",1))-1)))+1))) -> 1.45 | B53: STOCK BALANCE KAIN GREY | C53: Jali | E53: =F51+1 -> 46095 | F53: =IF(ISBLANK(E53)," - ",IF(G53=0,E53,E53+G53-1)) -> 46098 | G53: 4 | H53: 0 | I53: =IF(OR(F53=0,E53=0)," - ",NETWORKDAYS(E53,F53)) -> 2
A54: =IF(ISERROR(VALUE(SUBSTITUTE(prevWBS,".",""))),"0.1",IF(ISERROR(FIND("`",SUBSTITUTE(prevWBS,".","`",1))),prevWBS&".1",LEFT(prevWBS,FIND("`",SUBSTITUTE(prevWBS,".","`",1)))&IF(ISERROR(FIND("`",SUBSTITUTE(prevWBS,".","`",2))),VALUE(RIGHT(prevWBS,LEN(prevWBS)-FIND("`",SUBSTITUTE(prevWBS,".","`",1))))+1,VALUE(MID(prevWBS,FIND("`",SUBSTITUTE(prevWBS,".","`",1))+1,(FIND("`",SUBSTITUTE(prevWBS,".","`",2))-FIND("`",SUBSTITUTE(prevWBS,".","`",1))-1)))+1))) -> 1.46 | B54: STOCK GREY LEAD TIME PER GRADE | C54: Budi | E54: =F52+10 -> 46108 | F54: =IF(ISBLANK(E54)," - ",IF(G54=0,E54,E54+G54-1)) -> 46111 | G54: 4 | H54: 0 | I54: =IF(OR(F54=0,E54=0)," - ",NETWORKDAYS(E54,F54)) -> 2
A55: =IF(ISERROR(VALUE(SUBSTITUTE(prevWBS,".",""))),"0.1",IF(ISERROR(FIND("`",SUBSTITUTE(prevWBS,".","`",1))),prevWBS&".1",LEFT(prevWBS,FIND("`",SUBSTITUTE(prevWBS,".","`",1)))&IF(ISERROR(FIND("`",SUBSTITUTE(prevWBS,".","`",2))),VALUE(RIGHT(prevWBS,LEN(prevWBS)-FIND("`",SUBSTITUTE(prevWBS,".","`",1))))+1,VALUE(MID(prevWBS,FIND("`",SUBSTITUTE(prevWBS,".","`",1))+1,(FIND("`",SUBSTITUTE(prevWBS,".","`",2))-FIND("`",SUBSTITUTE(prevWBS,".","`",1))-1)))+1))) -> 1.47 | B55: STOCK KAIN GREY (GRADE) | C55: Jali | E55: =F53+10 -> 46108 | F55: =IF(ISBLANK(E55)," - ",IF(G55=0,E55,E55+G55-1)) -> 46111 | G55: 4 | H55: 0 | I55: =IF(OR(F55=0,E55=0)," - ",NETWORKDAYS(E55,F55)) -> 2
A56: =IF(ISERROR(VALUE(SUBSTITUTE(prevWBS,".",""))),"0.1",IF(ISERROR(FIND("`",SUBSTITUTE(prevWBS,".","`",1))),prevWBS&".1",LEFT(prevWBS,FIND("`",SUBSTITUTE(prevWBS,".","`",1)))&IF(ISERROR(FIND("`",SUBSTITUTE(prevWBS,".","`",2))),VALUE(RIGHT(prevWBS,LEN(prevWBS)-FIND("`",SUBSTITUTE(prevWBS,".","`",1))))+1,VALUE(MID(prevWBS,FIND("`",SUBSTITUTE(prevWBS,".","`",1))+1,(FIND("`",SUBSTITUTE(prevWBS,".","`",2))-FIND("`",SUBSTITUTE(prevWBS,".","`",1))-1)))+1))) -> 1.48 | B56: STOCK KAIN GREY (LW 22) | C56: Budi | E56: =F54+1 -> 46112 | F56: =IF(ISBLANK(E56)," - ",IF(G56=0,E56,E56+G56-1)) -> 46113 | G56: 2 | H56: 0 | I56: =IF(OR(F56=0,E56=0)," - ",NETWORKDAYS(E56,F56)) -> 2
A57: =IF(ISERROR(VALUE(SUBSTITUTE(prevWBS,".",""))),"0.1",IF(ISERROR(FIND("`",SUBSTITUTE(prevWBS,".","`",1))),prevWBS&".1",LEFT(prevWBS,FIND("`",SUBSTITUTE(prevWBS,".","`",1)))&IF(ISERROR(FIND("`",SUBSTITUTE(prevWBS,".","`",2))),VALUE(RIGHT(prevWBS,LEN(prevWBS)-FIND("`",SUBSTITUTE(prevWBS,".","`",1))))+1,VALUE(MID(prevWBS,FIND("`",SUBSTITUTE(prevWBS,".","`",1))+1,(FIND("`",SUBSTITUTE(prevWBS,".","`",2))-FIND("`",SUBSTITUTE(prevWBS,".","`",1))-1)))+1))) -> 1.49 | B57: STOCK KAIN PASIF (ALL AREA) | C57: Jali | E57: =F55+1 -> 46112 | F57: =IF(ISBLANK(E57)," - ",IF(G57=0,E57,E57+G57-1)) -> 46113 | G57: 2 | H57: 0 | I57: =IF(OR(F57=0,E57=0)," - ",NETWORKDAYS(E57,F57)) -> 2
A58: =IF(ISERROR(VALUE(SUBSTITUTE(prevWBS,".",""))),"0.1",IF(ISERROR(FIND("`",SUBSTITUTE(prevWBS,".","`",1))),prevWBS&".1",LEFT(prevWBS,FIND("`",SUBSTITUTE(prevWBS,".","`",1)))&IF(ISERROR(FIND("`",SUBSTITUTE(prevWBS,".","`",2))),VALUE(RIGHT(prevWBS,LEN(prevWBS)-FIND("`",SUBSTITUTE(prevWBS,".","`",1))))+1,VALUE(MID(prevWBS,FIND("`",SUBSTITUTE(prevWBS,".","`",1))+1,(FIND("`",SUBSTITUTE(prevWBS,".","`",2))-FIND("`",SUBSTITUTE(prevWBS,".","`",1))-1)))+1))) -> 1.50 | B58: STOCK LEADTIME | C58: Jali | E58: =F56+1 -> 46114 | F58: =IF(ISBLANK(E58)," - ",IF(G58=0,E58,E58+G58-1)) -> 46115 | G58: 2 | H58: 0 | I58: =IF(OR(F58=0,E58=0)," - ",NETWORKDAYS(E58,F58)) -> 2
A59: =IF(ISERROR(VALUE(SUBSTITUTE(prevWBS,".",""))),"0.1",IF(ISERROR(FIND("`",SUBSTITUTE(prevWBS,".","`",1))),prevWBS&".1",LEFT(prevWBS,FIND("`",SUBSTITUTE(prevWBS,".","`",1)))&IF(ISERROR(FIND("`",SUBSTITUTE(prevWBS,".","`",2))),VALUE(RIGHT(prevWBS,LEN(prevWBS)-FIND("`",SUBSTITUTE(prevWBS,".","`",1))))+1,VALUE(MID(prevWBS,FIND("`",SUBSTITUTE(prevWBS,".","`",1))+1,(FIND("`",SUBSTITUTE(prevWBS,".","`",2))-FIND("`",SUBSTITUTE(prevWBS,".","`",1))-1)))+1))) -> 1.51 | B59: MOVING HISTORY PER LIST BARCODE | C59: Star | E59: =F57+1 -> 46114 | F59: =IF(ISBLANK(E59)," - ",IF(G59=0,E59,E59+G59-1)) -> 46115 | G59: 2 | H59: 0 | I59: =IF(OR(F59=0,E59=0)," - ",NETWORKDAYS(E59,F59)) -> 2
A60: =IF(ISERROR(VALUE(SUBSTITUTE(prevWBS,".",""))),"0.1",IF(ISERROR(FIND("`",SUBSTITUTE(prevWBS,".","`",1))),prevWBS&".1",LEFT(prevWBS,FIND("`",SUBSTITUTE(prevWBS,".","`",1)))&IF(ISERROR(FIND("`",SUBSTITUTE(prevWBS,".","`",2))),VALUE(RIGHT(prevWBS,LEN(prevWBS)-FIND("`",SUBSTITUTE(prevWBS,".","`",1))))+1,VALUE(MID(prevWBS,FIND("`",SUBSTITUTE(prevWBS,".","`",1))+1,(FIND("`",SUBSTITUTE(prevWBS,".","`",2))-FIND("`",SUBSTITUTE(prevWBS,".","`",1))-1)))+1))) -> 1.52 | B60: MOVING HISTORY - GUDANG GREY | C60: Budi | E60: =F58+1 -> 46116 | F60: =IF(ISBLANK(E60)," - ",IF(G60=0,E60,E60+G60-1)) -> 46119 | G60: 4 | H60: 0 | I60: =IF(OR(F60=0,E60=0)," - ",NETWORKDAYS(E60,F60)) -> 2
A76: =IF(ISERROR(VALUE(SUBSTITUTE(prevWBS,".",""))),"1",IF(ISERROR(FIND("`",SUBSTITUTE(prevWBS,".","`",1))),TEXT(VALUE(prevWBS)+1,"#"),TEXT(VALUE(LEFT(prevWBS,FIND("`",SUBSTITUTE(prevWBS,".","`",1))-1))+1,"#"))) -> 1 | B76: Report | F76: =IF(ISBLANK(E76)," - ",IF(G76=0,E76,E76+G76-1)) -> - | I76: =IF(OR(F76=0,E76=0)," - ",NETWORKDAYS(E76,F76)) -> -
A77: =IF(ISERROR(VALUE(SUBSTITUTE(prevWBS,".",""))),"0.1",IF(ISERROR(FIND("`",SUBSTITUTE(prevWBS,".","`",1))),prevWBS&".1",LEFT(prevWBS,FIND("`",SUBSTITUTE(prevWBS,".","`",1)))&IF(ISERROR(FIND("`",SUBSTITUTE(prevWBS,".","`",2))),VALUE(RIGHT(prevWBS,LEN(prevWBS)-FIND("`",SUBSTITUTE(prevWBS,".","`",1))))+1,VALUE(MID(prevWBS,FIND("`",SUBSTITUTE(prevWBS,".","`",1))+1,(FIND("`",SUBSTITUTE(prevWBS,".","`",2))-FIND("`",SUBSTITUTE(prevWBS,".","`",1))-1)))+1))) -> 1.1 | B77: REPORT - WM - MOVING HISTORY - GUDANG GREY | C77: Billy, Baim | E77: 46057 | F77: =IF(ISBLANK(E77)," - ",IF(G77=0,E77,E77+G77-1)) -> 46063 | G77: 7 | H77: 0 | I77: =IF(OR(F77=0,E77=0)," - ",NETWORKDAYS(E77,F77)) -> 5
A78: =IF(ISERROR(VALUE(SUBSTITUTE(prevWBS,".",""))),"0.1",IF(ISERROR(FIND("`",SUBSTITUTE(prevWBS,".","`",1))),prevWBS&".1",LEFT(prevWBS,FIND("`",SUBSTITUTE(prevWBS,".","`",1)))&IF(ISERROR(FIND("`",SUBSTITUTE(prevWBS,".","`",2))),VALUE(RIGHT(prevWBS,LEN(prevWBS)-FIND("`",SUBSTITUTE(prevWBS,".","`",1))))+1,VALUE(MID(prevWBS,FIND("`",SUBSTITUTE(prevWBS,".","`",1))+1,(FIND("`",SUBSTITUTE(prevWBS,".","`",2))-FIND("`",SUBSTITUTE(prevWBS,".","`",1))-1)))+1))) -> 1.2 | B78: REPORT - WM - STOCK PER BARCODE | C78: Baim | E78: 46064 | F78: =IF(ISBLANK(E78)," - ",IF(G78=0,E78,E78+G78-1)) -> 46070 | G78: 7 | H78: 0 | I78: =IF(OR(F78=0,E78=0)," - ",NETWORKDAYS(E78,F78)) -> 5
A79: =IF(ISERROR(VALUE(SUBSTITUTE(prevWBS,".",""))),"0.1",IF(ISERROR(FIND("`",SUBSTITUTE(prevWBS,".","`",1))),prevWBS&".1",LEFT(prevWBS,FIND("`",SUBSTITUTE(prevWBS,".","`",1)))&IF(ISERROR(FIND("`",SUBSTITUTE(prevWBS,".","`",2))),VALUE(RIGHT(prevWBS,LEN(prevWBS)-FIND("`",SUBSTITUTE(prevWBS,".","`",1))))+1,VALUE(MID(prevWBS,FIND("`",SUBSTITUTE(prevWBS,".","`",1))+1,(FIND("`",SUBSTITUTE(prevWBS,".","`",2))-FIND("`",SUBSTITUTE(prevWBS,".","`",1))-1)))+1))) -> 1.3 | B79: REPORT - WM - LAPORAN PERSEDIAAN GUDANG PACKING | C79: Budi | E79: 46064 | F79: =IF(ISBLANK(E79)," - ",IF(G79=0,E79,E79+G79-1)) -> 46070 | G79: 7 | H79: 0 | I79: =IF(OR(F79=0,E79=0)," - ",NETWORKDAYS(E79,F79)) -> 5
A80: =IF(ISERROR(VALUE(SUBSTITUTE(prevWBS,".",""))),"0.1",IF(ISERROR(FIND("`",SUBSTITUTE(prevWBS,".","`",1))),prevWBS&".1",LEFT(prevWBS,FIND("`",SUBSTITUTE(prevWBS,".","`",1)))&IF(ISERROR(FIND("`",SUBSTITUTE(prevWBS,".","`",2))),VALUE(RIGHT(prevWBS,LEN(prevWBS)-FIND("`",SUBSTITUTE(prevWBS,".","`",1))))+1,VALUE(MID(prevWBS,FIND("`",SUBSTITUTE(prevWBS,".","`",1))+1,(FIND("`",SUBSTITUTE(prevWBS,".","`",2))-FIND("`",SUBSTITUTE(prevWBS,".","`",1))-1)))+1))) -> 1.4 | B80: REPORT - WM - LAPORAN GUDANG PACKING LEAD TIME | C80: Baim | E80: 46071 | F80: =IF(ISBLANK(E80)," - ",IF(G80=0,E80,E80+G80-1)) -> 46077 | G80: 7 | H80: 0 | I80: =IF(OR(F80=0,E80=0)," - ",NETWORKDAYS(E80,F80)) -> 5
A81: =IF(ISERROR(VALUE(SUBSTITUTE(prevWBS,".",""))),"0.1",IF(ISERROR(FIND("`",SUBSTITUTE(prevWBS,".","`",1))),prevWBS&".1",LEFT(prevWBS,FIND("`",SUBSTITUTE(prevWBS,".","`",1)))&IF(ISERROR(FIND("`",SUBSTITUTE(prevWBS,".","`",2))),VALUE(RIGHT(prevWBS,LEN(prevWBS)-FIND("`",SUBSTITUTE(prevWBS,".","`",1))))+1,VALUE(MID(prevWBS,FIND("`",SUBSTITUTE(prevWBS,".","`",1))+1,(FIND("`",SUBSTITUTE(prevWBS,".","`",2))-FIND("`",SUBSTITUTE(prevWBS,".","`",1))-1)))+1))) -> 1.5 | B81: REPORT - WM - LIST KARTON PER KODE ORDER | C81: Budi | E81: 46071 | F81: =IF(ISBLANK(E81)," - ",IF(G81=0,E81,E81+G81-1)) -> 46077 | G81: 7 | H81: 0 | I81: =IF(OR(F81=0,E81=0)," - ",NETWORKDAYS(E81,F81)) -> 5
A82: =IF(ISERROR(VALUE(SUBSTITUTE(prevWBS,".",""))),"0.1",IF(ISERROR(FIND("`",SUBSTITUTE(prevWBS,".","`",1))),prevWBS&".1",LEFT(prevWBS,FIND("`",SUBSTITUTE(prevWBS,".","`",1)))&IF(ISERROR(FIND("`",SUBSTITUTE(prevWBS,".","`",2))),VALUE(RIGHT(prevWBS,LEN(prevWBS)-FIND("`",SUBSTITUTE(prevWBS,".","`",1))))+1,VALUE(MID(prevWBS,FIND("`",SUBSTITUTE(prevWBS,".","`",1))+1,(FIND("`",SUBSTITUTE(prevWBS,".","`",2))-FIND("`",SUBSTITUTE(prevWBS,".","`",1))-1)))+1))) -> 1.6 | B82: REPORT - WM - MOVING HISTORY PER BARCODE | C82: Baim | E82: 46078 | F82: =IF(ISBLANK(E82)," - ",IF(G82=0,E82,E82+G82-1)) -> 46084 | G82: 7 | H82: 0 | I82: =IF(OR(F82=0,E82=0)," - ",NETWORKDAYS(E82,F82)) -> 5
A83: =IF(ISERROR(VALUE(SUBSTITUTE(prevWBS,".",""))),"0.1",IF(ISERROR(FIND("`",SUBSTITUTE(prevWBS,".","`",1))),prevWBS&".1",LEFT(prevWBS,FIND("`",SUBSTITUTE(prevWBS,".","`",1)))&IF(ISERROR(FIND("`",SUBSTITUTE(prevWBS,".","`",2))),VALUE(RIGHT(prevWBS,LEN(prevWBS)-FIND("`",SUBSTITUTE(prevWBS,".","`",1))))+1,VALUE(MID(prevWBS,FIND("`",SUBSTITUTE(prevWBS,".","`",1))+1,(FIND("`",SUBSTITUTE(prevWBS,".","`",2))-FIND("`",SUBSTITUTE(prevWBS,".","`",1))-1)))+1))) -> 1.7 | B83: REPORT - WM - MOVING HISTORY PER LIST KARTON | C83: Budi | E83: 46078 | F83: =IF(ISBLANK(E83)," - ",IF(G83=0,E83,E83+G83-1)) -> 46084 | G83: 7 | H83: 0 | I83: =IF(OR(F83=0,E83=0)," - ",NETWORKDAYS(E83,F83)) -> 5
A84: =IF(ISERROR(VALUE(SUBSTITUTE(prevWBS,".",""))),"0.1",IF(ISERROR(FIND("`",SUBSTITUTE(prevWBS,".","`",1))),prevWBS&".1",LEFT(prevWBS,FIND("`",SUBSTITUTE(prevWBS,".","`",1)))&IF(ISERROR(FIND("`",SUBSTITUTE(prevWBS,".","`",2))),VALUE(RIGHT(prevWBS,LEN(prevWBS)-FIND("`",SUBSTITUTE(prevWBS,".","`",1))))+1,VALUE(MID(prevWBS,FIND("`",SUBSTITUTE(prevWBS,".","`",1))+1,(FIND("`",SUBSTITUTE(prevWBS,".","`",2))-FIND("`",SUBSTITUTE(prevWBS,".","`",1))-1)))+1))) -> 1.8 | B84: REPORT - MM - STOCK KAIN GREY (GRADE) | C84: Billy, Budi | E84: 46057 | F84: =IF(ISBLANK(E84)," - ",IF(G84=0,E84,E84+G84-1)) -> 46063 | G84: 7 | H84: 0 | I84: =IF(OR(F84=0,E84=0)," - ",NETWORKDAYS(E84,F84)) -> 5
A85: =IF(ISERROR(VALUE(SUBSTITUTE(prevWBS,".",""))),"0.1",IF(ISERROR(FIND("`",SUBSTITUTE(prevWBS,".","`",1))),prevWBS&".1",LEFT(prevWBS,FIND("`",SUBSTITUTE(prevWBS,".","`",1)))&IF(ISERROR(FIND("`",SUBSTITUTE(prevWBS,".","`",2))),VALUE(RIGHT(prevWBS,LEN(prevWBS)-FIND("`",SUBSTITUTE(prevWBS,".","`",1))))+1,VALUE(MID(prevWBS,FIND("`",SUBSTITUTE(prevWBS,".","`",1))+1,(FIND("`",SUBSTITUTE(prevWBS,".","`",2))-FIND("`",SUBSTITUTE(prevWBS,".","`",1))-1)))+1))) -> 1.9 | B85: REPORT - MM - STOCK LEADTIME | C85: Baim | E85: 46085 | F85: =IF(ISBLANK(E85)," - ",IF(G85=0,E85,E85+G85-1)) -> 46091 | G85: 7 | H85: 0 | I85: =IF(OR(F85=0,E85=0)," - ",NETWORKDAYS(E85,F85)) -> 5
A86: =IF(ISERROR(VALUE(SUBSTITUTE(prevWBS,".",""))),"0.1",IF(ISERROR(FIND("`",SUBSTITUTE(prevWBS,".","`",1))),prevWBS&".1",LEFT(prevWBS,FIND("`",SUBSTITUTE(prevWBS,".","`",1)))&IF(ISERROR(FIND("`",SUBSTITUTE(prevWBS,".","`",2))),VALUE(RIGHT(prevWBS,LEN(prevWBS)-FIND("`",SUBSTITUTE(prevWBS,".","`",1))))+1,VALUE(MID(prevWBS,FIND("`",SUBSTITUTE(prevWBS,".","`",1))+1,(FIND("`",SUBSTITUTE(prevWBS,".","`",2))-FIND("`",SUBSTITUTE(prevWBS,".","`",1))-1)))+1))) -> 1.10 | B86: REPORT - MM - STOCK GREY LEAD TIME PER GRADE | C86: Budi | E86: 46085 | F86: =IF(ISBLANK(E86)," - ",IF(G86=0,E86,E86+G86-1)) -> 46091 | G86: 7 | H86: 0 | I86: =IF(OR(F86=0,E86=0)," - ",NETWORKDAYS(E86,F86)) -> 5
A87: =IF(ISERROR(VALUE(SUBSTITUTE(prevWBS,".",""))),"0.1",IF(ISERROR(FIND("`",SUBSTITUTE(prevWBS,".","`",1))),prevWBS&".1",LEFT(prevWBS,FIND("`",SUBSTITUTE(prevWBS,".","`",1)))&IF(ISERROR(FIND("`",SUBSTITUTE(prevWBS,".","`",2))),VALUE(RIGHT(prevWBS,LEN(prevWBS)-FIND("`",SUBSTITUTE(prevWBS,".","`",1))))+1,VALUE(MID(prevWBS,FIND("`",SUBSTITUTE(prevWBS,".","`",1))+1,(FIND("`",SUBSTITUTE(prevWBS,".","`",2))-FIND("`",SUBSTITUTE(prevWBS,".","`",1))-1)))+1))) -> 1.11 | B87: REPORT - MM - STOCK BALANCE KAIN GREY | C87: Budi | E87: 46092 | F87: =IF(ISBLANK(E87)," - ",IF(G87=0,E87,E87+G87-1)) -> 46098 | G87: 7 | H87: 0 | I87: =IF(OR(F87=0,E87=0)," - ",NETWORKDAYS(E87,F87)) -> 5
A88: =IF(ISERROR(VALUE(SUBSTITUTE(prevWBS,".",""))),"0.1",IF(ISERROR(FIND("`",SUBSTITUTE(prevWBS,".","`",1))),prevWBS&".1",LEFT(prevWBS,FIND("`",SUBSTITUTE(prevWBS,".","`",1)))&IF(ISERROR(FIND("`",SUBSTITUTE(prevWBS,".","`",2))),VALUE(RIGHT(prevWBS,LEN(prevWBS)-FIND("`",SUBSTITUTE(prevWBS,".","`",1))))+1,VALUE(MID(prevWBS,FIND("`",SUBSTITUTE(prevWBS,".","`",1))+1,(FIND("`",SUBSTITUTE(prevWBS,".","`",2))-FIND("`",SUBSTITUTE(prevWBS,".","`",1))-1)))+1))) -> 1.12 | B88: REPORT - MM - STOCK KAIN PASIF (ALL AREA) | C88: Baim | E88: 46092 | F88: =IF(ISBLANK(E88)," - ",IF(G88=0,E88,E88+G88-1)) -> 46098 | G88: 7 | H88: 0 | I88: =IF(OR(F88=0,E88=0)," - ",NETWORKDAYS(E88,F88)) -> 5
... A103: =IF(ISERROR(VALUE(SUBSTITUTE(prevWBS,".",""))),"0.1",IF(ISERROR(FIND("`",SUBSTITUTE(prevWBS,".","`",1))),prevWBS&".1",LEFT(prevWBS,FIND("`",SUBSTITUTE(prevWBS,".","`",1)))&IF(ISERROR(FIND("`",SUBSTITUTE(prevWBS,".","`",2))),VALUE(RIGHT(prevWBS,LEN(prevWBS)-FIND("`",SUBSTITUTE(prevWBS,".","`",1))))+1,VALUE(MID(prevWBS,FIND("`",SUBSTITUTE(prevWBS,".","`",1))+1,(FIND("`",SUBSTITUTE(prevWBS,".","`",2))-FIND("`",SUBSTITUTE(prevWBS,".","`",1))-1)))+1))) -> 1.27 | B103: REPORT - MM - STK Blank Gd. Packing | C103: Budi | E103: 46148 | F103: =IF(ISBLANK(E103)," - ",IF(G103=0,E103,E103+G103-1)) -> 46154 | G103: 7 | H103: 0 | I103: =IF(OR(F103=0,E103=0)," - ",NETWORKDAYS(E103,F103)) -> 5
A104: =IF(ISERROR(VALUE(SUBSTITUTE(prevWBS,".",""))),"1",IF(ISERROR(FIND("`",SUBSTITUTE(prevWBS,".","`",1))),TEXT(VALUE(prevWBS)+1,"#"),TEXT(VALUE(LEFT(prevWBS,FIND("`",SUBSTITUTE(prevWBS,".","`",1))-1))+1,"#"))) -> 2 | B104: Interfaces | F104: =IF(ISBLANK(E104)," - ",IF(G104=0,E104,E104+G104-1)) -> - | I104: =IF(OR(F104=0,E104=0)," - ",NETWORKDAYS(E104,F104)) -> -
A105: =IF(ISERROR(VALUE(SUBSTITUTE(prevWBS,".",""))),"0.1",IF(ISERROR(FIND("`",SUBSTITUTE(prevWBS,".","`",1))),prevWBS&".1",LEFT(prevWBS,FIND("`",SUBSTITUTE(prevWBS,".","`",1)))&IF(ISERROR(FIND("`",SUBSTITUTE(prevWBS,".","`",2))),VALUE(RIGHT(prevWBS,LEN(prevWBS)-FIND("`",SUBSTITUTE(prevWBS,".","`",1))))+1,VALUE(MID(prevWBS,FIND("`",SUBSTITUTE(prevWBS,".","`",1))+1,(FIND("`",SUBSTITUTE(prevWBS,".","`",2))-FIND("`",SUBSTITUTE(prevWBS,".","`",1))-1)))+1))) -> 2.1 | B105: INTERFACE BEA CUKAI | C105: Billy, Budi | E105: 46034 | F105: =IF(ISBLANK(E105)," - ",IF(G105=0,E105,E105+G105-1)) -> 46038 | G105: 5 | H105: 0 | I105: =IF(OR(F105=0,E105=0)," - ",NETWORKDAYS(E105,F105)) -> 5
A106: =IF(ISERROR(VALUE(SUBSTITUTE(prevWBS,".",""))),"0.1",IF(ISERROR(FIND("`",SUBSTITUTE(prevWBS,".","`",1))),prevWBS&".1",LEFT(prevWBS,FIND("`",SUBSTITUTE(prevWBS,".","`",1)))&IF(ISERROR(FIND("`",SUBSTITUTE(prevWBS,".","`",2))),VALUE(RIGHT(prevWBS,LEN(prevWBS)-FIND("`",SUBSTITUTE(prevWBS,".","`",1))))+1,VALUE(MID(prevWBS,FIND("`",SUBSTITUTE(prevWBS,".","`",1))+1,(FIND("`",SUBSTITUTE(prevWBS,".","`",2))-FIND("`",SUBSTITUTE(prevWBS,".","`",1))-1)))+1))) -> 2.2 | B106: INTERFACE PRINT BARCODE | C106: Billy, Baim, Budi | E106: 46023 | F106: =IF(ISBLANK(E106)," - ",IF(G106=0,E106,E106+G106-1)) -> 46032 | G106: 10 | H106: 0 | I106: 6
A107: =IF(ISERROR(VALUE(SUBSTITUTE(prevWBS,".",""))),"0.1",IF(ISERROR(FIND("`",SUBSTITUTE(prevWBS,".","`",1))),prevWBS&".1",LEFT(prevWBS,FIND("`",SUBSTITUTE(prevWBS,".","`",1)))&IF(ISERROR(FIND("`",SUBSTITUTE(prevWBS,".","`",2))),VALUE(RIGHT(prevWBS,LEN(prevWBS)-FIND("`",SUBSTITUTE(prevWBS,".","`",1))))+1,VALUE(MID(prevWBS,FIND("`",SUBSTITUTE(prevWBS,".","`",1))+1,(FIND("`",SUBSTITUTE(prevWBS,".","`",2))-FIND("`",SUBSTITUTE(prevWBS,".","`",1))-1)))+1))) -> 2.3 | B107: INTERFACE PRINT BARCODE BANYAK LIST KARTON | C107: Billy, Baim | E107: 46034 | F107: =IF(ISBLANK(E107)," - ",IF(G107=0,E107,E107+G107-1)) -> 46038 | G107: 5 | H107: 0 | I107: 5
A108: =IF(ISERROR(VALUE(SUBSTITUTE(prevWBS,".",""))),"1",IF(ISERROR(FIND("`",SUBSTITUTE(prevWBS,".","`",1))),TEXT(VALUE(prevWBS)+1,"#"),TEXT(VALUE(LEFT(prevWBS,FIND("`",SUBSTITUTE(prevWBS,".","`",1))-1))+1,"#"))) -> 3 | B108: Forms | F108: =IF(ISBLANK(E108)," - ",IF(G108=0,E108,E108+G108-1)) -> - | I108: =IF(OR(F108=0,E108=0)," - ",NETWORKDAYS(E108,F108)) -> -
A109: =IF(ISERROR(VALUE(SUBSTITUTE(prevWBS,".",""))),"0.1",IF(ISERROR(FIND("`",SUBSTITUTE(prevWBS,".","`",1))),prevWBS&".1",LEFT(prevWBS,FIND("`",SUBSTITUTE(prevWBS,".","`",1)))&IF(ISERROR(FIND("`",SUBSTITUTE(prevWBS,".","`",2))),VALUE(RIGHT(prevWBS,LEN(prevWBS)-FIND("`",SUBSTITUTE(prevWBS,".","`",1))))+1,VALUE(MID(prevWBS,FIND("`",SUBSTITUTE(prevWBS,".","`",1))+1,(FIND("`",SUBSTITUTE(prevWBS,".","`",2))-FIND("`",SUBSTITUTE(prevWBS,".","`",1))-1)))+1))) -> 3.1 | B109: Form Transfer Posting (ZSCMF001) | C109: Billy, Budi | E109: 46041 | F109: =IF(ISBLANK(E109)," - ",IF(G109=0,E109,E109+G109-1)) -> 46044 | G109: 4 | H109: 0 | I109: 4
A110: =IF(ISERROR(VALUE(SUBSTITUTE(prevWBS,".",""))),"0.1",IF(ISERROR(FIND("`",SUBSTITUTE(prevWBS,".","`",1))),prevWBS&".1",LEFT(prevWBS,FIND("`",SUBSTITUTE(prevWBS,".","`",1)))&IF(ISERROR(FIND("`",SUBSTITUTE(prevWBS,".","`",2))),VALUE(RIGHT(prevWBS,LEN(prevWBS)-FIND("`",SUBSTITUTE(prevWBS,".","`",1))))+1,VALUE(MID(prevWBS,FIND("`",SUBSTITUTE(prevWBS,".","`",1))+1,(FIND("`",SUBSTITUTE(prevWBS,".","`",2))-FIND("`",SUBSTITUTE(prevWBS,".","`",1))-1)))+1))) -> 3.2 | B110: Form Purchase Order (ZSCMF002) | C110: Billy, Baim | E110: 46041 | F110: =IF(ISBLANK(E110)," - ",IF(G110=0,E110,E110+G110-1)) -> 46044 | G110: 4 | H110: 0 | I110: 4
A111: =IF(ISERROR(VALUE(SUBSTITUTE(prevWBS,".",""))),"0.1",IF(ISERROR(FIND("`",SUBSTITUTE(prevWBS,".","`",1))),prevWBS&".1",LEFT(prevWBS,FIND("`",SUBSTITUTE(prevWBS,".","`",1)))&IF(ISERROR(FIND("`",SUBSTITUTE(prevWBS,".","`",2))),VALUE(RIGHT(prevWBS,LEN(prevWBS)-FIND("`",SUBSTITUTE(prevWBS,".","`",1))))+1,VALUE(MID(prevWBS,FIND("`",SUBSTITUTE(prevWBS,".","`",1))+1,(FIND("`",SUBSTITUTE(prevWBS,".","`",2))-FIND("`",SUBSTITUTE(prevWBS,".","`",1))-1)))+1))) -> 3.3 | B111: Form Good Receipt (ZSCMF003) | C111: Baim | E111: 46045 | F111: =IF(ISBLANK(E111)," - ",IF(G111=0,E111,E111+G111-1)) -> 46050 | G111: 6 | H111: 0 | I111: 4
A112: =IF(ISERROR(VALUE(SUBSTITUTE(prevWBS,".",""))),"0.1",IF(ISERROR(FIND("`",SUBSTITUTE(prevWBS,".","`",1))),prevWBS&".1",LEFT(prevWBS,FIND("`",SUBSTITUTE(prevWBS,".","`",1)))&IF(ISERROR(FIND("`",SUBSTITUTE(prevWBS,".","`",2))),VALUE(RIGHT(prevWBS,LEN(prevWBS)-FIND("`",SUBSTITUTE(prevWBS,".","`",1))))+1,VALUE(MID(prevWBS,FIND("`",SUBSTITUTE(prevWBS,".","`",1))+1,(FIND("`",SUBSTITUTE(prevWBS,".","`",2))-FIND("`",SUBSTITUTE(prevWBS,".","`",1))-1)))+1))) -> 3.4 | B112: Form Good Issue (ZSCMF004) | C112: Baim | E112: 46051 | F112: =IF(ISBLANK(E112)," - ",IF(G112=0,E112,E112+G112-1)) -> 46056 | G112: 6 | H112: 0 | I112: 4
A113: =IF(ISERROR(VALUE(SUBSTITUTE(prevWBS,".",""))),"0.1",IF(ISERROR(FIND("`",SUBSTITUTE(prevWBS,".","`",1))),prevWBS&".1",LEFT(prevWBS,FIND("`",SUBSTITUTE(prevWBS,".","`",1)))&IF(ISERROR(FIND("`",SUBSTITUTE(prevWBS,".","`",2))),VALUE(RIGHT(prevWBS,LEN(prevWBS)-FIND("`",SUBSTITUTE(prevWBS,".","`",1))))+1,VALUE(MID(prevWBS,FIND("`",SUBSTITUTE(prevWBS,".","`",1))+1,(FIND("`",SUBSTITUTE(prevWBS,".","`",2))-FIND("`",SUBSTITUTE(prevWBS,".","`",1))-1)))+1))) -> 3.5 | B113: Form Bukti Tanda Terima | C113: Budi | E113: 46045 | F113: =IF(ISBLANK(E113)," - ",IF(G113=0,E113,E113+G113-1)) -> 46050 | G113: 6 | H113: 0 | I113: 4
A114: =IF(ISERROR(VALUE(SUBSTITUTE(prevWBS,".",""))),"1",IF(ISERROR(FIND("`",SUBSTITUTE(prevWBS,".","`",1))),TEXT(VALUE(prevWBS)+1,"#"),TEXT(VALUE(LEFT(prevWBS,FIND("`",SUBSTITUTE(prevWBS,".","`",1))-1))+1,"#"))) -> 4 | B114: Enhancement | F114: =IF(ISBLANK(E114)," - ",IF(G114=0,E114,E114+G114-1)) -> - | I114: =IF(OR(F114=0,E114=0)," - ",NETWORKDAYS(E114,F114)) -> -
A115: =IF(ISERROR(VALUE(SUBSTITUTE(prevWBS,".",""))),"0.1",IF(ISERROR(FIND("`",SUBSTITUTE(prevWBS,".","`",1))),prevWBS&".1",LEFT(prevWBS,FIND("`",SUBSTITUTE(prevWBS,".","`",1)))&IF(ISERROR(FIND("`",SUBSTITUTE(prevWBS,".","`",2))),VALUE(RIGHT(prevWBS,LEN(prevWBS)-FIND("`",SUBSTITUTE(prevWBS,".","`",1))))+1,VALUE(MID(prevWBS,FIND("`",SUBSTITUTE(prevWBS,".","`",1))+1,(FIND("`",SUBSTITUTE(prevWBS,".","`",2))-FIND("`",SUBSTITUTE(prevWBS,".","`",1))-1)))+1))) -> 4.1 | B115: Custom field for qty in PCS at Report Stock | C115: Billy, Budi | E115: 46051 | F115: =IF(ISBLANK(E115)," - ",IF(G115=0,E115,E115+G115-1)) -> 46056 | G115: 6 | H115: 0 | I115: 4

Sheet h
A1: RICEF BY LEUWITEX ( update 2 Maret 2026 )
B4: Project Start Date | C4: 45986 | G4: Display Week | H4: 1 | K4: ="Week "&(K6-($C$4-WEEKDAY($C$4,1)+2))/7+1 -> Week 1 | R4: ="Week "&(R6-($C$4-WEEKDAY($C$4,1)+2))/7+1 -> Week 2 | Y4: ="Week "&(Y6-($C$4-WEEKDAY($C$4,1)+2))/7+1 -> Week 3 | AF4: ="Week "&(AF6-($C$4-WEEKDAY($C$4,1)+2))/7+1 -> Week 4 | AM4: ="Week "&(AM6-($C$4-WEEKDAY($C$4,1)+2))/7+1 -> Week 5 | AT4: ="Week "&(AT6-($C$4-WEEKDAY($C$4,1)+2))/7+1 -> Week 6 | BA4: ="Week "&(BA6-($C$4-WEEKDAY($C$4,1)+2))/7+1 -> Week 7 | BH4: ="Week "&(BH6-($C$4-WEEKDAY($C$4,1)+2))/7+1 -> Week 8
B5: Project Lead | C5: Billy | K5: =K6 -> 45985 | R5: =R6 -> 45992 | Y5: =Y6 -> 45999 | AF5: =AF6 -> 46006 | AM5: =AM6 -> 46013 | AT5: =AT6 -> 46020 | BA5: =BA6 -> 46027 | BH5: =BH6 -> 46034
K6: =C4-WEEKDAY(C4,1)+2+7*(H4-1) -> 45985 | L6: =K6+1 -> 45986 | M6: =L6+1 -> 45987 | N6: =M6+1 -> 45988 | O6: =N6+1 -> 45989 | P6: =O6+1 -> 45990 | Q6: =P6+1 -> 45991 | R6: =Q6+1 -> 45992 | S6: =R6+1 -> 45993 | ... BN6: =BM6+1 -> 46040
A7: WBS | B7: TASK | C7: PIC | D7: NOTES | E7: START | F7: END | G7: DAYS | H7: % DONE | I7: WORK DAYS | K7: =CHOOSE(WEEKDAY(K6,1),"S","M","T","W","T","F","S") -> M | L7: =CHOOSE(WEEKDAY(L6,1),"S","M","T","W","T","F","S") -> T | M7: =CHOOSE(WEEKDAY(M6,1),"S","M","T","W","T","F","S") -> W | N7: =CHOOSE(WEEKDAY(N6,1),"S","M","T","W","T","F","S") -> T | O7: =CHOOSE(WEEKDAY(O6,1),"S","M","T","W","T","F","S") -> F | P7: =CHOOSE(WEEKDAY(P6,1),"S","M","T","W","T","F","S") -> S | Q7: =CHOOSE(WEEKDAY(Q6,1),"S","M","T","W","T","F","S") -> S | R7: =CHOOSE(WEEKDAY(R6,1),"S","M","T","W","T","F","S") -> M | ... BN7: =CHOOSE(WEEKDAY(BN6,1),"S","M","T","W","T","F","S") -> S
A8: =IF(ISERROR(VALUE(SUBSTITUTE(prevWBS,".",""))),"1",IF(ISERROR(FIND("`",SUBSTITUTE(prevWBS,".","`",1))),TEXT(VALUE(prevWBS)+1,"#"),TEXT(VALUE(LEFT(prevWBS,FIND("`",SUBSTITUTE(prevWBS,".","`",1))-1))+1,"#"))) -> 1 | B8: SAP API development | F8: =IF(ISBLANK(E8)," - ",IF(G8=0,E8,E8+G8-1)) -> - | I8: =IF(OR(F8=0,E8=0)," - ",NETWORKDAYS(E8,F8)) -> -
A9: =IF(ISERROR(VALUE(SUBSTITUTE(prevWBS,".",""))),"0.1",IF(ISERROR(FIND("`",SUBSTITUTE(prevWBS,".","`",1))),prevWBS&".1",LEFT(prevWBS,FIND("`",SUBSTITUTE(prevWBS,".","`",1)))&IF(ISERROR(FIND("`",SUBSTITUTE(prevWBS,".","`",2))),VALUE(RIGHT(prevWBS,LEN(prevWBS)-FIND("`",SUBSTITUTE(prevWBS,".","`",1))))+1,VALUE(MID(prevWBS,FIND("`",SUBSTITUTE(prevWBS,".","`",1))+1,(FIND("`",SUBSTITUTE(prevWBS,".","`",2))-FIND("`",SUBSTITUTE(prevWBS,".","`",1))-1)))+1))) -> 1.1 | B9: INSTALL ECLIPSE, ADOBE LIFECYCLE DI PC | C9: Baim, Budi | E9: 45987 | F9: =IF(ISBLANK(E9)," - ",IF(G9=0,E9,E9+G9-1)) -> 45987 | G9: 1 | H9: 1 | I9: =IF(OR(F9=0,E9=0)," - ",NETWORKDAYS(E9,F9)) -> 1
A10: =IF(ISERROR(VALUE(SUBSTITUTE(prevWBS,".",""))),"0.1",IF(ISERROR(FIND("`",SUBSTITUTE(prevWBS,".","`",1))),prevWBS&".1",LEFT(prevWBS,FIND("`",SUBSTITUTE(prevWBS,".","`",1)))&IF(ISERROR(FIND("`",SUBSTITUTE(prevWBS,".","`",2))),VALUE(RIGHT(prevWBS,LEN(prevWBS)-FIND("`",SUBSTITUTE(prevWBS,".","`",1))))+1,VALUE(MID(prevWBS,FIND("`",SUBSTITUTE(prevWBS,".","`",1))+1,(FIND("`",SUBSTITUTE(prevWBS,".","`",2))-FIND("`",SUBSTITUTE(prevWBS,".","`",1))-1)))+1))) -> 1.2 | B10: BELAJAR KE SOLTIUS TENTANG SAP | C10: Baim, Budi | E10: 45988 | F10: =IF(ISBLANK(E10)," - ",IF(G10=0,E10,E10+G10-1)) -> 46054 | G10: 67 | H10: 0.4 | I10: =IF(OR(F10=0,E10=0)," - ",NETWORKDAYS(E10,F10)) -> 47
A11: =IF(ISERROR(VALUE(SUBSTITUTE(prevWBS,".",""))),"0.1",IF(ISERROR(FIND("`",SUBSTITUTE(prevWBS,".","`",1))),prevWBS&".1",LEFT(prevWBS,FIND("`",SUBSTITUTE(prevWBS,".","`",1)))&IF(ISERROR(FIND("`",SUBSTITUTE(prevWBS,".","`",2))),VALUE(RIGHT(prevWBS,LEN(prevWBS)-FIND("`",SUBSTITUTE(prevWBS,".","`",1))))+1,VALUE(MID(prevWBS,FIND("`",SUBSTITUTE(prevWBS,".","`",1))+1,(FIND("`",SUBSTITUTE(prevWBS,".","`",2))-FIND("`",SUBSTITUTE(prevWBS,".","`",1))-1)))+1))) -> 1.3 | B11: INTEGRASI API SAP KE PRINT BARCODE INTERNAL | C11: Baim, Budi | E11: 45995 | F11: =IF(ISBLANK(E11)," - ",IF(G11=0,E11,E11+G11-1)) -> 46001 | G11: 7 | H11: 1 | I11: =IF(OR(F11=0,E11=0)," - ",NETWORKDAYS(E11,F11)) -> 5
A12: =IF(ISERROR(VALUE(SUBSTITUTE(prevWBS,".",""))),"0.1",IF(ISERROR(FIND("`",SUBSTITUTE(prevWBS,".","`",1))),prevWBS&".1",LEFT(prevWBS,FIND("`",SUBSTITUTE(prevWBS,".","`",1)))&IF(ISERROR(FIND("`",SUBSTITUTE(prevWBS,".","`",2))),VALUE(RIGHT(prevWBS,LEN(prevWBS)-FIND("`",SUBSTITUTE(prevWBS,".","`",1))))+1,VALUE(MID(prevWBS,FIND("`",SUBSTITUTE(prevWBS,".","`",1))+1,(FIND("`",SUBSTITUTE(prevWBS,".","`",2))-FIND("`",SUBSTITUTE(prevWBS,".","`",1))-1)))+1))) -> 1.4 | B12: MAPPING IT INVENTORY | C12: Baim | E12: 46009 | F12: =IF(ISBLANK(E12)," - ",IF(G12=0,E12,E12+G12-1)) -> 46014 | G12: 6 | H12: 1 | I12: =IF(OR(F12=0,E12=0)," - ",NETWORKDAYS(E12,F12)) -> 4
A13: =IF(ISERROR(VALUE(SUBSTITUTE(prevWBS,".",""))),"0.1",IF(ISERROR(FIND("`",SUBSTITUTE(prevWBS,".","`",1))),prevWBS&".1",LEFT(prevWBS,FIND("`",SUBSTITUTE(prevWBS,".","`",1)))&IF(ISERROR(FIND("`",SUBSTITUTE(prevWBS,".","`",2))),VALUE(RIGHT(prevWBS,LEN(prevWBS)-FIND("`",SUBSTITUTE(prevWBS,".","`",1))))+1,VALUE(MID(prevWBS,FIND("`",SUBSTITUTE(prevWBS,".","`",1))+1,(FIND("`",SUBSTITUTE(prevWBS,".","`",2))-FIND("`",SUBSTITUTE(prevWBS,".","`",1))-1)))+1))) -> 1.5 | B13: BELAJAR MENDAFTARKAN API SAP | C13: Baim, Budi | E13: 46021 | F13: =IF(ISBLANK(E13)," - ",IF(G13=0,E13,E13+G13-1)) -> 46021 | G13: 1 | H13: 1 | I13: =IF(OR(F13=0,E13=0)," - ",NETWORKDAYS(E13,F13)) -> 1
A14: =IF(ISERROR(VALUE(SUBSTITUTE(prevWBS,".",""))),"0.1",IF(ISERROR(FIND("`",SUBSTITUTE(prevWBS,".","`",1))),prevWBS&".1",LEFT(prevWBS,FIND("`",SUBSTITUTE(prevWBS,".","`",1)))&IF(ISERROR(FIND("`",SUBSTITUTE(prevWBS,".","`",2))),VALUE(RIGHT(prevWBS,LEN(prevWBS)-FIND("`",SUBSTITUTE(prevWBS,".","`",1))))+1,VALUE(MID(prevWBS,FIND("`",SUBSTITUTE(prevWBS,".","`",1))+1,(FIND("`",SUBSTITUTE(prevWBS,".","`",2))-FIND("`",SUBSTITUTE(prevWBS,".","`",1))-1)))+1))) -> 1.6 | B14: MAPPING TABEL TAMBAHAN BEA CUKAI | C14: Baim | E14: 46021 | F14: =IF(ISBLANK(E14)," - ",IF(G14=0,E14,E14+G14-1)) -> 46030 | G14: 10 | H14: 1 | I14: =IF(OR(F14=0,E14=0)," - ",NETWORKDAYS(E14,F14)) -> 8
A15: =IF(ISERROR(VALUE(SUBSTITUTE(prevWBS,".",""))),"0.1",IF(ISERROR(FIND("`",SUBSTITUTE(prevWBS,".","`",1))),prevWBS&".1",LEFT(prevWBS,FIND("`",SUBSTITUTE(prevWBS,".","`",1)))&IF(ISERROR(FIND("`",SUBSTITUTE(prevWBS,".","`",2))),VALUE(RIGHT(prevWBS,LEN(prevWBS)-FIND("`",SUBSTITUTE(prevWBS,".","`",1))))+1,VALUE(MID(prevWBS,FIND("`",SUBSTITUTE(prevWBS,".","`",1))+1,(FIND("`",SUBSTITUTE(prevWBS,".","`",2))-FIND("`",SUBSTITUTE(prevWBS,".","`",1))-1)))+1))) -> 1.7 | B15: SIT | C15: Baim, Budi | E15: 46028 | F15: =IF(ISBLANK(E15)," - ",IF(G15=0,E15,E15+G15-1)) -> 46030 | G15: 3 | H15: 1 | I15: =IF(OR(F15=0,E15=0)," - ",NETWORKDAYS(E15,F15)) -> 3
A16: =IF(ISERROR(VALUE(SUBSTITUTE(prevWBS,".",""))),"0.1",IF(ISERROR(FIND("`",SUBSTITUTE(prevWBS,".","`",1))),prevWBS&".1",LEFT(prevWBS,FIND("`",SUBSTITUTE(prevWBS,".","`",1)))&IF(ISERROR(FIND("`",SUBSTITUTE(prevWBS,".","`",2))),VALUE(RIGHT(prevWBS,LEN(prevWBS)-FIND("`",SUBSTITUTE(prevWBS,".","`",1))))+1,VALUE(MID(prevWBS,FIND("`",SUBSTITUTE(prevWBS,".","`",1))+1,(FIND("`",SUBSTITUTE(prevWBS,".","`",2))-FIND("`",SUBSTITUTE(prevWBS,".","`",1))-1)))+1))) -> 1.8 | B16: INTEGRASI API SAP UNTUK BEA CUKAI | C16: Baim | E16: 46031 | F16: =IF(ISBLANK(E16)," - ",IF(G16=0,E16,E16+G16-1)) -> 46040 | G16: 10 | H16: 0.5 | I16: =IF(OR(F16=0,E16=0)," - ",NETWORKDAYS(E16,F16)) -> 6
A17: =IF(ISERROR(VALUE(SUBSTITUTE(prevWBS,".",""))),"0.1",IF(ISERROR(FIND("`",SUBSTITUTE(prevWBS,".","`",1))),prevWBS&".1",LEFT(prevWBS,FIND("`",SUBSTITUTE(prevWBS,".","`",1)))&IF(ISERROR(FIND("`",SUBSTITUTE(prevWBS,".","`",2))),VALUE(RIGHT(prevWBS,LEN(prevWBS)-FIND("`",SUBSTITUTE(prevWBS,".","`",1))))+1,VALUE(MID(prevWBS,FIND("`",SUBSTITUTE(prevWBS,".","`",1))+1,(FIND("`",SUBSTITUTE(prevWBS,".","`",2))-FIND("`",SUBSTITUTE(prevWBS,".","`",1))-1)))+1))) -> 1.9 | B17: BELAJAR MENGEDIT FORM SAP | C17: Baim, Budi | E17: 46030 | F17: =IF(ISBLANK(E17)," - ",IF(G17=0,E17,E17+G17-1)) -> 46030 | G17: 1 | H17: 1 | I17: =IF(OR(F17=0,E17=0)," - ",NETWORKDAYS(E17,F17)) -> 1
A18: =IF(ISERROR(VALUE(SUBSTITUTE(prevWBS,".",""))),"0.1",IF(ISERROR(FIND("`",SUBSTITUTE(prevWBS,".","`",1))),prevWBS&".1",LEFT(prevWBS,FIND("`",SUBSTITUTE(prevWBS,".","`",1)))&IF(ISERROR(FIND("`",SUBSTITUTE(prevWBS,".","`",2))),VALUE(RIGHT(prevWBS,LEN(prevWBS)-FIND("`",SUBSTITUTE(prevWBS,".","`",1))))+1,VALUE(MID(prevWBS,FIND("`",SUBSTITUTE(prevWBS,".","`",1))+1,(FIND("`",SUBSTITUTE(prevWBS,".","`",2))-FIND("`",SUBSTITUTE(prevWBS,".","`",1))-1)))+1))) -> 1.10 | B18: KUT SAP BAGIAN MASTER DATA MM | C18: Baim | E18: 46037 | F18: =IF(ISBLANK(E18)," - ",IF(G18=0,E18,E18+G18-1)) -> 46038 | G18: 2 | H18: 1 | I18: =IF(OR(F18=0,E18=0)," - ",NETWORKDAYS(E18,F18)) -> 2
A19: =IF(ISERROR(VALUE(SUBSTITUTE(prevWBS,".",""))),"0.1",IF(ISERROR(FIND("`",SUBSTITUTE(prevWBS,".","`",1))),prevWBS&".1",LEFT(prevWBS,FIND("`",SUBSTITUTE(prevWBS,".","`",1)))&IF(ISERROR(FIND("`",SUBSTITUTE(prevWBS,".","`",2))),VALUE(RIGHT(prevWBS,LEN(prevWBS)-FIND("`",SUBSTITUTE(prevWBS,".","`",1))))+1,VALUE(MID(prevWBS,FIND("`",SUBSTITUTE(prevWBS,".","`",1))+1,(FIND("`",SUBSTITUTE(prevWBS,".","`",2))-FIND("`",SUBSTITUTE(prevWBS,".","`",1))-1)))+1))) -> 1.11 | B19: KUT SAP BAGIAN MASTER DATA SD dan FICO | C19: Budi | E19: 46037 | F19: =IF(ISBLANK(E19)," - ",IF(G19=0,E19,E19+G19-1)) -> 46038 | G19: 2 | H19: 1 | I19: =IF(OR(F19=0,E19=0)," - ",NETWORKDAYS(E19,F19)) -> 2
A20: =IF(ISERROR(VALUE(SUBSTITUTE(prevWBS,".",""))),"0.1",IF(ISERROR(FIND("`",SUBSTITUTE(prevWBS,".","`",1))),prevWBS&".1",LEFT(prevWBS,FIND("`",SUBSTITUTE(prevWBS,".","`",1)))&IF(ISERROR(FIND("`",SUBSTITUTE(prevWBS,".","`",2))),VALUE(RIGHT(prevWBS,LEN(prevWBS)-FIND("`",SUBSTITUTE(prevWBS,".","`",1))))+1,VALUE(MID(prevWBS,FIND("`",SUBSTITUTE(prevWBS,".","`",1))+1,(FIND("`",SUBSTITUTE(prevWBS,".","`",2))-FIND("`",SUBSTITUTE(prevWBS,".","`",1))-1)))+1))) -> 1.12 | B20: Modifikasi Form Invoice (Barang Bekas, Avfal, BS, Maklon, Masker) | C20: Baim | E20: 46032 | F20: =IF(ISBLANK(E20)," - ",IF(G20=0,E20,E20+G20-1)) -> 46043 | G20: 12 | H20: 0.9 | I20: =IF(OR(F20=0,E20=0)," - ",NETWORKDAYS(E20,F20)) -> 8
... A23: =IF(ISERROR(VALUE(SUBSTITUTE(prevWBS,".",""))),"0.1",IF(ISERROR(FIND("`",SUBSTITUTE(prevWBS,".","`",1))),prevWBS&".1",LEFT(prevWBS,FIND("`",SUBSTITUTE(prevWBS,".","`",1)))&IF(ISERROR(FIND("`",SUBSTITUTE(prevWBS,".","`",2))),VALUE(RIGHT(prevWBS,LEN(prevWBS)-FIND("`",SUBSTITUTE(prevWBS,".","`",1))))+1,VALUE(MID(prevWBS,FIND("`",SUBSTITUTE(prevWBS,".","`",1))+1,(FIND("`",SUBSTITUTE(prevWBS,".","`",2))-FIND("`",SUBSTITUTE(prevWBS,".","`",1))-1)))+1))) -> 1.15 | B23: Buat UI penarikan data dari API dan insert data Material | C23: Budi | E23: 46056 | F23: =IF(ISBLANK(E23)," - ",IF(G23=0,E23,E23+G23-1)) -> 46057 | G23: 2 | H23: 1 | I23: =IF(OR(F23=0,E23=0)," - ",NETWORKDAYS(E23,F23)) -> 2
A24: =IF(ISERROR(VALUE(SUBSTITUTE(prevWBS,".",""))),"0.1",IF(ISERROR(FIND("`",SUBSTITUTE(prevWBS,".","`",1))),prevWBS&".1",LEFT(prevWBS,FIND("`",SUBSTITUTE(prevWBS,".","`",1)))&IF(ISERROR(FIND("`",SUBSTITUTE(prevWBS,".","`",2))),VALUE(RIGHT(prevWBS,LEN(prevWBS)-FIND("`",SUBSTITUTE(prevWBS,".","`",1))))+1,VALUE(MID(prevWBS,FIND("`",SUBSTITUTE(prevWBS,".","`",1))+1,(FIND("`",SUBSTITUTE(prevWBS,".","`",2))-FIND("`",SUBSTITUTE(prevWBS,".","`",1))-1)))+1))) -> 1.16 | B24: Buat UI penarikan data dari API dan insert data Warehouse | C24: Budi | E24: =F22+1 -> 46058 | F24: =IF(ISBLANK(E24)," - ",IF(G24=0,E24,E24+G24-1)) -> 46059 | G24: 2 | H24: 1 | I24: =IF(OR(F24=0,E24=0)," - ",NETWORKDAYS(E24,F24)) -> 2
A25: =IF(ISERROR(VALUE(SUBSTITUTE(prevWBS,".",""))),"0.1",IF(ISERROR(FIND("`",SUBSTITUTE(prevWBS,".","`",1))),prevWBS&".1",LEFT(prevWBS,FIND("`",SUBSTITUTE(prevWBS,".","`",1)))&IF(ISERROR(FIND("`",SUBSTITUTE(prevWBS,".","`",2))),VALUE(RIGHT(prevWBS,LEN(prevWBS)-FIND("`",SUBSTITUTE(prevWBS,".","`",1))))+1,VALUE(MID(prevWBS,FIND("`",SUBSTITUTE(prevWBS,".","`",1))+1,(FIND("`",SUBSTITUTE(prevWBS,".","`",2))-FIND("`",SUBSTITUTE(prevWBS,".","`",1))-1)))+1))) -> 1.17 | B25: Buat UI penarikan data dari API dan insert data Asset | C25: Baim | E25: =F22+1 -> 46058 | F25: =IF(ISBLANK(E25)," - ",IF(G25=0,E25,E25+G25-1)) -> 46059 | G25: 2 | H25: 1 | I25: =IF(OR(F25=0,E25=0)," - ",NETWORKDAYS(E25,F25)) -> 2
A26: =IF(ISERROR(VALUE(SUBSTITUTE(prevWBS,".",""))),"0.1",IF(ISERROR(FIND("`",SUBSTITUTE(prevWBS,".","`",1))),prevWBS&".1",LEFT(prevWBS,FIND("`",SUBSTITUTE(prevWBS,".","`",1)))&IF(ISERROR(FIND("`",SUBSTITUTE(prevWBS,".","`",2))),VALUE(RIGHT(prevWBS,LEN(prevWBS)-FIND("`",SUBSTITUTE(prevWBS,".","`",1))))+1,VALUE(MID(prevWBS,FIND("`",SUBSTITUTE(prevWBS,".","`",1))+1,(FIND("`",SUBSTITUTE(prevWBS,".","`",2))-FIND("`",SUBSTITUTE(prevWBS,".","`",1))-1)))+1))) -> 1.18 | B26: Buat UI penarikan data dari API dan insert data Invoice | C26: Budi | E26: =E23+1 -> 46057 | F26: =IF(ISBLANK(E26)," - ",IF(G26=0,E26,E26+G26-1)) -> 46058 | G26: 2 | H26: 1 | I26: =IF(OR(F26=0,E26=0)," - ",NETWORKDAYS(E26,F26)) -> 2
A27: =IF(ISERROR(VALUE(SUBSTITUTE(prevWBS,".",""))),"0.1",IF(ISERROR(FIND("`",SUBSTITUTE(prevWBS,".","`",1))),prevWBS&".1",LEFT(prevWBS,FIND("`",SUBSTITUTE(prevWBS,".","`",1)))&IF(ISERROR(FIND("`",SUBSTITUTE(prevWBS,".","`",2))),VALUE(RIGHT(prevWBS,LEN(prevWBS)-FIND("`",SUBSTITUTE(prevWBS,".","`",1))))+1,VALUE(MID(prevWBS,FIND("`",SUBSTITUTE(prevWBS,".","`",1))+1,(FIND("`",SUBSTITUTE(prevWBS,".","`",2))-FIND("`",SUBSTITUTE(prevWBS,".","`",1))-1)))+1))) -> 1.19 | B27: Buat UI penarikan data dari API dan insert data Supplier | C27: Baim | E27: =F23+1 -> 46058 | F27: =IF(ISBLANK(E27)," - ",IF(G27=0,E27,E27+G27-1)) -> 46059 | G27: 2 | H27: 1 | I27: =IF(OR(F27=0,E27=0)," - ",NETWORKDAYS(E27,F27)) -> 2
A28: =IF(ISERROR(VALUE(SUBSTITUTE(prevWBS,".",""))),"0.1",IF(ISERROR(FIND("`",SUBSTITUTE(prevWBS,".","`",1))),prevWBS&".1",LEFT(prevWBS,FIND("`",SUBSTITUTE(prevWBS,".","`",1)))&IF(ISERROR(FIND("`",SUBSTITUTE(prevWBS,".","`",2))),VALUE(RIGHT(prevWBS,LEN(prevWBS)-FIND("`",SUBSTITUTE(prevWBS,".","`",1))))+1,VALUE(MID(prevWBS,FIND("`",SUBSTITUTE(prevWBS,".","`",1))+1,(FIND("`",SUBSTITUTE(prevWBS,".","`",2))-FIND("`",SUBSTITUTE(prevWBS,".","`",1))-1)))+1))) -> 1.20 | B28: Buat UI penarikan data dari API dan insert data Master Customer | C28: Budi | E28: =F24+1 -> 46060 | F28: =IF(ISBLANK(E28)," - ",IF(G28=0,E28,E28+G28-1)) -> 46063 | G28: 4 | H28: 1 | I28: =IF(OR(F28=0,E28=0)," - ",NETWORKDAYS(E28,F28)) -> 2
A29: =IF(ISERROR(VALUE(SUBSTITUTE(prevWBS,".",""))),"0.1",IF(ISERROR(FIND("`",SUBSTITUTE(prevWBS,".","`",1))),prevWBS&".1",LEFT(prevWBS,FIND("`",SUBSTITUTE(prevWBS,".","`",1)))&IF(ISERROR(FIND("`",SUBSTITUTE(prevWBS,".","`",2))),VALUE(RIGHT(prevWBS,LEN(prevWBS)-FIND("`",SUBSTITUTE(prevWBS,".","`",1))))+1,VALUE(MID(prevWBS,FIND("`",SUBSTITUTE(prevWBS,".","`",1))+1,(FIND("`",SUBSTITUTE(prevWBS,".","`",2))-FIND("`",SUBSTITUTE(prevWBS,".","`",1))-1)))+1))) -> 1.21 | B29: Buat UI penarikan data dari API dan insert data PO | C29: Baim | E29: =F24+1 -> 46060 | F29: =IF(ISBLANK(E29)," - ",IF(G29=0,E29,E29+G29-1)) -> 46063 | G29: 4 | H29: 1 | I29: =IF(OR(F29=0,E29=0)," - ",NETWORKDAYS(E29,F29)) -> 2
A30: =IF(ISERROR(VALUE(SUBSTITUTE(prevWBS,".",""))),"0.1",IF(ISERROR(FIND("`",SUBSTITUTE(prevWBS,".","`",1))),prevWBS&".1",LEFT(prevWBS,FIND("`",SUBSTITUTE(prevWBS,".","`",1)))&IF(ISERROR(FIND("`",SUBSTITUTE(prevWBS,".","`",2))),VALUE(RIGHT(prevWBS,LEN(prevWBS)-FIND("`",SUBSTITUTE(prevWBS,".","`",1))))+1,VALUE(MID(prevWBS,FIND("`",SUBSTITUTE(prevWBS,".","`",1))+1,(FIND("`",SUBSTITUTE(prevWBS,".","`",2))-FIND("`",SUBSTITUTE(prevWBS,".","`",1))-1)))+1))) -> 1.22 | B30: Buat UI penarikan data dari API dan insert data Material Document | C30: Budi | E30: =F28+1 -> 46064 | F30: =IF(ISBLANK(E30)," - ",IF(G30=0,E30,E30+G30-1)) -> 46065 | G30: 2 | H30: 1 | I30: =IF(OR(F30=0,E30=0)," - ",NETWORKDAYS(E30,F30)) -> 2
A31: =IF(ISERROR(VALUE(SUBSTITUTE(prevWBS,".",""))),"0.1",IF(ISERROR(FIND("`",SUBSTITUTE(prevWBS,".","`",1))),prevWBS&".1",LEFT(prevWBS,FIND("`",SUBSTITUTE(prevWBS,".","`",1)))&IF(ISERROR(FIND("`",SUBSTITUTE(prevWBS,".","`",2))),VALUE(RIGHT(prevWBS,LEN(prevWBS)-FIND("`",SUBSTITUTE(prevWBS,".","`",1))))+1,VALUE(MID(prevWBS,FIND("`",SUBSTITUTE(prevWBS,".","`",1))+1,(FIND("`",SUBSTITUTE(prevWBS,".","`",2))-FIND("`",SUBSTITUTE(prevWBS,".","`",1))-1)))+1))) -> 1.23 | B31: Buat UI penarikan data dari API dan insert data BOM | C31: Baim | E31: =F29+1 -> 46064 | F31: =IF(ISBLANK(E31)," - ",IF(G31=0,E31,E31+G31-1)) -> 46065 | G31: 2 | H31: 1 | I31: =IF(OR(F31=0,E31=0)," - ",NETWORKDAYS(E31,F31)) -> 2
A32: =IF(ISERROR(VALUE(SUBSTITUTE(prevWBS,".",""))),"0.1",IF(ISERROR(FIND("`",SUBSTITUTE(prevWBS,".","`",1))),prevWBS&".1",LEFT(prevWBS,FIND("`",SUBSTITUTE(prevWBS,".","`",1)))&IF(ISERROR(FIND("`",SUBSTITUTE(prevWBS,".","`",2))),VALUE(RIGHT(prevWBS,LEN(prevWBS)-FIND("`",SUBSTITUTE(prevWBS,".","`",1))))+1,VALUE(MID(prevWBS,FIND("`",SUBSTITUTE(prevWBS,".","`",1))+1,(FIND("`",SUBSTITUTE(prevWBS,".","`",2))-FIND("`",SUBSTITUTE(prevWBS,".","`",1))-1)))+1))) -> 1.24 | B32: UAT | C32: Baim, Budi | E32: =F30 -> 46065 | F32: =IF(ISBLANK(E32)," - ",IF(G32=0,E32,E32+G32-1)) -> 46067 | G32: 3 | H32: 1 | I32: =IF(OR(F32=0,E32=0)," - ",NETWORKDAYS(E32,F32)) -> 2
A33: =IF(ISERROR(VALUE(SUBSTITUTE(prevWBS,".",""))),"0.1",IF(ISERROR(FIND("`",SUBSTITUTE(prevWBS,".","`",1))),prevWBS&".1",LEFT(prevWBS,FIND("`",SUBSTITUTE(prevWBS,".","`",1)))&IF(ISERROR(FIND("`",SUBSTITUTE(prevWBS,".","`",2))),VALUE(RIGHT(prevWBS,LEN(prevWBS)-FIND("`",SUBSTITUTE(prevWBS,".","`",1))))+1,VALUE(MID(prevWBS,FIND("`",SUBSTITUTE(prevWBS,".","`",1))+1,(FIND("`",SUBSTITUTE(prevWBS,".","`",2))-FIND("`",SUBSTITUTE(prevWBS,".","`",1))-1)))+1))) -> 1.25 | B33: BBK INTERN | C33: Budi | E33: =F32+1 -> 46068 | F33: =IF(ISBLANK(E33)," - ",IF(G33=0,E33,E33+G33-1)) -> 46072 | G33: 5 | H33: 0 | I33: =IF(OR(F33=0,E33=0)," - ",NETWORKDAYS(E33,F33)) -> 4
A34: =IF(ISERROR(VALUE(SUBSTITUTE(prevWBS,".",""))),"0.1",IF(ISERROR(FIND("`",SUBSTITUTE(prevWBS,".","`",1))),prevWBS&".1",LEFT(prevWBS,FIND("`",SUBSTITUTE(prevWBS,".","`",1)))&IF(ISERROR(FIND("`",SUBSTITUTE(prevWBS,".","`",2))),VALUE(RIGHT(prevWBS,LEN(prevWBS)-FIND("`",SUBSTITUTE(prevWBS,".","`",1))))+1,VALUE(MID(prevWBS,FIND("`",SUBSTITUTE(prevWBS,".","`",1))+1,(FIND("`",SUBSTITUTE(prevWBS,".","`",2))-FIND("`",SUBSTITUTE(prevWBS,".","`",1))-1)))+1))) -> 1.26 | B34: LAPORAN SURAT JALAN (P) | C34: Baim | E34: =F32+1 -> 46068 | F34: =IF(ISBLANK(E34)," - ",IF(G34=0,E34,E34+G34-1)) -> 46072 | G34: 5 | H34: 0.8 | I34: =IF(OR(F34=0,E34=0)," - ",NETWORKDAYS(E34,F34)) -> 4
A35: =IF(ISERROR(VALUE(SUBSTITUTE(prevWBS,".",""))),"0.1",IF(ISERROR(FIND("`",SUBSTITUTE(prevWBS,".","`",1))),prevWBS&".1",LEFT(prevWBS,FIND("`",SUBSTITUTE(prevWBS,".","`",1)))&IF(ISERROR(FIND("`",SUBSTITUTE(prevWBS,".","`",2))),VALUE(RIGHT(prevWBS,LEN(prevWBS)-FIND("`",SUBSTITUTE(prevWBS,".","`",1))))+1,VALUE(MID(prevWBS,FIND("`",SUBSTITUTE(prevWBS,".","`",1))+1,(FIND("`",SUBSTITUTE(prevWBS,".","`",2))-FIND("`",SUBSTITUTE(prevWBS,".","`",1))-1)))+1))) -> 1.27 | B35: DETAIL LIST KARTON PER RAK | C35: Budi | E35: =F33+1 -> 46073 | F35: =IF(ISBLANK(E35)," - ",IF(G35=0,E35,E35+G35-1)) -> 46076 | G35: 4 | H35: 0 | I35: =IF(OR(F35=0,E35=0)," - ",NETWORKDAYS(E35,F35)) -> 2
A36: =IF(ISERROR(VALUE(SUBSTITUTE(prevWBS,".",""))),"0.1",IF(ISERROR(FIND("`",SUBSTITUTE(prevWBS,".","`",1))),prevWBS&".1",LEFT(prevWBS,FIND("`",SUBSTITUTE(prevWBS,".","`",1)))&IF(ISERROR(FIND("`",SUBSTITUTE(prevWBS,".","`",2))),VALUE(RIGHT(prevWBS,LEN(prevWBS)-FIND("`",SUBSTITUTE(prevWBS,".","`",1))))+1,VALUE(MID(prevWBS,FIND("`",SUBSTITUTE(prevWBS,".","`",1))+1,(FIND("`",SUBSTITUTE(prevWBS,".","`",2))-FIND("`",SUBSTITUTE(prevWBS,".","`",1))-1)))+1))) -> 1.28 | B36: LAPORAN GUDANG PACKING LEAD TIME | C36: Baim/Star | E36: =F34+1 -> 46073 | F36: =IF(ISBLANK(E36)," - ",IF(G36=0,E36,E36+G36-1)) -> 46076 | G36: 4 | H36: 0 | I36: =IF(OR(F36=0,E36=0)," - ",NETWORKDAYS(E36,F36)) -> 2
A37: =IF(ISERROR(VALUE(SUBSTITUTE(prevWBS,".",""))),"0.1",IF(ISERROR(FIND("`",SUBSTITUTE(prevWBS,".","`",1))),prevWBS&".1",LEFT(prevWBS,FIND("`",SUBSTITUTE(prevWBS,".","`",1)))&IF(ISERROR(FIND("`",SUBSTITUTE(prevWBS,".","`",2))),VALUE(RIGHT(prevWBS,LEN(prevWBS)-FIND("`",SUBSTITUTE(prevWBS,".","`",1))))+1,VALUE(MID(prevWBS,FIND("`",SUBSTITUTE(prevWBS,".","`",1))+1,(FIND("`",SUBSTITUTE(prevWBS,".","`",2))-FIND("`",SUBSTITUTE(prevWBS,".","`",1))-1)))+1))) -> 1.29 | B37: LAPORAN PERSEDIAAN GUDANG PACKING | C37: Budi/Star | E37: =F35+1 -> 46077 | F37: =IF(ISBLANK(E37)," - ",IF(G37=0,E37,E37+G37-1)) -> 46078 | G37: 2 | H37: 0 | I37: =IF(OR(F37=0,E37=0)," - ",NETWORKDAYS(E37,F37)) -> 2
A38: =IF(ISERROR(VALUE(SUBSTITUTE(prevWBS,".",""))),"0.1",IF(ISERROR(FIND("`",SUBSTITUTE(prevWBS,".","`",1))),prevWBS&".1",LEFT(prevWBS,FIND("`",SUBSTITUTE(prevWBS,".","`",1)))&IF(ISERROR(FIND("`",SUBSTITUTE(prevWBS,".","`",2))),VALUE(RIGHT(prevWBS,LEN(prevWBS)-FIND("`",SUBSTITUTE(prevWBS,".","`",1))))+1,VALUE(MID(prevWBS,FIND("`",SUBSTITUTE(prevWBS,".","`",1))+1,(FIND("`",SUBSTITUTE(prevWBS,".","`",2))-FIND("`",SUBSTITUTE(prevWBS,".","`",1))-1)))+1))) -> 1.30 | B38: DASHBOARD LAYOUT PER BIN | C38: Baim | E38: =F36+1 -> 46077 | F38: =IF(ISBLANK(E38)," - ",IF(G38=0,E38,E38+G38-1)) -> 46078 | G38: 2 | H38: 0 | I38: =IF(OR(F38=0,E38=0)," - ",NETWORKDAYS(E38,F38)) -> 2
A39: =IF(ISERROR(VALUE(SUBSTITUTE(prevWBS,".",""))),"0.1",IF(ISERROR(FIND("`",SUBSTITUTE(prevWBS,".","`",1))),prevWBS&".1",LEFT(prevWBS,FIND("`",SUBSTITUTE(prevWBS,".","`",1)))&IF(ISERROR(FIND("`",SUBSTITUTE(prevWBS,".","`",2))),VALUE(RIGHT(prevWBS,LEN(prevWBS)-FIND("`",SUBSTITUTE(prevWBS,".","`",1))))+1,VALUE(MID(prevWBS,FIND("`",SUBSTITUTE(prevWBS,".","`",1))+1,(FIND("`",SUBSTITUTE(prevWBS,".","`",2))-FIND("`",SUBSTITUTE(prevWBS,".","`",1))-1)))+1))) -> 1.31 | B39: FORM BC - PO | C39: Jali | E39: =F37+1 -> 46079 | F39: =IF(ISBLANK(E39)," - ",IF(G39=0,E39,E39+G39-1)) -> 46083 | G39: 5 | H39: 0 | I39: =IF(OR(F39=0,E39=0)," - ",NETWORKDAYS(E39,F39)) -> 3
A40: =IF(ISERROR(VALUE(SUBSTITUTE(prevWBS,".",""))),"0.1",IF(ISERROR(FIND("`",SUBSTITUTE(prevWBS,".","`",1))),prevWBS&".1",LEFT(prevWBS,FIND("`",SUBSTITUTE(prevWBS,".","`",1)))&IF(ISERROR(FIND("`",SUBSTITUTE(prevWBS,".","`",2))),VALUE(RIGHT(prevWBS,LEN(prevWBS)-FIND("`",SUBSTITUTE(prevWBS,".","`",1))))+1,VALUE(MID(prevWBS,FIND("`",SUBSTITUTE(prevWBS,".","`",1))+1,(FIND("`",SUBSTITUTE(prevWBS,".","`",2))-FIND("`",SUBSTITUTE(prevWBS,".","`",1))-1)))+1))) -> 1.32 | B40: LAPORAN SURAT JALAN SLOC | C40: Budi | E40: =F37+1 -> 46079 | F40: =IF(ISBLANK(E40)," - ",IF(G40=0,E40,E40+G40-1)) -> 46080 | G40: 2 | H40: 0 | I40: =IF(OR(F40=0,E40=0)," - ",NETWORKDAYS(E40,F40)) -> 2
A41: =IF(ISERROR(VALUE(SUBSTITUTE(prevWBS,".",""))),"0.1",IF(ISERROR(FIND("`",SUBSTITUTE(prevWBS,".","`",1))),prevWBS&".1",LEFT(prevWBS,FIND("`",SUBSTITUTE(prevWBS,".","`",1)))&IF(ISERROR(FIND("`",SUBSTITUTE(prevWBS,".","`",2))),VALUE(RIGHT(prevWBS,LEN(prevWBS)-FIND("`",SUBSTITUTE(prevWBS,".","`",1))))+1,VALUE(MID(prevWBS,FIND("`",SUBSTITUTE(prevWBS,".","`",1))+1,(FIND("`",SUBSTITUTE(prevWBS,".","`",2))-FIND("`",SUBSTITUTE(prevWBS,".","`",1))-1)))+1))) -> 1.33 | B41: LIST KARTON PER KODE ORDER | C41: Baim/Star | E41: =F38+1 -> 46079 | F41: =IF(ISBLANK(E41)," - ",IF(G41=0,E41,E41+G41-1)) -> 46080 | G41: 2 | H41: 0 | I41: =IF(OR(F41=0,E41=0)," - ",NETWORKDAYS(E41,F41)) -> 2
A42: =IF(ISERROR(VALUE(SUBSTITUTE(prevWBS,".",""))),"0.1",IF(ISERROR(FIND("`",SUBSTITUTE(prevWBS,".","`",1))),prevWBS&".1",LEFT(prevWBS,FIND("`",SUBSTITUTE(prevWBS,".","`",1)))&IF(ISERROR(FIND("`",SUBSTITUTE(prevWBS,".","`",2))),VALUE(RIGHT(prevWBS,LEN(prevWBS)-FIND("`",SUBSTITUTE(prevWBS,".","`",1))))+1,VALUE(MID(prevWBS,FIND("`",SUBSTITUTE(prevWBS,".","`",1))+1,(FIND("`",SUBSTITUTE(prevWBS,".","`",2))-FIND("`",SUBSTITUTE(prevWBS,".","`",1))-1)))+1))) -> 1.34 | B42: FORM BC - GRS | C42: Jali | E42: =F39+1 -> 46084 | F42: =IF(ISBLANK(E42)," - ",IF(G42=0,E42,E42+G42-1)) -> 46085 | G42: 2 | H42: 0 | I42: =IF(OR(F42=0,E42=0)," - ",NETWORKDAYS(E42,F42)) -> 2
A43: =IF(ISERROR(VALUE(SUBSTITUTE(prevWBS,".",""))),"0.1",IF(ISERROR(FIND("`",SUBSTITUTE(prevWBS,".","`",1))),prevWBS&".1",LEFT(prevWBS,FIND("`",SUBSTITUTE(prevWBS,".","`",1)))&IF(ISERROR(FIND("`",SUBSTITUTE(prevWBS,".","`",2))),VALUE(RIGHT(prevWBS,LEN(prevWBS)-FIND("`",SUBSTITUTE(prevWBS,".","`",1))))+1,VALUE(MID(prevWBS,FIND("`",SUBSTITUTE(prevWBS,".","`",1))+1,(FIND("`",SUBSTITUTE(prevWBS,".","`",2))-FIND("`",SUBSTITUTE(prevWBS,".","`",1))-1)))+1))) -> 1.35 | B43: LIST STK INTERN DAN EXTERN | C43: Budi | E43: =F40+1 -> 46081 | F43: =IF(ISBLANK(E43)," - ",IF(G43=0,E43,E43+G43-1)) -> 46084 | G43: 4 | H43: 0 | I43: =IF(OR(F43=0,E43=0)," - ",NETWORKDAYS(E43,F43)) -> 2
A44: =IF(ISERROR(VALUE(SUBSTITUTE(prevWBS,".",""))),"0.1",IF(ISERROR(FIND("`",SUBSTITUTE(prevWBS,".","`",1))),prevWBS&".1",LEFT(prevWBS,FIND("`",SUBSTITUTE(prevWBS,".","`",1)))&IF(ISERROR(FIND("`",SUBSTITUTE(prevWBS,".","`",2))),VALUE(RIGHT(prevWBS,LEN(prevWBS)-FIND("`",SUBSTITUTE(prevWBS,".","`",1))))+1,VALUE(MID(prevWBS,FIND("`",SUBSTITUTE(prevWBS,".","`",1))+1,(FIND("`",SUBSTITUTE(prevWBS,".","`",2))-FIND("`",SUBSTITUTE(prevWBS,".","`",1))-1)))+1))) -> 1.36 | B44: MONITORING KAIN GREY | C44: Baim | E44: =F41+1 -> 46081 | F44: =IF(ISBLANK(E44)," - ",IF(G44=0,E44,E44+G44-1)) -> 46084 | G44: 4 | H44: 0 | I44: =IF(OR(F44=0,E44=0)," - ",NETWORKDAYS(E44,F44)) -> 2
A45: =IF(ISERROR(VALUE(SUBSTITUTE(prevWBS,".",""))),"0.1",IF(ISERROR(FIND("`",SUBSTITUTE(prevWBS,".","`",1))),prevWBS&".1",LEFT(prevWBS,FIND("`",SUBSTITUTE(prevWBS,".","`",1)))&IF(ISERROR(FIND("`",SUBSTITUTE(prevWBS,".","`",2))),VALUE(RIGHT(prevWBS,LEN(prevWBS)-FIND("`",SUBSTITUTE(prevWBS,".","`",1))))+1,VALUE(MID(prevWBS,FIND("`",SUBSTITUTE(prevWBS,".","`",1))+1,(FIND("`",SUBSTITUTE(prevWBS,".","`",2))-FIND("`",SUBSTITUTE(prevWBS,".","`",1))-1)))+1))) -> 1.37 | B45: FORM BC - BPB | C45: Jali | E45: =F43+2 -> 46086 | F45: =IF(ISBLANK(E45)," - ",IF(G45=0,E45,E45+G45-1)) -> 46087 | G45: 2 | H45: 0 | I45: =IF(OR(F45=0,E45=0)," - ",NETWORKDAYS(E45,F45)) -> 2
A46: =IF(ISERROR(VALUE(SUBSTITUTE(prevWBS,".",""))),"0.1",IF(ISERROR(FIND("`",SUBSTITUTE(prevWBS,".","`",1))),prevWBS&".1",LEFT(prevWBS,FIND("`",SUBSTITUTE(prevWBS,".","`",1)))&IF(ISERROR(FIND("`",SUBSTITUTE(prevWBS,".","`",2))),VALUE(RIGHT(prevWBS,LEN(prevWBS)-FIND("`",SUBSTITUTE(prevWBS,".","`",1))))+1,VALUE(MID(prevWBS,FIND("`",SUBSTITUTE(prevWBS,".","`",1))+1,(FIND("`",SUBSTITUTE(prevWBS,".","`",2))-FIND("`",SUBSTITUTE(prevWBS,".","`",1))-1)))+1))) -> 1.38 | B46: MOVING HISTORY PER LIST KARTON | C46: Budi/Star | E46: =F43+1 -> 46085 | F46: =IF(ISBLANK(E46)," - ",IF(G46=0,E46,E46+G46-1)) -> 46086 | G46: 2 | H46: 0 | I46: =IF(OR(F46=0,E46=0)," - ",NETWORKDAYS(E46,F46)) -> 2
A47: =IF(ISERROR(VALUE(SUBSTITUTE(prevWBS,".",""))),"0.1",IF(ISERROR(FIND("`",SUBSTITUTE(prevWBS,".","`",1))),prevWBS&".1",LEFT(prevWBS,FIND("`",SUBSTITUTE(prevWBS,".","`",1)))&IF(ISERROR(FIND("`",SUBSTITUTE(prevWBS,".","`",2))),VALUE(RIGHT(prevWBS,LEN(prevWBS)-FIND("`",SUBSTITUTE(prevWBS,".","`",1))))+1,VALUE(MID(prevWBS,FIND("`",SUBSTITUTE(prevWBS,".","`",1))+1,(FIND("`",SUBSTITUTE(prevWBS,".","`",2))-FIND("`",SUBSTITUTE(prevWBS,".","`",1))-1)))+1))) -> 1.39 | B47: MOVING HISTORY PER LIST BARCODE | C47: Baim | E47: =F44+1 -> 46085 | F47: =IF(ISBLANK(E47)," - ",IF(G47=0,E47,E47+G47-1)) -> 46086 | G47: 2 | H47: 0 | I47: =IF(OR(F47=0,E47=0)," - ",NETWORKDAYS(E47,F47)) -> 2
A48: =IF(ISERROR(VALUE(SUBSTITUTE(prevWBS,".",""))),"0.1",IF(ISERROR(FIND("`",SUBSTITUTE(prevWBS,".","`",1))),prevWBS&".1",LEFT(prevWBS,FIND("`",SUBSTITUTE(prevWBS,".","`",1)))&IF(ISERROR(FIND("`",SUBSTITUTE(prevWBS,".","`",2))),VALUE(RIGHT(prevWBS,LEN(prevWBS)-FIND("`",SUBSTITUTE(prevWBS,".","`",1))))+1,VALUE(MID(prevWBS,FIND("`",SUBSTITUTE(prevWBS,".","`",1))+1,(FIND("`",SUBSTITUTE(prevWBS,".","`",2))-FIND("`",SUBSTITUTE(prevWBS,".","`",1))-1)))+1))) -> 1.40 | B48: REPORT CANCEL KAIN KELUAR | C48: Budi | E48: =F46+1 -> 46087 | F48: =IF(ISBLANK(E48)," - ",IF(G48=0,E48,E48+G48-1)) -> 46090 | G48: 4 | H48: 0 | I48: =IF(OR(F48=0,E48=0)," - ",NETWORKDAYS(E48,F48)) -> 2
A49: =IF(ISERROR(VALUE(SUBSTITUTE(prevWBS,".",""))),"0.1",IF(ISERROR(FIND("`",SUBSTITUTE(prevWBS,".","`",1))),prevWBS&".1",LEFT(prevWBS,FIND("`",SUBSTITUTE(prevWBS,".","`",1)))&IF(ISERROR(FIND("`",SUBSTITUTE(prevWBS,".","`",2))),VALUE(RIGHT(prevWBS,LEN(prevWBS)-FIND("`",SUBSTITUTE(prevWBS,".","`",1))))+1,VALUE(MID(prevWBS,FIND("`",SUBSTITUTE(prevWBS,".","`",1))+1,(FIND("`",SUBSTITUTE(prevWBS,".","`",2))-FIND("`",SUBSTITUTE(prevWBS,".","`",1))-1)))+1))) -> 1.41 | B49: REPORT CANCEL KAIN MASUK | C49: Baim | E49: =F47+1 -> 46087 | F49: =IF(ISBLANK(E49)," - ",IF(G49=0,E49,E49+G49-1)) -> 46090 | G49: 4 | H49: 0 | I49: =IF(OR(F49=0,E49=0)," - ",NETWORKDAYS(E49,F49)) -> 2
A50: =IF(ISERROR(VALUE(SUBSTITUTE(prevWBS,".",""))),"0.1",IF(ISERROR(FIND("`",SUBSTITUTE(prevWBS,".","`",1))),prevWBS&".1",LEFT(prevWBS,FIND("`",SUBSTITUTE(prevWBS,".","`",1)))&IF(ISERROR(FIND("`",SUBSTITUTE(prevWBS,".","`",2))),VALUE(RIGHT(prevWBS,LEN(prevWBS)-FIND("`",SUBSTITUTE(prevWBS,".","`",1))))+1,VALUE(MID(prevWBS,FIND("`",SUBSTITUTE(prevWBS,".","`",1))+1,(FIND("`",SUBSTITUTE(prevWBS,".","`",2))-FIND("`",SUBSTITUTE(prevWBS,".","`",1))-1)))+1))) -> 1.42 | B50: FORM BC - SJ | C50: Jali | E50: =F47+2 -> 46088 | F50: =IF(ISBLANK(E50)," - ",IF(G50=0,E50,E50+G50-1)) -> 46091 | G50: 4 | H50: 0 | I50: =IF(OR(F50=0,E50=0)," - ",NETWORKDAYS(E50,F50)) -> 2
A51: =IF(ISERROR(VALUE(SUBSTITUTE(prevWBS,".",""))),"0.1",IF(ISERROR(FIND("`",SUBSTITUTE(prevWBS,".","`",1))),prevWBS&".1",LEFT(prevWBS,FIND("`",SUBSTITUTE(prevWBS,".","`",1)))&IF(ISERROR(FIND("`",SUBSTITUTE(prevWBS,".","`",2))),VALUE(RIGHT(prevWBS,LEN(prevWBS)-FIND("`",SUBSTITUTE(prevWBS,".","`",1))))+1,VALUE(MID(prevWBS,FIND("`",SUBSTITUTE(prevWBS,".","`",1))+1,(FIND("`",SUBSTITUTE(prevWBS,".","`",2))-FIND("`",SUBSTITUTE(prevWBS,".","`",1))-1)))+1))) -> 1.43 | B51: REPORT COSTING | C51: Budi | E51: =F48+1 -> 46091 | F51: =IF(ISBLANK(E51)," - ",IF(G51=0,E51,E51+G51-1)) -> 46092 | G51: 2 | H51: 0 | I51: =IF(OR(F51=0,E51=0)," - ",NETWORKDAYS(E51,F51)) -> 2
A52: =IF(ISERROR(VALUE(SUBSTITUTE(prevWBS,".",""))),"0.1",IF(ISERROR(FIND("`",SUBSTITUTE(prevWBS,".","`",1))),prevWBS&".1",LEFT(prevWBS,FIND("`",SUBSTITUTE(prevWBS,".","`",1)))&IF(ISERROR(FIND("`",SUBSTITUTE(prevWBS,".","`",2))),VALUE(RIGHT(prevWBS,LEN(prevWBS)-FIND("`",SUBSTITUTE(prevWBS,".","`",1))))+1,VALUE(MID(prevWBS,FIND("`",SUBSTITUTE(prevWBS,".","`",1))+1,(FIND("`",SUBSTITUTE(prevWBS,".","`",2))-FIND("`",SUBSTITUTE(prevWBS,".","`",1))-1)))+1))) -> 1.44 | B52: REPORT PEMARTAIAN | C52: Baim | E52: =F49+1 -> 46091 | F52: =IF(ISBLANK(E52)," - ",IF(G52=0,E52,E52+G52-1)) -> 46092 | G52: 2 | H52: 0 | I52: =IF(OR(F52=0,E52=0)," - ",NETWORKDAYS(E52,F52)) -> 2
A53: =IF(ISERROR(VALUE(SUBSTITUTE(prevWBS,".",""))),"0.1",IF(ISERROR(FIND("`",SUBSTITUTE(prevWBS,".","`",1))),prevWBS&".1",LEFT(prevWBS,FIND("`",SUBSTITUTE(prevWBS,".","`",1)))&IF(ISERROR(FIND("`",SUBSTITUTE(prevWBS,".","`",2))),VALUE(RIGHT(prevWBS,LEN(prevWBS)-FIND("`",SUBSTITUTE(prevWBS,".","`",1))))+1,VALUE(MID(prevWBS,FIND("`",SUBSTITUTE(prevWBS,".","`",1))+1,(FIND("`",SUBSTITUTE(prevWBS,".","`",2))-FIND("`",SUBSTITUTE(prevWBS,".","`",1))-1)))+1))) -> 1.45 | B53: FORM BC - INVOICE | C53: Jali | E53: =F50+1 -> 46092 | F53: =IF(ISBLANK(E53)," - ",IF(G53=0,E53,E53+G53-1)) -> 46093 | G53: 2 | H53: 0 | I53: =IF(OR(F53=0,E53=0)," - ",NETWORKDAYS(E53,F53)) -> 2
A54: =IF(ISERROR(VALUE(SUBSTITUTE(prevWBS,".",""))),"0.1",IF(ISERROR(FIND("`",SUBSTITUTE(prevWBS,".","`",1))),prevWBS&".1",LEFT(prevWBS,FIND("`",SUBSTITUTE(prevWBS,".","`",1)))&IF(ISERROR(FIND("`",SUBSTITUTE(prevWBS,".","`",2))),VALUE(RIGHT(prevWBS,LEN(prevWBS)-FIND("`",SUBSTITUTE(prevWBS,".","`",1))))+1,VALUE(MID(prevWBS,FIND("`",SUBSTITUTE(prevWBS,".","`",1))+1,(FIND("`",SUBSTITUTE(prevWBS,".","`",2))-FIND("`",SUBSTITUTE(prevWBS,".","`",1))-1)))+1))) -> 1.46 | B54: REPORT RESERVASI | C54: Budi | E54: =F51+1 -> 46093 | F54: =IF(ISBLANK(E54)," - ",IF(G54=0,E54,E54+G54-1)) -> 46094 | G54: 2 | H54: 0 | I54: =IF(OR(F54=0,E54=0)," - ",NETWORKDAYS(E54,F54)) -> 2
A55: =IF(ISERROR(VALUE(SUBSTITUTE(prevWBS,".",""))),"0.1",IF(ISERROR(FIND("`",SUBSTITUTE(prevWBS,".","`",1))),prevWBS&".1",LEFT(prevWBS,FIND("`",SUBSTITUTE(prevWBS,".","`",1)))&IF(ISERROR(FIND("`",SUBSTITUTE(prevWBS,".","`",2))),VALUE(RIGHT(prevWBS,LEN(prevWBS)-FIND("`",SUBSTITUTE(prevWBS,".","`",1))))+1,VALUE(MID(prevWBS,FIND("`",SUBSTITUTE(prevWBS,".","`",1))+1,(FIND("`",SUBSTITUTE(prevWBS,".","`",2))-FIND("`",SUBSTITUTE(prevWBS,".","`",1))-1)))+1))) -> 1.47 | B55: REPORT RESUME KODE PARTAI | C55: Baim | E55: =F52+1 -> 46093 | F55: =IF(ISBLANK(E55)," - ",IF(G55=0,E55,E55+G55-1)) -> 46094 | G55: 2 | H55: 0 | I55: =IF(OR(F55=0,E55=0)," - ",NETWORKDAYS(E55,F55)) -> 2
A56: =IF(ISERROR(VALUE(SUBSTITUTE(prevWBS,".",""))),"0.1",IF(ISERROR(FIND("`",SUBSTITUTE(prevWBS,".","`",1))),prevWBS&".1",LEFT(prevWBS,FIND("`",SUBSTITUTE(prevWBS,".","`",1)))&IF(ISERROR(FIND("`",SUBSTITUTE(prevWBS,".","`",2))),VALUE(RIGHT(prevWBS,LEN(prevWBS)-FIND("`",SUBSTITUTE(prevWBS,".","`",1))))+1,VALUE(MID(prevWBS,FIND("`",SUBSTITUTE(prevWBS,".","`",1))+1,(FIND("`",SUBSTITUTE(prevWBS,".","`",2))-FIND("`",SUBSTITUTE(prevWBS,".","`",1))-1)))+1))) -> 1.48 | B56: FORM BC - STOCK GUDANG | C56: Jali | E56: =F53+1 -> 46094 | F56: =IF(ISBLANK(E56)," - ",IF(G56=0,E56,E56+G56-1)) -> 46097 | G56: 4 | H56: 0 | I56: =IF(OR(F56=0,E56=0)," - ",NETWORKDAYS(E56,F56)) -> 2
A57: =IF(ISERROR(VALUE(SUBSTITUTE(prevWBS,".",""))),"0.1",IF(ISERROR(FIND("`",SUBSTITUTE(prevWBS,".","`",1))),prevWBS&".1",LEFT(prevWBS,FIND("`",SUBSTITUTE(prevWBS,".","`",1)))&IF(ISERROR(FIND("`",SUBSTITUTE(prevWBS,".","`",2))),VALUE(RIGHT(prevWBS,LEN(prevWBS)-FIND("`",SUBSTITUTE(prevWBS,".","`",1))))+1,VALUE(MID(prevWBS,FIND("`",SUBSTITUTE(prevWBS,".","`",1))+1,(FIND("`",SUBSTITUTE(prevWBS,".","`",2))-FIND("`",SUBSTITUTE(prevWBS,".","`",1))-1)))+1))) -> 1.49 | B57: STK BLANK GD. PACKING | C57: Budi | E57: =F54+1 -> 46095 | F57: =IF(ISBLANK(E57)," - ",IF(G57=0,E57,E57+G57-1)) -> 46098 | G57: 4 | H57: 0 | I57: =IF(OR(F57=0,E57=0)," - ",NETWORKDAYS(E57,F57)) -> 2
A58: =IF(ISERROR(VALUE(SUBSTITUTE(prevWBS,".",""))),"0.1",IF(ISERROR(FIND("`",SUBSTITUTE(prevWBS,".","`",1))),prevWBS&".1",LEFT(prevWBS,FIND("`",SUBSTITUTE(prevWBS,".","`",1)))&IF(ISERROR(FIND("`",SUBSTITUTE(prevWBS,".","`",2))),VALUE(RIGHT(prevWBS,LEN(prevWBS)-FIND("`",SUBSTITUTE(prevWBS,".","`",1))))+1,VALUE(MID(prevWBS,FIND("`",SUBSTITUTE(prevWBS,".","`",1))+1,(FIND("`",SUBSTITUTE(prevWBS,".","`",2))-FIND("`",SUBSTITUTE(prevWBS,".","`",1))-1)))+1))) -> 1.50 | B58: STOCK BALANCE KAIN GREY | C58: Baim | E58: =F55+1 -> 46095 | F58: =IF(ISBLANK(E58)," - ",IF(G58=0,E58,E58+G58-1)) -> 46098 | G58: 4 | H58: 0 | I58: =IF(OR(F58=0,E58=0)," - ",NETWORKDAYS(E58,F58)) -> 2
A59: =IF(ISERROR(VALUE(SUBSTITUTE(prevWBS,".",""))),"0.1",IF(ISERROR(FIND("`",SUBSTITUTE(prevWBS,".","`",1))),prevWBS&".1",LEFT(prevWBS,FIND("`",SUBSTITUTE(prevWBS,".","`",1)))&IF(ISERROR(FIND("`",SUBSTITUTE(prevWBS,".","`",2))),VALUE(RIGHT(prevWBS,LEN(prevWBS)-FIND("`",SUBSTITUTE(prevWBS,".","`",1))))+1,VALUE(MID(prevWBS,FIND("`",SUBSTITUTE(prevWBS,".","`",1))+1,(FIND("`",SUBSTITUTE(prevWBS,".","`",2))-FIND("`",SUBSTITUTE(prevWBS,".","`",1))-1)))+1))) -> 1.51 | B59: FORM BC - WIP | C59: Jali | E59: =F56+1 -> 46098 | F59: =IF(ISBLANK(E59)," - ",IF(G59=0,E59,E59+G59-1)) -> 46100 | G59: 3 | H59: 0 | I59: =IF(OR(F59=0,E59=0)," - ",NETWORKDAYS(E59,F59)) -> 3
A60: =IF(ISERROR(VALUE(SUBSTITUTE(prevWBS,".",""))),"0.1",IF(ISERROR(FIND("`",SUBSTITUTE(prevWBS,".","`",1))),prevWBS&".1",LEFT(prevWBS,FIND("`",SUBSTITUTE(prevWBS,".","`",1)))&IF(ISERROR(FIND("`",SUBSTITUTE(prevWBS,".","`",2))),VALUE(RIGHT(prevWBS,LEN(prevWBS)-FIND("`",SUBSTITUTE(prevWBS,".","`",1))))+1,VALUE(MID(prevWBS,FIND("`",SUBSTITUTE(prevWBS,".","`",1))+1,(FIND("`",SUBSTITUTE(prevWBS,".","`",2))-FIND("`",SUBSTITUTE(prevWBS,".","`",1))-1)))+1))) -> 1.52 | B60: FORM BC - MASTER MATERIAL | C60: Jali | E60: =F57+1 -> 46099 | F60: =IF(ISBLANK(E60)," - ",IF(G60=0,E60,E60+G60-1)) -> 46100 | G60: 2 | H60: 0 | I60: =IF(OR(F60=0,E60=0)," - ",NETWORKDAYS(E60,F60)) -> 2
A61: =IF(ISERROR(VALUE(SUBSTITUTE(prevWBS,".",""))),"0.1",IF(ISERROR(FIND("`",SUBSTITUTE(prevWBS,".","`",1))),prevWBS&".1",LEFT(prevWBS,FIND("`",SUBSTITUTE(prevWBS,".","`",1)))&IF(ISERROR(FIND("`",SUBSTITUTE(prevWBS,".","`",2))),VALUE(RIGHT(prevWBS,LEN(prevWBS)-FIND("`",SUBSTITUTE(prevWBS,".","`",1))))+1,VALUE(MID(prevWBS,FIND("`",SUBSTITUTE(prevWBS,".","`",1))+1,(FIND("`",SUBSTITUTE(prevWBS,".","`",2))-FIND("`",SUBSTITUTE(prevWBS,".","`",1))-1)))+1))) -> 1.53 | B61: STOCK GREY LEAD TIME PER GRADE | C61: Budi | E61: =F57+1 -> 46099 | F61: =IF(ISBLANK(E61)," - ",IF(G61=0,E61,E61+G61-1)) -> 46100 | G61: 2 | H61: 0 | I61: =IF(OR(F61=0,E61=0)," - ",NETWORKDAYS(E61,F61)) -> 2
A62: =IF(ISERROR(VALUE(SUBSTITUTE(prevWBS,".",""))),"0.1",IF(ISERROR(FIND("`",SUBSTITUTE(prevWBS,".","`",1))),prevWBS&".1",LEFT(prevWBS,FIND("`",SUBSTITUTE(prevWBS,".","`",1)))&IF(ISERROR(FIND("`",SUBSTITUTE(prevWBS,".","`",2))),VALUE(RIGHT(prevWBS,LEN(prevWBS)-FIND("`",SUBSTITUTE(prevWBS,".","`",1))))+1,VALUE(MID(prevWBS,FIND("`",SUBSTITUTE(prevWBS,".","`",1))+1,(FIND("`",SUBSTITUTE(prevWBS,".","`",2))-FIND("`",SUBSTITUTE(prevWBS,".","`",1))-1)))+1))) -> 1.54 | B62: STOCK KAIN GREY (GRADE) | C62: Baim | E62: =F58+1 -> 46099 | F62: =IF(ISBLANK(E62)," - ",IF(G62=0,E62,E62+G62-1)) -> 46100 | G62: 2 | H62: 0 | I62: =IF(OR(F62=0,E62=0)," - ",NETWORKDAYS(E62,F62)) -> 2
A63: =IF(ISERROR(VALUE(SUBSTITUTE(prevWBS,".",""))),"0.1",IF(ISERROR(FIND("`",SUBSTITUTE(prevWBS,".","`",1))),prevWBS&".1",LEFT(prevWBS,FIND("`",SUBSTITUTE(prevWBS,".","`",1)))&IF(ISERROR(FIND("`",SUBSTITUTE(prevWBS,".","`",2))),VALUE(RIGHT(prevWBS,LEN(prevWBS)-FIND("`",SUBSTITUTE(prevWBS,".","`",1))))+1,VALUE(MID(prevWBS,FIND("`",SUBSTITUTE(prevWBS,".","`",1))+1,(FIND("`",SUBSTITUTE(prevWBS,".","`",2))-FIND("`",SUBSTITUTE(prevWBS,".","`",1))-1)))+1))) -> 1.55 | B63: FORM BC - MASTER MATERIAL | C63: Jali | E63: =F60+9 -> 46109 | F63: =IF(ISBLANK(E63)," - ",IF(G63=0,E63,E63+G63-1)) -> 46112 | G63: 4 | H63: 0 | I63: =IF(OR(F63=0,E63=0)," - ",NETWORKDAYS(E63,F63)) -> 2
A64: =IF(ISERROR(VALUE(SUBSTITUTE(prevWBS,".",""))),"0.1",IF(ISERROR(FIND("`",SUBSTITUTE(prevWBS,".","`",1))),prevWBS&".1",LEFT(prevWBS,FIND("`",SUBSTITUTE(prevWBS,".","`",1)))&IF(ISERROR(FIND("`",SUBSTITUTE(prevWBS,".","`",2))),VALUE(RIGHT(prevWBS,LEN(prevWBS)-FIND("`",SUBSTITUTE(prevWBS,".","`",1))))+1,VALUE(MID(prevWBS,FIND("`",SUBSTITUTE(prevWBS,".","`",1))+1,(FIND("`",SUBSTITUTE(prevWBS,".","`",2))-FIND("`",SUBSTITUTE(prevWBS,".","`",1))-1)))+1))) -> 1.56 | B64: STOCK KAIN GREY (LW 22) | C64: Budi | E64: =F61+9 -> 46109 | F64: =IF(ISBLANK(E64)," - ",IF(G64=0,E64,E64+G64-1)) -> 46112 | G64: 4 | H64: 0 | I64: =IF(OR(F64=0,E64=0)," - ",NETWORKDAYS(E64,F64)) -> 2
A65: =IF(ISERROR(VALUE(SUBSTITUTE(prevWBS,".",""))),"0.1",IF(ISERROR(FIND("`",SUBSTITUTE(prevWBS,".","`",1))),prevWBS&".1",LEFT(prevWBS,FIND("`",SUBSTITUTE(prevWBS,".","`",1)))&IF(ISERROR(FIND("`",SUBSTITUTE(prevWBS,".","`",2))),VALUE(RIGHT(prevWBS,LEN(prevWBS)-FIND("`",SUBSTITUTE(prevWBS,".","`",1))))+1,VALUE(MID(prevWBS,FIND("`",SUBSTITUTE(prevWBS,".","`",1))+1,(FIND("`",SUBSTITUTE(prevWBS,".","`",2))-FIND("`",SUBSTITUTE(prevWBS,".","`",1))-1)))+1))) -> 1.57 | B65: STOCK KAIN PASIF (ALL AREA) | C65: Baim | E65: =F62+9 -> 46109 | F65: =IF(ISBLANK(E65)," - ",IF(G65=0,E65,E65+G65-1)) -> 46112 | G65: 4 | H65: 0 | I65: =IF(OR(F65=0,E65=0)," - ",NETWORKDAYS(E65,F65)) -> 2
A66: =IF(ISERROR(VALUE(SUBSTITUTE(prevWBS,".",""))),"0.1",IF(ISERROR(FIND("`",SUBSTITUTE(prevWBS,".","`",1))),prevWBS&".1",LEFT(prevWBS,FIND("`",SUBSTITUTE(prevWBS,".","`",1)))&IF(ISERROR(FIND("`",SUBSTITUTE(prevWBS,".","`",2))),VALUE(RIGHT(prevWBS,LEN(prevWBS)-FIND("`",SUBSTITUTE(prevWBS,".","`",1))))+1,VALUE(MID(prevWBS,FIND("`",SUBSTITUTE(prevWBS,".","`",1))+1,(FIND("`",SUBSTITUTE(prevWBS,".","`",2))-FIND("`",SUBSTITUTE(prevWBS,".","`",1))-1)))+1))) -> 1.58 | B66: FORM BC - MASTER VENDOR | C66: Jali | E66: =F63+1 -> 46113 | F66: =IF(ISBLANK(E66)," - ",IF(G66=0,E66,E66+G66-1)) -> 46116 | G66: 4 | H66: 0 | I66: =IF(OR(F66=0,E66=0)," - ",NETWORKDAYS(E66,F66)) -> 3
A67: =IF(ISERROR(VALUE(SUBSTITUTE(prevWBS,".",""))),"0.1",IF(ISERROR(FIND("`",SUBSTITUTE(prevWBS,".","`",1))),prevWBS&".1",LEFT(prevWBS,FIND("`",SUBSTITUTE(prevWBS,".","`",1)))&IF(ISERROR(FIND("`",SUBSTITUTE(prevWBS,".","`",2))),VALUE(RIGHT(prevWBS,LEN(prevWBS)-FIND("`",SUBSTITUTE(prevWBS,".","`",1))))+1,VALUE(MID(prevWBS,FIND("`",SUBSTITUTE(prevWBS,".","`",1))+1,(FIND("`",SUBSTITUTE(prevWBS,".","`",2))-FIND("`",SUBSTITUTE(prevWBS,".","`",1))-1)))+1))) -> 1.59 | B67: STOCK LEADTIME | C67: Budi | E67: =F64+1 -> 46113 | F67: =IF(ISBLANK(E67)," - ",IF(G67=0,E67,E67+G67-1)) -> 46114 | G67: 2 | H67: 0 | I67: =IF(OR(F67=0,E67=0)," - ",NETWORKDAYS(E67,F67)) -> 2
A68: =IF(ISERROR(VALUE(SUBSTITUTE(prevWBS,".",""))),"0.1",IF(ISERROR(FIND("`",SUBSTITUTE(prevWBS,".","`",1))),prevWBS&".1",LEFT(prevWBS,FIND("`",SUBSTITUTE(prevWBS,".","`",1)))&IF(ISERROR(FIND("`",SUBSTITUTE(prevWBS,".","`",2))),VALUE(RIGHT(prevWBS,LEN(prevWBS)-FIND("`",SUBSTITUTE(prevWBS,".","`",1))))+1,VALUE(MID(prevWBS,FIND("`",SUBSTITUTE(prevWBS,".","`",1))+1,(FIND("`",SUBSTITUTE(prevWBS,".","`",2))-FIND("`",SUBSTITUTE(prevWBS,".","`",1))-1)))+1))) -> 1.60 | B68: STOCK PER BARCODE | C68: Baim/Jali | E68: =F65+1 -> 46113 | F68: =IF(ISBLANK(E68)," - ",IF(G68=0,E68,E68+G68-1)) -> 46114 | G68: 2 | H68: 0 | I68: =IF(OR(F68=0,E68=0)," - ",NETWORKDAYS(E68,F68)) -> 2
A69: =IF(ISERROR(VALUE(SUBSTITUTE(prevWBS,".",""))),"0.1",IF(ISERROR(FIND("`",SUBSTITUTE(prevWBS,".","`",1))),prevWBS&".1",LEFT(prevWBS,FIND("`",SUBSTITUTE(prevWBS,".","`",1)))&IF(ISERROR(FIND("`",SUBSTITUTE(prevWBS,".","`",2))),VALUE(RIGHT(prevWBS,LEN(prevWBS)-FIND("`",SUBSTITUTE(prevWBS,".","`",1))))+1,VALUE(MID(prevWBS,FIND("`",SUBSTITUTE(prevWBS,".","`",1))+1,(FIND("`",SUBSTITUTE(prevWBS,".","`",2))-FIND("`",SUBSTITUTE(prevWBS,".","`",1))-1)))+1))) -> 1.61 | B69: FORM BC - UPDATE DOK EXPORT | C69: Jali | E69: =F66+1 -> 46117 | F69: =IF(ISBLANK(E69)," - ",IF(G69=0,E69,E69+G69-1)) -> 46120 | G69: 4 | H69: 0 | I69: =IF(OR(F69=0,E69=0)," - ",NETWORKDAYS(E69,F69)) -> 3
A70: =IF(ISERROR(VALUE(SUBSTITUTE(prevWBS,".",""))),"0.1",IF(ISERROR(FIND("`",SUBSTITUTE(prevWBS,".","`",1))),prevWBS&".1",LEFT(prevWBS,FIND("`",SUBSTITUTE(prevWBS,".","`",1)))&IF(ISERROR(FIND("`",SUBSTITUTE(prevWBS,".","`",2))),VALUE(RIGHT(prevWBS,LEN(prevWBS)-FIND("`",SUBSTITUTE(prevWBS,".","`",1))))+1,VALUE(MID(prevWBS,FIND("`",SUBSTITUTE(prevWBS,".","`",1))+1,(FIND("`",SUBSTITUTE(prevWBS,".","`",2))-FIND("`",SUBSTITUTE(prevWBS,".","`",1))-1)))+1))) -> 1.62 | B70: MOVING HISTORY - GUDANG GREY | C70: Budi | E70: =F67+1 -> 46115 | F70: =IF(ISBLANK(E70)," - ",IF(G70=0,E70,E70+G70-1)) -> 46118 | G70: 4 | H70: 0 | I70: =IF(OR(F70=0,E70=0)," - ",NETWORKDAYS(E70,F70)) -> 2
